Workbook

Sheet INPUT
D2: eenheid | E2: INVULLEN:
A3: SCENARIO 1 (alleen BVO is bekend) | C3: BVO | F3: <<ALTIJD INVULLEN
A5: OF
A7: SCENARIO 2 (meer hoeveelheden bekend) | C7: Bruto inhoud | D7: m3
C8: Bebouwd oppervlak | D8: m2
C9: Bruto gevel oppervlak | D9: m2
C10: Gevelopeningen | D10: m2
C11: Bruto dak oppervlak | D11: m2
C12: Dakopeningen | D12: m2
C13: Bruto binnenwandoppervlak | D13: m2
C14: Binnenwandopeningen | D14: m2
C15: Bruto terrein oppervlak | D15: m2
A18: KEUZES (VOOR BEIDE SCENARIO'S) | E18: KEUZE:
C19: Voldoen aan NEN9120 | E19: nee
C20: BBL, A, B of C | E20: BBL
C21: BENG, Frisse scholen Engergie klasse A,B of C, ENG of 0 op de meter | E21: BENG
C22: Aandeel biobased hergebruikt of gerecycled | E22: 15%
C23: Losmaakbaarheidsindex | E23: 30%
C24: Subbemetering | E24: nee
C25: Afvalwater hergebruiksysteem | E25: nee
C26: Grijswatersysteem | E26: nee
C27: Groendak | E27: nee
C28: Waterretentie systeem | E28: nee
C29: Extra beveiligingsmaatregelen | E29: nee
C30: Toegangscontrolesysteem | E30: nee
... C33: Slim gebouw | E33: nee
A36: VERDELING FUNCTIES | C36: School | E36: =Elementclusters!Q2 -> 1
C37: Kinderdagopvang | E37: 0
C38: Gymzaal | E38: 0
C39: Totaal (100%) | E39: =SUM(E36:E38) -> 1 | F39: =IF(E39<100%,"CONTROLEER INGEVULDE WAARDEN",IF(E39>100%,"CONTROLEER INGEVULDE WAARDEN",""))

Sheet Kenmerken
A1: Doelen en Uitgangspunten Generiek PvE | F1: POM
A2: Bovenliggend object naam | B2: Objectnaam | C2: Kenmerknaam | D2: Waarde | E2: Eenheid | F2: Parameter voor model? | G2: Zo ja welke fase? | H2: Hoe? | I2: Parameter Financieel | J2: Keuze velden | K2: Beoordelingskader | L2: Hoe | M2: Fase | N2: Wanneer
A3: Een betere school | B3: Kenmerken locatie | C3: Bouwhoogte | D3: 12 | E3: m | F3: Ja | G3: Gebied | H3: Uit Omgevingsplan of in te voeren | I3: nee | K3: Randvoorwaarde voor POM | L3: In ontwerpgeneratie | M3: gebouw
C4: Bebouwingspercentage | D4: 50 | E4: % | F4: ja | G4: Gebied | H4: Uit Omgevingsplan of in te voeren | I4: nee | K4: Randvoorwaarde voor POM | L4: In gebiedsuitgangspunten | M4: Gebied
C5: Eventuele ontheffingen/afwijkingen | D5: n.v.t. | F5: ja | G5: Gebied | H5: Uit Omgevingsplan of in te voeren | I5: nee | K5: Randvoorwaarde voor POM | L5: In gebiedsuitgangspunten | M5: Gebied
C6: Bijzondere aandachtspunten | D6: n.v.t. | F6: ja | G6: Gebied | H6: Uit Omgevingsplan of in te voeren | I6: nee | K6: Randvoorwaarde voor POM | L6: In gebiedsuitgangspunten | M6: Gebied
C7: Verkeerssituatie | D7: De verkeersontsluiting van het Integraal Kindcentrum is gericht op langzaam verkeer. De locatie is primair bereikbaar te voet en per fiets. Autoverkeer wordt zoveel mogelijk beperkt en gescheiden van loop- en fietsroutes van kinderen. De verkeerssituatie is ingericht op veilige breng- en haalmomenten binnen een woonomgeving. | F7: nee | I7: nee | K7: Handmatig door gebruiker | L7: Sliderkeuze 1-5 : 1 Voldoet helemaal niet 2Voldoet in grote mate niet 3 Voldoet in beperte mate 4 voldoet in grote mate 5 Voldoet voledig | M7: Afgewogen besluit
C8: Parkeren motorvoertuigen | D8: Parkeren voor motorvoertuigen is beperkt en functioneel van aard en bedoeld voor personeel, leveranciers en incidenteel bezoek. Parkeren vindt plaats op of nabij de kavel, passend binnen het stedenbouwkundig kader en geldende parkeernormen. Uitgangspunt is het voorkomen van verkeersonveiligheid en overlast voor de omgeving. | F8: ja | G8: Gebied | H8: In te tekenen | I8: nee | K8: Handmatig door gebruiker | L8: Sliderkeuze 1-5 | M8: Afgewogen besluit
C9: Stalling fietsen/scooters | D9: Voor leerlingen en medewerkers wordt voorzien in voldoende stallingsmogelijkheden voor fietsen en scooters. De stallingen zijn goed bereikbaar, overzichtelijk en veilig gesitueerd in relatie tot de entrees van het gebouw. Fietsstallingen vormen een integraal onderdeel van de verkeersafwikkeling rondom het IKC | F9: ja | G9: Gebied | H9: In te tekenen | I9: nee | K9: Handmatig door gebruiker | L9: Sliderkeuze 1-5 | M9: Afgewogen besluit
C10: Functies buitenruimte | D10: De buitenruimte maakt functioneel onderdeel uit van het Integraal Kindcentrum en is primair bedoeld voor gebruik door leerlingen van de basisschool en kinderen van de voorschoolse educatie. De buitenruimte wordt ingericht als speel- en verblijfsruimte die het onderwijs en de ontwikkeling van kinderen ondersteunt. De buitenruimte voor de voorschoolse educatie is afgebakend en niet openbaar toegankelijk. De buitenruimte van de basisschool is in principe niet publiek toegankelijk en wordt gebruikt tijdens schooltijden en onder toezicht. Buiten schooltijden kan medegebruik plaatsvinden indien dit organisatorisch en veilig kan worden ingericht. De buitenruimte is gericht op spelen, bewegen en verblijven en vormt een duidelijke overgang tussen gebouw en omgeving. | F10: ja | G10: Gebied | H10: In te tekenen | I10: nee | K10: Handmatig door gebruiker | L10: Sliderkeuze 1-5 | M10: Afgewogen besluit
B11: Wet- en regelgeving | C11: Wet- en regelgeving | D11: Het project moet voldoen aan alle relevante vigerende wet- en regelgeving (o.a. Bbl, Arbowetgeving), waaronder, maar niet beperkt tot, de wet- en regelgeving die genoemd wordt bij de gedefinieerde eisen. Bij verwijzingen naar externe normen (bijv. NEN -normen) moet worden uitgegaan van de meest recente versie en alle delen van de norm tenzij anders aangegeven. | F11: nee | I11: nee | K11: Niet
A12: Een functionele school | B12: Kenmerken school | C12: Aantal leerlingen | D12: 380 | E12: Leerlingen | F12: ja | G12: Start | H12: IN te voeren | I12: nee | K12: Randvoorwaarde voor POM | L12: In ontwerpgeneratie | M12: gebouw
C13: Aantal onderwijsmedewerkers | D13: 18 | E13: Docenten | F13: ja | G13: Start | H13: IN te voeren | I13: nee | K13: Randvoorwaarde voor POM | L13: In ontwerpgeneratie | M13: gebouw
C14: Aantal stafmedewerkers | D14: 4 | E14: Stafmedewerkers | F14: ja | G14: Start | H14: IN te voeren | I14: nee | K14: Randvoorwaarde voor POM | L14: In ontwerpgeneratie | M14: gebouw
C15: Onderwijstype | D15: Integraal Kindcentrum (IKC) met primair onderwijs en voorschoolse educatie. Binnen het gebouw is ruimte voor onderwijs aan kinderen van 4 tot 12 jaar en voorschoolse educatie voor kinderen van 2 tot 4 jaar. Eventueel medegebruik voor buitenschoolse opvang vindt plaats binnen de onderwijsruimten. | F15: nee | I15: nee | K15: Niet
C16: Identiteit/cultuur | D16: De school kenmerkt zich door een open en inclusieve cultuur, gericht op samenwerking, veiligheid en ontwikkeling. De huisvesting ondersteunt ontmoeting, overzicht en een prettige leer- en werkomgeving voor leerlingen en medewerkers. | F16: nee | I16: nee | K16: Niet
C17: Onderwijsvisie | D17: Het onderwijs is gericht op een evenwichtige ontwikkeling van kinderen, waarbij klassikale instructie wordt gecombineerd met zelfstandig werken en samenwerken. De leeromgeving faciliteert verschillende werkvormen en sluit aan bij de ontwikkelingsfase van leerlingen. | F17: nee | I17: nee | K17: Niet
C18: Missie | D18: De missie van de school is het bieden van kwalitatief goed primair onderwijs in een veilige en stimulerende omgeving, waarin leerlingen zich cognitief, sociaal en persoonlijk kunnen ontwikkelen. | F18: nee | I18: nee | K18: Niet
C19: Doelgroep | D19: De doelgroep bestaat uit kinderen van 2 tot 12 jaar uit de directe omgeving van de school. De school bedient een gemengde populatie leerlingen uit de wijk en biedt passend onderwijs binnen het reguliere primair onderwijs en voorschoolse educatie. | F19: nee | I19: nee | K19: Niet
C20: Structuur | D20: De school is georganiseerd volgens een onderbouw-, middenbouw- en bovenbouwstructuur, met een logische clustering van onderwijsruimten per bouw. Deze structuur ondersteunt overzicht, herkenbaarheid en efficiënt gebruik van ruimten. | F20: ja | G20: Start | H20: PvE-Tool | I20: nee | K20: Handmatig door gebruiker | L20: Sliderkeuze 1-5 | M20: Afgewogen besluit
C21: Aanvullende functies/gebruikers | D21: Naast het primair onderwijs en de voorschoolse educatie zijn er geen aanvullende externe gebouwgebruikers die beschikken over eigen, exclusieve ruimten binnen het gebouw. Eventuele buitenschoolse opvang en andere activiteiten maken gebruik van medegebruik van onderwijsruimten binnen vastgestelde tijden en afspraken. De gymzaal is een afzonderlijke functie en valt buiten het onderwijsdeel van het gebouw. | F21: ja | G21: Start | H21: PvE-Tool | I21: nee | K21: Handmatig door gebruiker | L21: Sliderkeuze 1-5 | M21: Afgewogen besluit
C22: Combinatiefuncties | D22: Buiten schooltijden kunnen de bestaande ruimten beperkt worden ingezet voor medegebruik, zoals buitenschoolse opvang en incidentele buurt- of wijkgerichte activiteiten. Dit betreft laagdrempelige activiteiten die passen binnen de onderwijsfunctie, zoals ontmoetingen, cursussen of kleinschalige bijeenkomsten. Het medegebruik vindt plaats binnen vastgestelde tijden en afspraken, zonder dat hiervoor aanvullende ruimten of aanpassingen aan het programma nodig zijn. | F22: nee | I22: nee | K22: Handmatig door gebruiker | L22: Sliderkeuze 1-5 | M22: Afgewogen besluit
B23: Huisvestingsconcept | C23: Huisvestingsconcept algemeen | D23: Het beoogde huisvestingsconcept is gericht op een functionele, overzichtelijke en flexibele leeromgeving die verschillende onderwijsactiviteiten ondersteunt. De huisvesting faciliteert zowel klassikale instructie als zelfstandig werken en samenwerken in kleinere groepen. Ruimten zijn zodanig georganiseerd dat ontmoeting en interactie tussen leerlingen en medewerkers mogelijk is, zonder dat dit ten koste gaat van rust en concentratie. De achterliggende doelstelling is het creëren van een toekomstbestendig gebouw dat meebeweegt met veranderende onderwijsbehoeften, efficiënt ruimtegebruik mogelijk maakt en bijdraagt aan een prettige en veilige leer- en werkomgeving voor alle gebruikers. | F23: nee | I23: nee | K23: Handmatig door gebruiker | L23: Sliderkeuze 1-5 | M23: Afgewogen besluit
C24: Ruimtelijke indeling | D24: De ruimtelijke indeling van het gebouw is gebaseerd op een heldere zonering en logische clustering van functies. Onderwijsruimten zijn geclusterd per bouw (onderbouw, middenbouw en bovenbouw), waardoor overzicht en herkenbaarheid voor leerlingen en medewerkers ontstaat. Ondersteunende functies en gedeelde voorzieningen zijn centraal gepositioneerd en goed bereikbaar vanuit de onderwijsclusters. De ruimten voor voorschoolse educatie vormen een eigen, duidelijk herkenbare zone binnen het gebouw, met een directe relatie met de buitenruimte. Functies met een mogelijk intensiever gebruik, zoals de gymzaal, zijn ruimtelijk zodanig gescheiden of gepositioneerd dat verstoring van het onderwijs wordt beperkt. | F24: Ja | G24: Start | H24: PvE-Tool | I24: nee | K24: Handmatig door gebruiker | L24: Sliderkeuze 1-5 | M24: Afgewogen besluit
C25: Logistiek | D25: De logistiek van het gebouw is gericht op overzicht en veiligheid. Er wordt uitgegaan van een duidelijke hoofdentree voor het primair onderwijs, met een logische en overzichtelijke routing naar de onderwijsruimten. Voor de voorschoolse educatie wordt voorzien in een eigen entree of een duidelijk gescheiden toegang, zodat verschillende gebruikersgroepen op een veilige en herkenbare wijze het gebouw kunnen betreden en verlaten. Bezoekers en medewerkers maken gebruik van de hoofdentree, waarbij interne routes zodanig zijn ingericht dat kruisende stromen zoveel mogelijk worden beperkt. Deze opzet draagt bij aan rust, veiligheid en efficiënt gebruik van het gebouw. | F25: nee | I25: nee | K25: Handmatig door gebruiker | L25: Sliderkeuze 1-5 | M25: Afgewogen besluit
C26: Gemeenschappelijke ruimtes | D26: Binnen het gebouw zijn enkele functies en ruimten bedoeld voor gedeeld gebruik door de verschillende gebouwgebruikers. Het betreft met name een centrale hal of ontmoetingsruimte die fungeert als entreegebied en informeel verblijfsgebied. Daarnaast kunnen ondersteunende ruimten, zoals een leer- of werkgebied, een kleine bibliotheekvoorziening of multifunctionele ruimte, flexibel worden ingezet door zowel onderwijs, voorschoolse educatie als eventueel medegebruik buiten schooltijden. Het gedeeld gebruik van deze ruimten draagt bij aan efficiënt ruimtegebruik en ontmoeting, zonder dat dit leidt tot extra ruimtevraag. | F26: nee | I26: nee | K26: Handmatig door gebruiker | L26: Sliderkeuze 1-5 | M26: Afgewogen besluit
C27: Typologie onderwijsruimten | D27: De onderwijsruimten zijn opgezet volgens een gedifferentieerde ruimtelijke typologie die aansluit op verschillende werkvormen en groepsgroottes. Uitgangspunt is een combinatie van overwegend gesloten groepsruimten voor klassikale instructie, aangevuld met aanvullende ruimten voor zelfstandig werken en samenwerken in kleinere groepen. De groepsruimten bieden plaats aan reguliere groepsgroottes en zijn zodanig van omvang dat flexibel gebruik mogelijk is. Aanvullende ruimten in de nabijheid van de groepsruimten ondersteunen differentiatie in het onderwijs, zoals werken in kleine groepen of individueel werken. De mate van open- en geslotenheid is afgestemd op een balans tussen rust, overzicht en interactie. De inrichting van de onderwijsruimten is flexibel en aanpasbaar, zodat verschillende onderwijsactiviteiten en toekomstige veranderingen in het onderwijsprogramma kunnen worden gefaciliteerd. | F27: ja | G27: Start | H27: PvE-Tool | I27: nee | K27: Handmatig door gebruiker | L27: Sliderkeuze 1-5 | M27: Afgewogen besluit
A28: Een aantrekkelijke school | B28: Uitstraling exterieur | C28: Beschrijving | D28: eigentijds en herkenbaar, passend binnen de schaal van de woonomgeving, uitnodigend en kindvriendelijk, overzichtelijk en transparant, duurzaam en toekomstbestendig, zorgvuldig ingepast in de omgeving | F28: nee | I28: nee | K28: Handmatig door gebruiker | L28: Sliderkeuze 1-5 | M28: Afgewogen besluit
B29: Uitstraling interieur | C29: Beschrijving | D29: licht en overzichtelijk, rustig en veilig, flexibel en aanpasbaar, warm en uitnodigend, functioneel en duurzaam, stimulerend voor leren en ontmoeten | F29: nee | I29: nee | K29: Niet
B30: Uitstraling buitenruimten | C30: Beschrijving | D30: groen en kindvriendelijk, veilig en overzichtelijk, uitnodigend tot spelen en bewegen, robuust en onderhoudsvriendelijk, passend bij de woonomgeving, functioneel en duurzaam | F30: nee | I30: nee | K30: Handmatig door gebruiker | L30: Sliderkeuze 1-5 | M30: Afgewogen besluit
A31: Een inclusieve school | B31: Een inclusieve school | C31: Relevante norm(en) | D31: NEN 9120 | F31: nee | I31: ja | J31: Voldoen aan NEN9120 JA of Nee | K31: Randvoorwaarde voor POM
B32: Ruimtelijke aspecten | C32: Navigatie ('wayfinding') | D32: Gebruikers moeten eenvoudig hun weg kunnen vinden binnen en buiten het gebouw, met een minimale noodzaak voor bewegwijzering. Denk aan natuurlijke looproutes, zichtlijnen en herkenningspunten. Bewegwijzering moet duidelijk zijn voor alle gebruikers, ongeacht leeftijd of fysieke mogelijkheden. | F32: nee | I32: nee | K32: Niet
C33: Hoogteverschillen | D33: Alle verdiepingen zelfstandig bereikbaar zijn voor alle gebruikers, ongeacht leeftijd of fysieke mogelijkheden. Op de verdiepingen zelf moeten hoogteverschillen en drempels vermeden worden. Waar hoogteverschillen niet te vermijden zijn, moet een vaste opstap, lift, trap en/of hellingbaan worden toegepast. | F33: nee | I33: nee
C34: Ruimte voor gebruik mobiliteitshulpmiddelen | D34: Het gebouw moet in verblijfsruimtes en de routes daar naartoe voorzien in voldoende ruimte voor het gebruik van mobiliteitshulpmiddelen. Denk aan doorgangsbreedtes, passeerruimte in gangen, draaicirkels bij trappen, manoeuvreerruimte bij deuren, en bedieningsruimte bij ramen, kasten, zonwering en andere bedienbare gebouwelementen. | F34: nee | I34: nee | K34: Automatisch door POM | L34: Toetsing van gangbreedtes en en draaijcirkels | M34: Gebouw
C35: Ruimten voor ondersteuning/behandeling | D35: Het gebouw moet voorzien in behandel- en/of spreekruimte(n) waar leerlingen kunnen afspreken met zorg- of ondersteuningspersoneel (bijv. maatschappelijk werkers, onderwijspsychologen, logopedisten). Kan gaan om specifieke ruimten, maar ook dubbel ruimtegebruik is mogelijk. Comfort, privacy en rust zijn belangrijke kwaliteiten. | F35: ja | G35: Start | H35: PvE-Tool | I35: nee | K35: Randvoorwaarde voor POM | L35: Ruimtes zijn onderdeel van de ruimtestaat | M35: Gebouw
C36: Ruimte voor opslag hulpmiddelen | D36: Het gebouw moet beschikken over opslagruimte voor hulpmiddelen die door leerlingen met een beperking worden gebruikt (bijv. rolstoelen, loophulpmiddelen, aangepaste stoelen en tafels, brailleleesapparatuur). Opslag moet gepositioneerd zijn in de directe omgeving van de onderwijsruimten waar de hulpmiddelen worden gebruikt. | F36: ja | G36: Start | H36: PvE-Tool | I36: nee | K36: Randvoorwaarde voor POM | L36: Ruimtes zijn onderdeel van de ruimtestaat | M36: Gebouw
C37: Diversiteit in plekken | D37: Voorzie in verschillende soorten ruimtes die aansluiten op uiteenlopende voorkeuren en behoeftes. Denk niet alleen aan klassieke onderwijsruimtes, maar ook stilteplekken voor geconcentreerd werken, groepsruimten voor samenwerking en informele leeromgevingen waar leerlingen zich op hun gemak voelen. | F37: ja | G37: Start | H37: PvE-Tool | I37: nee | K37: Randvoorwaarde voor POM | L37: Ruimtes zijn onderdeel van de ruimtestaat | M37: Gebouw
B38: Technische aspecten | C38: Binnenklimaat | D38: Sommige gebruikers zijn gevoeliger voor geluid, licht, temperatuur en allergenen dan anderen. Vanuit dit perspectief is het belangrijk dat binnenklimaat in de school beter is dan wettelijk minimum (zie DP-13). | F38: nee | I38: nee | K38: Niet
C39: Aanpasbaarheid | D39: Verblijfsruimtes moeten flexibel in te richten zijn om aan te sluiten op de diverse behoeften van gebruikers. Aandachtspunten zijn het kunnen aanpassen van de inrichting en de aanpasbaarheid van binnenklimaat (te openen ramen, aanpassen verlichting, aanpassen verwarming) | F39: nee | I39: nee | K39: Niet
C40: Aansluitingen hulpmiddelen | D40: In de school moeten voldoende en goed gepositioneerde aansluitingen beschikbaar zijn voor het opladen en gebruiken van hulpmiddelen door leerlingen en medewerkers met een beperking. Denk aan stroompunten voor het opladen van elektrische rolstoelen, gehoorversterkende apparatuur of andere hulpmiddelen. | F40: nee | I40: nee | K40: Niet
C41: Bedieningsgemak | D41: Bedienbare elementen (o.a. zonwering, deuren, ramen, verlichting) moeten veilig en eenvoudig te bedienen zijn voor alle gebouwgebruikers, ongeacht leeftijd of fysieke mogelijkheden. Denk aan reikhoogtes, zichtbaarheid en bedienweerstand. Bij voorkeur zijn zware bouwdelen zoals brandwerende deuren automatisch of elektrisch te bedienen. | F41: nee | I41: nee | K41: Niet
B42: Belevingsaspecten | C42: Prikkelarme plekken | D42: De huisvesting moet een rustige uitstraling en een prettige akoestiek hebben zodat leerlingen met een verhoogde gevoeligheid voor prikkels zich beter kunnen concentreren. Er moet voorzien worden in speciale prikkelarme ruimten of plekken waar leerlingen zich kunnen terugtrekken. | F42: ja | G42: Start | H42: PvE-Tool | I42: nee | K42: Niet
C43: Intuïtieve 'leesbare' ruimten | D43: Het beoogde gebruik van een ruimte moet eenvoudig te begrijpen zijn. Leerlingen moeten intuïtief aanvoelen waarvoor een ruimte bedoeld is (bijv. een stilteruimte versus een ruimte voor sociale interactie). Denk aan gebruik kleuren, pictogrammen en inrichtingselementen. | F43: nee | I43: nee | K43: Niet
C44: Natuurlijke elementen | D44: Het ontwerp moet natuurlijke elementen integreren om welzijn en concentratie te bevorderen. Dit omvat (uit)zicht op groen, daglichttoetreding, beplanting binnen en buiten het gebouw en het gebruik van natuurlijke materialen. | F44: nee | I44: nee | K44: Niet
C45: Zichtlijnen | D45: In verblijfsruimten moeten er een visuele verbinding met buiten zijn. Er moet uitzicht zijn voor ieder type gebruiker (groot of klein, zittend, staand, liggend op een bed). Het gebouw moet voorzien worden van meerdere doorkijkjes op kijkhoogte van specifieke gebruikersgroep | F45: nee | I45: nee | K45: Niet
C46: Menselijke maat | D46: Het gebouw moet een menselijke maat hebben en gebruikers een gevoel van geborgenheid geven. Denk aan opdelen van open ruimten in kleinere, herkenbare zones, en het creëren van plekken met besloten karakter waar leerlingen zich veilig en comfortabel voelen. | F46: nee | I46: nee | K46: Niet
A47: Een gezonde school | B47: Binnenklimaat | C47: Geluid | D47: Klasse B (Goed) conform PvE Frisse scholen. Het akoestisch comfort in de onderwijsruimten is beter dan minimaal vereist conform Bbl. Spraak moet goed verstaanbaar zijn. Geluidsabsorberende materialen in plafonds en wanden moeten galm verminderen. Hinderlijk geluid van installaties, vanuit buiten, en van naastgelegen ruimten moet gedempt worden zodat leerlingen en docenten zich goed kunnen concentreren. Bij renovatie kan het zijn dat klasse B niet realiseerbaar is voor wat betreft eisen aan lucht- en contactgeluidsisolatie omdat aanpassingen aan bestaande vloeren en wanden te kostbaar zijn. In dat geval volstaat Klasse C (Voldoende). | F47: nee | I47: ja | J47: Klasse A, B of C | K47: Randvoorwaarde voor POM | L47: Absoltuut getal in €
C48: Temperatuur | D48: Klasse B (Goed) conform PvE Frisse scholen. Het thermisch comfort in de onderwijsruimten moet beter zijn dan minimaal vereist conform Bbl. Grote temperatuurwisselingen moeten beperkt worden door goede isolatie, effectieve zonwering en een efficiënte verwarmings- en koelstrategie. In de zomer moet het comfortabel blijven, met slechts incidentele uitschieters tijdens extreem warme dagen. | F48: nee | I48: ja | J48: Klasse A, B of C | K48: Randvoorwaarde voor POM | L48: Absoltuut getal in €
C49: Licht | D49: Klasse B (Goed) conform PvE Frisse scholen. Het visueel comfort in de onderwijsruimten moet beter zijn dan minimaal vereist conform Bbl, met een goede balans tussen dag- en kunstlicht. Ramen moeten uitzicht en natuurlijke lichtinval bieden zonder verblinding. Kunstverlichting moet gelijkmatig verdeeld zijn. Hinderlijke contrasten, flikkeringen, en reflecties moeten beperkt worden (zie ook REQ-63). Bij renovatie kan het zijn dat klasse B niet realiseerbaar is voor wat betreft eisen aan daglichttoetreding omdat aanpassingen aan de gevel kostbaar zijn en/of conflicteren met de ambitie om een energieneutraal gebouw te realiseren. In dat geval volstaat klasse C (Voldoende). Aandachtspunt vanuit NEN 9120 is dat er aandacht besteed aan overgangen van lichte naar donkere ruimten. Plotselinge veranderingen in de verlichtingssterkte, met name bij entrees/toegangen, moeten worden vermeden. | F49: nee | I49: ja | J49: Klasse A, B of C | K49: Randvoorwaarde voor POM | L49: Absoltuut getal in €
C50: Lucht | D50: Klasse B (Goed) conform PvE Frisse scholen. De luchtkwaliteit in de onderwijsruimten moet beter zijn dan minimaal vereist conform Bbl. Regelbare mechanische en natuurlijke ventilatie moeten zorgen voor de aanvoer van frisse lucht en de afvoer van vervuilde lucht. Verontreinigingen en CO₂-concentraties moeten beperkt blijven, ook bij intensief gebruik van klaslokalen. Zie ook REQ-108 voor eisen met betrekking luchtkwaliteit en materiaalgebruik. | F50: nee | I50: ja | J50: Klasse A, B of C | K50: Randvoorwaarde voor POM | L50: Absoltuut getal in €
C51: Kwaliteitsborging | D51: Klasse B (Goed) conform PvE Frisse scholen. Er wordt een oplevertoets uitgevoerd zodat kan worden vastgesteld of de gestelde binnenklimaateisen daadwerkelijk behaald worden. Zie hiervoor de Frisse scholen Toets voor de onderdelen lucht-temperatuur-licht-geluid. Bij oplevering wordt mondeling en schriftelijk een instructie gegeven over het juiste gebruik van de beïnvloedingsmogelijkheden en voorzieningen. | F51: nee | I51: nee | K51: Randvoorwaarde voor POM | L51: Absoltuut getal in €
C52: Comfort niet-onderwijsruimten | D52: Bovenstaande uitgangspunten gelden voor de onderwijsruimten in het gebouw. Vanuit het oogpunt van flexibiliteit is voor de kantoor(achtige) ruimten uitgegaan van een gelijk comfortniveau. Voor de overige ruimten zijn specifieke eisen geformuleerd. | F52: nee | I52: ja | J52: BBL, A, B of C | K52: Randvoorwaarde voor POM | L52: Absoltuut getal in €
B53: Stimuleren beweging | C53: Ruimten bewegingsonderwijs | D53: Er moet voldoende ruimte beschikbaar zijn voor bewegingsonderwijs, passend bij de leeftijdsgroepen en het onderwijsconcept. Dat kan gaan om een gymzaal (indien niet in nabijheid beschikbaar) of een multifunctionele speelruimte die geschikt is voor lessen lichamelijke opvoeding. | F53: ja | G53: Start | H53: PvE-Tool | I53: nee | K53: Randvoorwaarde voor POM | L53: Ruimtes zijn onderdeel van de ruimtestaat | M53: Gebouw
C54: Beweging door gebouw | D54: Het gebouwontwerp moet uitnodigen tot beweging en tegelijkertijd een veilige en toegankelijke verkeersstroom ondersteunen. Aandachtspunten zijn aantrekkelijke en goed zichtbare trappen die trapgebruik stimuleren en brede gangen zonder obstakels die vrije en veilige doorstroming mogelijk maken. | F54: nee | I54: nee | K54: Niet
C55: Beweging op leer/werkplek | D55: De inrichting moet een dynamische leer- en werkomgeving ondersteunen, zodat leerlingen op naar behoefte van plek of houding kunnen wisselen. Aandachtspunten zijn in hoogte verstelbare tafels en stoelen (voor zover onderdeel scope) en flexibele zithoeken die actief zitten en staand werken mogelijk maken. | F55: nee | I55: nee | K55: Niet
C56: Beweging in buitenruimtes | D56: De buitenruimte moet aantrekkelijk en functioneel worden ingericht om leerlingen te stimuleren om te bewegen en actief te spelen. Denk aan diverse speel- en sportvoorzieningen, uitdagende speelaanleidingen en gevarieerde ondergronden die uitnodigen tot rennen, springen en balspelen. | F56: nee | I56: nee | K56: Niet
A57: Een duurzame school | B57: Energiegebruik | C57: Energiezuinig gebouwontwerp | D57: Bouwkundige maatregelen moeten de energievraag maximaal beperken volgens de Trias Energetica. Aandachtspunten zijn een slimme oriëntatie van ruimtes ten opzichte van de zon, gebruik van daglicht, hoogwaardige isolatie, luchtdichtheid van gevels en het gebruik van natuurlijke ventilatie en thermische massa om behoefte aan actieve koeling te minimaliseren. | F57: nee | I57: ja | J57: BENG, Frisse scholen Engergie klasse A,B of C, ENG of 0 op de meter | K57: Randvoorwaarde voor POM | L57: Absoltuut getal in €
C58: Energiezuinigheid installaties | D58: Nieuwe installaties moeten energiezuinig zijn en bijdragen aan het beperken van de warmtevraag en de koellast. Dit betekent o.a. efficiënte verwarmings- en ventilatiesystemen (conform NEN-EN 16798), warmteterugwinning, vraaggestuurde regelingen, en energiezuinige verlichting. Keuzes voor de verwarmingsinstallatie moeten aansluiten bij de (toekomstige) warmtevisie van de wijk om desinvesteringen te voorkomen | F58: nee | I58: nee | K58: Randvoorwaarde voor POM | L58: Absoltuut getal in €
C59: Gebruik hernieuwbare energie | D59: De energievraag moet ingevuld kunnen worden door gebruik hernieuwbare energiebronnen. Aandachtspunten zijn inzet van zonnecellen, warmtepompen en lage temperatuurverwarming (LTV) in combinatie met bodem-, water- of luchtwarmte. | F59: nee | I59: nee | K59: Randvoorwaarde voor POM | L59: Absoltuut getal in €
C60: Energiemonitoring | D60: Het gebouw moet voorzien worden van een gebouwautomatiserings- en controlesysteem (GACS) om de prestatie en het energiegebruik van de technische installaties te monitoren, aan te sturen en te optimaliseren, conform NEN-EN-ISO 52120. Zie ook DP-31. | F60: nee | I60: nee | K60: Randvoorwaarde voor POM | L60: Absoltuut getal in €
C61: Regeltechniek | D61: De centrale warmteopwekking en andere installaties moeten zodanig in te regelen zijn dat er geen sprake is van onnodig energieverbruik. Door middel van bijv. kloktijden, overwerktimers en een weekend- en vakantieprogramma moet het mogelijk zijn de werking van installaties af te stemmen op de bezetting en het gebruik van het gebouw. | F61: nee | I61: nee | K61: Randvoorwaarde voor POM | L61: Absoltuut getal in €
C62: Kwaliteitsborging | D62: Klasse C (Voldoende): er moet een oplevertoets worden uitgevoerd waarbij gecontroleerd wordt dat de energiebesparende maatregelen daadwerkelijk zijn uitgevoerd. | F62: nee | I62: nee | K62: Niet
C63: Energielabel | D63: A+++++ | I63: nee | K63: Randvoorwaarde voor POM | L63: Absoltuut getal in €
C64: Primair fossiel energiegebruik | D64: 0 | E64: kWh/m2/jaar | F64: nee | I64: nee | K64: Randvoorwaarde voor POM | L64: Absoltuut getal in €
C65: Aandeel hernieuwbaar | D65: 100 | E65: % | F65: nee | I65: nee | K65: Randvoorwaarde voor POM | L65: Absoltuut getal in €
C66: Aandeel aardgas | D66: 0 | E66: % | F66: nee | I66: nee | K66: Niet
C67: Werkelijke Energie intensiteit indicator (WEii) | D67: 60 | E67: kWh/m2/jaar | F67: nee | I67: nee | K67: Randvoorwaarde voor POM | L67: Absoltuut getal in €
C68: Onderwerp van de innovatie | D68: Passiefbouw (leerlab 1) | F68: nee | I68: nee | K68: Automatisch door POM | L68: Meten hoveelheid zonbelaste geveloppervlak. Hoe hoger dit opvlak hoe lager de score | M68: Gebouw
C69: Scope van de innovatie | D69: Een geheel bouwdeel of element; de keuze hierin is productafhankelijk. | F69: nee | I69: nee | K69: Niet
C70: Ontwikkelstadium (TRL) | D70: Min. TRL 5 (validatie prototype), max. TRL 7 (prototype in operationele omgeving) | F70: nee | I70: nee | K70: Niet
B71: Materiaalgebruik | C71: Behoud en hergebruik | D71: Materialen van het bestaande gebouw moeten zoveel mogelijk behouden of binnen het project hergebruikt worden. Dit beperkt het gebruik van nieuwe materiaal en de noodzaak om verwijderd materiaal af te voeren en te verwerken. | F71: nee | I71: nee | K71: Randvoorwaarde voor POM | L71: Absoltuut getal in €
C72: CO~2~-uitstoot | D72: Nieuwe toe te passen materialen moeten een zo laag mogelijke materiaalgebonden CO~2~-uitstoot hebben, met name wat betreft emissies die gepaard gaan met de extractie, de verwerking, het transport van het materiaal. | F72: nee | I72: nee | K72: Randvoorwaarde voor POM | L72: Absoltuut getal in €
C73: Biobased | D73: Daar waar mogelijk moet er gebruik gemaakt worden van biobased materialen. Denk aan hout voor constructiedelen en vezelgewassen bij (na)isolatie, daarbij rekening houdend met de vochthuishouding in het gebouw. | F73: nee | I73: nee | K73: Randvoorwaarde voor POM | L73: Absoltuut getal in €
C74: Losmaakbaarheid | D74: Nieuw toegepaste bouwmaterialen moeten zoveel mogelijk 'losmaakbaar' zijn zodat deze aan het einde van de levensduur van het gebouw eenvoudig gedemonteerd en hergebruikt kunnen worden. | F74: nee | I74: nee | K74: Randvoorwaarde voor POM | L74: Absoltuut getal in €
C75: Gezondheid | D75: Toegepaste materialen mogen geen gezondheidsrisico's voor gebruikers met zich mee brengen. Er moet gebruik gemaakt worden van materialen zonder toxische stoffen of materialen waarbij het aandeel toxische stoffen schadelijke grenswaarden niet overschrijdt. Conform PvE Frisse scholen klasse B is de formaldehydeconcentratie in de lucht max. 30 microgram/m³, de TVOC -concentratie max. 200 microgram/m^3^ en worden er geen schadelijke weekmakers/ftalaten (zoals DEHP, DBP en BBP) toegepast. | F75: nee | I75: nee | K75: Randvoorwaarde voor POM | L75: Absoltuut getal in €
C76: Certificering | D76: De herkomst en duurzame eigenschappen van materialen moet onderbouwd kunnen worden, bij voorkeur aan de hand van certificaten (bijv. Cradle2Cradle, Natureplus, Declare-certificering). Materialen waarbij de controle niet goed mogelijk is, moeten vermeden worden. | F76: nee | I76: nee | K76: Niet
C77: Documentatie | D77: De opdrachtnemer draagt zorg voor het registreren en vastleggen van alle materialen die in het gebouw worden tijdens ontwerp en realisatie toegevoegd in een materialenpaspoort. | F77: nee | I77: nee | K77: Niet
C78: Materiaalgebonden CO~2~-uitstoot | D78: 330 | E78: kg CO2-eq / m2BVO/jaar | F78: nee | I78: nee | K78: Randvoorwaarde voor POM | L78: Absoltuut getal in €
C79: Aandeel biobased, hergebruikt en/of gerecycled materiaal | D79: 25 | E79: % | F79: nee | I79: ja | J79: Aandeel biobased hergebruikt of gerecycled 15% 25% of 35% | K79: Randvoorwaarde voor POM | L79: Absoltuut getal in €
C80: Losmaakbaarheidsindex | D80: 40 | E80: % | F80: nee | I80: ja | J80: LI 30% 40% of 50% | K80: Randvoorwaarde voor POM | L80: Absoltuut getal in €
B81: Waterverbruik | C81: Verbruiksefficiëntie | D81: Waterverbruikende voorzieningen moeten waterbesparend zijn zonder verlies van functionaliteit en comfort. Aandachtspunten zijn waterbesparende kranen in keukens en sanitaire ruimtes, efficiënte douches, wc’s, en zuinige (af)wasmachines. Ook schoonmaakinstallaties moeten efficiënt omgaan met waterverbruik. | F81: nee | I81: nee | K81: Randvoorwaarde voor POM | L81: Absoltuut getal in €
C82: Monitoring | D82: Het moet mogelijk zijn om het waterverbruik te monitoren. Er zijn (sub)watermeters op de hoofdaansluiting en op alle voorzieningen/ruimten met een significant waterverbruik (≥ 10% totaal). Het verbruik moet per gebruikersgroep afleesbaar zijn in een monitorings- of gebouwbeheersysteem. | F82: nee | I82: Ja | J82: Wel of geen subbemetering | K82: Randvoorwaarde voor POM | L82: Absoltuut getal in €
C83: Afvoer vuil water | D83: In de ontwerpfase moet onderzocht worden of het haalbaar is om een hergebruiksysteem te realiseren waarbij afvalwater (afkomstig van bijv. wastafels, douches, wasmachines) herbruikt wordt voor niet-drinkwater toepassingen zoals doorspoelen toiletten of irrigatie. | F83: nee | I83: Ja | J83: Wel of geen Afvalwater hergebruiksysteem | K83: Randvoorwaarde voor POM | L83: Absoltuut getal in €
C84: Afvoer hemelwater | D84: In de ontwerpfase moet onderzocht worden of het haalbaar is om een hergebruiksysteem (waarbij hemelwater wordt opgevangen, opgeslagen en indien nodig behandeld) en/of opvangsysteem (waarbij hemelwater wordt opgevangen in de grond of in tanks) te realiseren. | F84: nee | I84: Ja | J84: Wel of of geen grijswatersysteem | K84: Randvoorwaarde voor POM | L84: Absoltuut getal in €
B85: Afvalbeheer | C85: Inventarisatie bouwafval | D85: In geval van sloopwerkzaamheden moet een inventarisatie worden uitgevoerd om te bepalen welke materialen en producten hergebruikt, getransformeerd of gerecycled kunnen worden. Denk aan de terugwinning van bouwmaterialen zoals deuren, kozijnen, plafondpanelen en installaties. Bouwafval wordt zoveel mogelijk beperkt. | F85: nee | I85: nee | K85: Niet
C86: Scheiden bouwafval | D86: Bouw- en sloopafval moet op de bouwplaats gescheiden worden ingezameld om hergebruik en recycling te maximaliseren. Aandachtspunten zijn aparte containers voor verschillende materialen, en samenwerking met afvalverwerkers die circulaire verwerking ondersteunen. | F86: nee | I86: nee | K86: Niet
C87: Afval tijdens gebruiksfase | D87: Het gebouw moet beschikken over adequate voorzieningen voor afvalscheiding en opslag, afgestemd op de afvalstromen van gebruikers. Aandachtspunten zijn strategisch geplaatste inzamelpunten voor papier, plastic, GFT en restafval, en een efficiënte logistiek voor opslag en afvoer door de afvaldienst. | F87: nee | I87: nee | K87: Niet
B88: Natuurinclusiviteit | C88: Onderzoek | D88: Maatregelen ten aanzien van natuurinclusief bouwen moeten vastgesteld worden op basis van een flora- en fauna-inventarisatie. Deze inventarisatie moet uitgevoerd worden door een professionele ecoloog. In de inventarisatie moeten de ecologische waarden van de locatie beschreven worden op basis van bureau- en veldonderzoek. | F88: nee | I88: nee | K88: Randvoorwaarde voor POM | L88: Absoltuut getal in €
C89: Natuurvoorzieningen gebouw | D89: Waar mogelijk dienen bouwkundige wijzigingen bij te dragen aan de versterking van het lokale ecosysteem. Denk aan de toepassing van een bruin of groen dak en kleinschaligere maatregelen, zoals gevelbeplanting en nestruimte voor dieren. | F89: nee | I89: ja | J89: Wel of geen groendak | K89: Randvoorwaarde voor POM | L89: Absoltuut getal in €
C90: Natuurvoorzieningen buitenruimte | D90: Waar mogelijk dient de inrichting van de buitenruimte bij te dragen aan de versterking van het lokale ecosysteem. Denk aan gebruik inheemse plantsoorten, realisatie natuurspeelplaats en functies die kunnen bijdragen aan opvang van water (bijv. wadi, vijver). | F90: nee | I90: nee | K90: Niet
B91: Klimaatadaptatie | C91: Bestendigheid tegen hitte | D91: Opwarming van het gebouw en uitstraling van warmte naar de omgeving moet worden tegengegaan. Aandachtspunten zijn toepassing van warmtewerende of verkoelende materialen, het creëren van schaduw, en de toepassing van verticaal en horizontaal groen. Eventuele beplanting bestaat uit soorten die bestendig zijn tegen warme omstandigheden. | F91: nee | I91: nee | K91: Randvoorwaarde voor POM | L91: Absoltuut getal in €
C92: Bestendigheid tegen extreme neerslag | D92: Extreme neerslag wordt door het gebouw weerstaan zonder beschadigd te raken of minder goed te presteren. Gebouw en terrein zijn zodanig ontworpen dat neerslag op locatie wordt opgevangen en vertraagd wordt afgevoerd. | F92: nee | I92: ja | J92: Wel of geen waterretentie systeem | K92: Randvoorwaarde voor POM | L92: Absoltuut getal in €
C93: Bestendigheid tegen droogte | D93: Droogte wordt door het gebouw weerstaan zonder beschadigd te raken (denk aan evt. lagere grondwaterstand). Eventuele beplanting bestaat uit soorten die bestendig zijn tegen droge omstandigheden. Het gebouw zelf zorgt voor reductie waterverbruik (zie eisen met betrekking tot waterverbruik bij DP-17) | F93: nee | I93: nee | K93: Niet
C94: Bestendigheid tegen overstromingen | D94: In geval van een overstroming (stijging van 0,2 meter of minder) mag er geen schade optreden aan de gebouwstructuur en de elektrische installaties. Aandachtspunten zijn waterrobuuste vloer, waterrobuuste inrichting, hoogte stopcontacten, en verdeling van functies over verdiepingen. | F94: nee | I94: nee | K94: Niet
B95: Adaptiviteit plattegrond | C95: Ruimtescheidingen | D95: Binnenwanden moeten zonder ingrijpende/kostbare ingrepen verplaatsbaar zijn. Dragende wanden moeten zo veel mogelijk voorkomen worden. | F95: nee | I95: nee | K95: Randvoorwaarde voor POM | L95: Absoltuut getal in €
C96: Stramienmaat | D96: Het gevelontwerp, de constructie en de installaties moeten op één, fijnmazig stramien uitgelegd worden dat maximale mogelijkheden biedt voor het later kunnen aanpassen van de plattegrond ten behoeve van veranderende onderwijsprocessen of zelfs, op lange termijn, het transformeren van het gebouw tot een andere functie. | F96: nee | I96: nee | K96: Automatisch door POM | L96: Beoordeling op maakbaarheid Bouwsystemen. Hoe meer bouwsystemen toepasbaar zijn hoe hoger de score | M96: Gebouw
C97: Positionering vaste delen | D97: De structuur van het gebouw moet zodanig ontworpen zijn dat moeilijk of niet te verwijderen obstakels (bijv. kolommen, dragende wanden, trappenhuizen, schachten) geen belemmering vormen voor aanpassingen in in de indeling van het gebouw. | F97: nee | I97: nee | K97: Automatisch door POM | L97: Beoordeling op maakbaarheid Bouwsystemen. Hoe meer bouwsystemen toepasbaar zijn hoe hoger de score | M97: Gebouw
C98: Installatieontwerp | D98: De installatie-infrastructuur moet zodanig zijn opgezet, dat de mogelijke indelingsvarianten kunnen worden gerealiseerd zonder aanpassing van de hoofdstructuur en centrale vermogens van de installatie. | F98: nee | I98: nee | K98: Automatisch door POM | L98: Beoordeling op maakbaarheid Bouwsystemen. Hoe meer bouwsystemen toepasbaar zijn hoe hoger de score | M98: Gebouw
B99: Adaptiviteit ruimten | C99: Effectief ruimtegebruik | D99: Verkeersruimten en andere secundaire ruimtes moeten zodanig ontworpen worden dat ze ook functioneel gebruikt kunnen worden, resulterend in een zo goed mogelijke verhouding tussen het bruto en functionele oppervlak. Denk aan brede gangen die ruimte bieden aan studieplekken, of een centrale trap die ook dienst kan doen als tribune of pauzeplek. Aandachtspunt: zodra ondersteunende ruimten (bijv. gang) gebruikt kunnen worden als verblijfsruimten (bijv. leerplek) dan zal dit extra eisen met zich meebrengen (bijv. daglichteisen). | F99: nee | I99: nee | K99: Automatisch door POM | L99: Meten van Bruto netto verhouding. Hoe lager deze verghouding hoe beter de score | M99: Gebouw
C100: Gecombineerd ruimtegebruik | D100: Ruimten moeten zodanig worden ontworpen dat ze goed te combineren en/of uitwisselbaar zijn. Dit betekent dat indien een ruimte onderdeel uitmaakt van een andere ruimte de strengste eisen van de meest kritische ruimte gelden. Denk aan binnenklimaateisen voor een (open) garderobe of pantry binnen een personeelsruimte. | F100: nee | I100: nee | K100: Niet
...

Sheet Sheet1
D1: Inclusieve school | E1: Toeslag op inbouwpakket | F1: Gezonde school | G1: Toeslag op W-installaties, Dak, Gevel, Inbouw | H1: Duurzame school | I1: Toeslag op alles | J1: Veilige school | K1: Toeslag op terrein, gevel en inbouw | L1: Digitale school | M1: Toeslag op E-installaties | N1: Bouwlocatie | O1: Toeslag op AUK | P1: Fundatie | Q1: Toeslag op fundering | R1: Aantal verdiepingen | S1: Toeslag | T1: Uitstraling (Architectuur) gevel | U1: Toeslag op gevel en constructie | V1: Uitstraling (Architectuur) binnen | W1: Toeslag op constructie en inbouw | X1: Exploitatieperiode
D2: Ja | E2: 0.01 | F2: Ja, maximaal | G2: 0.1 | H2: Ja, maximaal | I2: 0.2 | J2: Ja | K2: 0.02 | L2: Ja | M2: 0.02 | N2: Stad, goed bereikbaar | O2: 0 | P2: Fundering op palen | Q2: 0.05 | R2: 1 | T2: Sober en doelmatig | U2: -0.02 | V2: Sober en doelmatig | W2: -0.02 | X2: 25
D3: Nee | E3: 0 | F3: Ja, iets meer dan wettelijk vereist | G3: 0.05 | H3: Ja, iets meer dan wettelijk vereist | I3: 0.1 | J3: Nee | K3: 0 | L3: Nee | M3: 0 | N3: Stad, slecht bereikbaar | O3: 0.03 | P3: Fundering op staal | Q3: 0 | R3: 2 | T3: Gemiddeld | U3: 0 | V3: Gemiddeld | W3: 0 | X3: 30
F4: Nee | G4: 0 | H4: Nee | I4: 0 | N4: Dorp | O4: 0 | P4: Complexe omstandigheden | Q4: 0.1 | R4: 3 | T4: Hoogwaardige architectuur | U4: 0.1 | V4: Hoogwaardige architectuur | W4: 0.1 | X4: 40
N5: Eilanden | O5: 0.05 | R5: 4 | X5: 50
E14: heeft impact op exploitatie?
C15: Ja/nee | D15: Voldoen aan NEN9120 JA of Nee | E15: nee
C16: BBL, A, B of C | D16: BBL, A, B of C
C17: BENG, Frisse scholen Engergie klasse A,B of C, ENG of 0 op de meter | D17: BENG, Frisse scholen Engergie klasse A,B of C, ENG of 0 op de meter | E17: ja
C18: 15% 25% of 35% | D18: Aandeel biobased hergebruikt of gerecycled | E18: nee
C19: 30%, 40%, 50% | D19: Losmaakbaarheidsindex | E19: nee
C20: Ja/nee | D20: Subbemetering | E20: ja | F20: gemiddeld circa 8,5% besparing
C21: Ja/nee | D21: Afvalwater hergebruiksysteem | E21: ja | F21: gemiddeld circa 0,75 cent per jaar per BVO
C22: Ja/nee | D22: Grijswatersysteem | E22: ja
C23: Ja/nee | D23: Groendak | E23: ja
C24: Ja/nee | D24: Waterretentie systeem | E24: ja
C25: Ja/nee | D25: Extra beveiligingsmaatregelen | E25: ja
C26: Ja/nee | D26: Toegangscontrolesysteem | E26: ja
C27: Ja/nee | D27: Camerasysteem | E27: ja
C28: Ja/nee | D28: Vandaalbestendigheidsmaatregelen
C29: Ja/nee | D29: Slim gebouw | E29: ja

Sheet PO TCO
C1: Scenarios obv Kwaliteitskader 2026
C2: PO Klein 1312m2 | E2: PO Groot 2423m2
B3: BVO | C3: 1312 | D3: 1312 | E3: 2423 | F3: 2423
B4: NEN2699 | C4: Basis | D4: TCO | E4: Basis | F4: TCO
A5: 1 | B5: Bouwkundige werken | C5: 1211 | D5: 1267 | E5: 1071 | F5: 1122
A6: 2 | B6: Installatietechnische werken | C6: 573 | D6: 645 | E6: 527 | F6: 600
A7: 3 | B7: Vaste inrichting | C7: 45 | D7: 45 | E7: 36 | F7: 36
A8: 4 | B8: Terrein | C8: 88 | D8: 88 | E8: 95 | F8: 95
A9: 5 | B9: Indirecte bouwkosten | C9: 385 | D9: 411 | E9: 348 | F9: 373
A10: 6 | B10: Bouwkosten | C10: 2302 | D10: 2456 | E10: 2077 | F10: 2226
A11: 7 | B11: Bijkomende kosten | C11: 413 | D11: 441 | E11: 373 | F11: 400
A12: 8 | B12: Belasting | C12: 567 | D12: 605 | E12: 512 | F12: 549
A13: 9 | B13: Investeringskosten | C13: 3283 | D13: 3502 | E13: 2962 | F13: 3175
B16: Toeslagen
B17: Energie neutraal | C17: 143 | D17: 0 | E17: 138 | F17: 0
B18: Duurzaamheid | C18: 212 | D18: 212 | E18: 212 | F18: 212
B19: Frisse scholen | C19: 233 | D19: 233 | E19: 203 | F19: 203
B20: Exploitatie | C20: 24 | D20: 17 | E20: 20 | F20: 14
B21: ICT | C21: 5 | D21: 5 | E21: 5 | F21: 5
B22: Kwaliteit buitenruimte | C22: 96 | D22: 96 | E22: 100 | F22: 100
B23: Overig | C23: 113 | D23: 113 | E23: 83 | F23: 83
B24: Totaal aanvullend | C24: 826 | D24: 676 | E24: 762 | F24: 617
B27: Exploitatie (40 jaar)
B28: Heffingen | C28: 13 | D28: 14 | E28: 11 | F28: 12
B29: Verzekeringen | C29: 6 | D29: 6 | E29: 5 | F29: 5
B30: Onderhoud | C30: 54 | D30: 54 | E30: 47 | F30: 48
B31: Verbruik | C31: 13 | D31: 4 | E31: 13 | F31: 4
B32: Beheerskosten | C32: 0 | D32: 0 | E32: 0 | F32: 0
B33: Financieringskosten | C33: 0 | D33: 0 | E33: 0 | F33: 0
B34: Schoonmaakkosten | C34: 15 | D34: 14 | E34: 14 | F34: 14
B35: Totaal per m2 BVO/jaar | C35: 100 | D35: 93 | E35: 91 | F35: 84

Sheet Vormfactoren
A1: scenario 1 = ik krijg alleen BVO | D1: Indien alleen de BVO bekend is zal scenario 1 de vormfactoren bepalen.
A2: BVO | B2: =INPUT!E3 -> 0 | D2: Scenario 2 zal de vormfactoren, indien allen bekend, doorrekenen naar het TCO.
A4: Vormfactoren vlgs Cost Indicators | C4: Laag | D4: Top | E4: Hoog | F4: Perth | H4: resultaat waarmee gerekend wordt:
A5: Verdiepingshoogte | B5: BI / BVO (m¹) | C5: 2.9 | D5: 3.7 | E5: 4.4 | F5: =(C5+(4*D5)+E5)/6 -> 3.6833333 | H5: =F5 -> 3.6833333 | I5: BI / BVO (m¹)
A6: Aantal bouwlagen | B6: BVO / BBO (st) | C6: 1.7 | D6: 2.9 | E6: 8 | F6: =(C6+(4*D6)+E6)/6 -> 3.55 | H6: =F6 -> 3.55 | I6: BVO / BBO (st)
A7: Bebouwingspercentage | B7: BBO / BTO | C7: 0.4 | D7: 0.63 | E7: 0.95 | F7: =(C7+(4*D7)+E7)/6 -> 0.645 | H7: =F7 -> 0.645 | I7: BBO / BTO
A8: Gevelfactor | B8: BGO / BVO | C8: 0.32 | D8: 0.52 | E8: 0.82 | F8: =(C8+(4*D8)+E8)/6 -> 0.53666667 | H8: =F8 -> 0.53666667 | I8: BGO / BVO
A9: Gevelopeningen | B9: OG / BGO | C9: 0.25 | D9: 0.41 | E9: 0.76 | F9: =(C9+(4*D9)+E9)/6 -> 0.44166667 | H9: =F9 -> 0.44166667 | I9: OG / BGO
A10: Dakfactor | B10: BDO / BBO | C10: 1 | D10: 1.01 | E10: 1.13 | F10: =(C10+(4*D10)+E10)/6 -> 1.0283333 | H10: =F10 -> 1.0283333 | I10: BDO / BBO
A11: Dakopeningen | B11: OD / BDO | C11: 0 | D11: 0.05 | E11: 0.2 | F11: =(C11+(4*D11)+E11)/6 -> 0.066666667 | H11: =F11 -> 0.066666667 | I11: OD / BDO
A12: Binnenwandfactor | B12: BBWO / BVO | C12: 0.3 | D12: 0.66 | E12: 1 | F12: =(C12+(4*D12)+E12)/6 -> 0.65666667 | H12: =F12 -> 0.65666667 | I12: BBWO / BVO
A13: Binnenwandopeningen | B13: OBW / BBWO | C13: 0.06 | D13: 0.22 | E13: 0.85 | F13: =(C13+(4*D13)+E13)/6 -> 0.29833333 | H13: =F13 -> 0.29833333 | I13: OBW / BBWO
A14: Terreinoppervlak | B14: kavel / BVO | C14: 0.39 | D14: 0.54 | E14: 1.29 | F14: =(C14+(4*D14)+E14)/6 -> 0.64 | H14: =F14 -> 0.64 | I14: kavel / BVO
E16: Scenario 2:
A17: Afgeleide hoeveelheden in m2 | C17: M2 obv BVO factoren: | E17: Verkregen uit POM: | H17: resultaat waarmee gerekend wordt:
A18: Bruto inhoud | B18: BI | C18: =B2*H5 -> 0 | E18: =INPUT!E7 -> 0 | H18: =IF(E18>0,E18,C18) -> 0 | I18: BI
A19: Bebouwd oppervlak | B19: BBO | C19: =B2/H6 -> 0 | E19: =INPUT!E8 -> 0 | H19: =IF(E19>0,E19,C19) -> 0 | I19: BBO
A20: Bruto gevel oppervlak | B20: BGO | C20: =B2*H8 -> 0 | E20: =INPUT!E9 -> 0 | H20: =IF(E20>0,E20,C20) -> 0 | I20: BGO
A21: Gevelopeningen | B21: OG | C21: =C20*H9 -> 0 | E21: =INPUT!E10 -> 0 | H21: =IF(E21>0,E21,C21) -> 0 | I21: OG
A22: Bruto dak oppervlak | B22: BDO | C22: =C19*H10 -> 0 | E22: =INPUT!E11 -> 0 | H22: =IF(E22>0,E22,C22) -> 0 | I22: BDO
A23: Dakopeningen | B23: OD | C23: =C22*H11 -> 0 | E23: =INPUT!E12 -> 0 | H23: =IF(E23>0,E23,C23) -> 0 | I23: OD
A24: Bruto binnenwandoppervlak | B24: BBWO | C24: =B2*H12 -> 0 | E24: =INPUT!E13 -> 0 | H24: =IF(E24>0,E24,C24) -> 0 | I24: BBWO
A25: Binnenwandopeningen | B25: OBW | C25: =C24*H13 -> 0 | E25: =INPUT!E14 -> 0 | H25: =IF(E25>0,E25,C25) -> 0 | I25: OBW
A26: Bruto terrein oppervlak | B26: BTO | C26: =B2*H14 -> 0 | E26: =INPUT!E15 -> 0 | H26: =IF(E26>0,E26,C26) -> 0 | I26: BTO

Sheet keuzevelden
A1: nee | B1: BBL | C1: BENG | D1: 15% | E1: 30%
A2: ja | B2: A | C2: Frisse scholen Engergie klasse A | D2: 25% | E2: 40%
B3: B | C3: Frisse scholen Engergie klasse B | D3: 35% | E3: 50%
B4: C | C4: Frisse scholen Engergie klasse C
C5: ENG
C6: 0 op de meter

Sheet Elementclusters
B1: Bouwkosten | C1: Eenheid | M1: Totaal | P1: PO-School | S1: Gymzaal | V1: Kinderopvang | Y1: Functie 4 | AB1: Functie 5
B2: verhouding functies | Q2: =100%-T2-W2-Z2-AC2 -> 1 | T2: =INPUT!E38 -> 0 | W2: =INPUT!E37 -> 0 | Z2: =0% -> 0 | AC2: =0% -> 0 | AF2: Pro rata obv PO Scholen
B3: Basis | M3: Laag | N3: Top | O3: Hoog | P3: Laag | Q3: Top | R3: Hoog | S3: Laag | T3: Top | U3: Hoog | V3: Laag | W3: Top | X3: Hoog | Y3: Laag | Z3: Top | AA3: Hoog | AB3: Laag | AC3: Top | AD3: Hoog | AF3: Gymzaal | AI3: Kinderopvang | AL3: Functie 4 | AO3: Functie 5
B4: Slopen | C4: €/m² BVO | M4: =AVERAGE(P4*$Q$2+S4*$T$2+V4*$W$2+Y4*$Z$2+AB4*$AC$2) -> 0 | N4: =AVERAGE(Q4*$Q$2+T4*$T$2+W4*$W$2+Z4*$Z$2+AC4*$AC$2) -> 0 | O4: =AVERAGE(R4*$Q$2+U4*$T$2+X4*$W$2+AA4*$Z$2+AD4*$AC$2) -> 0 | P4: 0 | Q4: 0 | R4: 0 | S4: =P4*$AG$5 -> 0 | T4: =Q4*$AG$5 -> 0 | U4: =R4*$AG$5 -> 0 | V4: =P4*$AJ$5 -> 0 | W4: =Q4*$AJ$5 -> 0 | X4: =R4*$AJ$5 -> 0 | Y4: 0 | Z4: 0 | AA4: 0 | AB4: 0 | AC4: 0 | AD4: 0
B5: Onderbouw | C5: €/m² BBO | I5: 120 | J5: 195 | K5: 485 | M5: =AVERAGE(P5*$Q$2+S5*$T$2+V5*$W$2+Y5*$Z$2+AB5*$AC$2) -> 120 | N5: =AVERAGE(Q5*$Q$2+T5*$T$2+W5*$W$2+Z5*$Z$2+AC5*$AC$2) -> 185 | O5: =AVERAGE(R5*$Q$2+U5*$T$2+X5*$W$2+AA5*$Z$2+AD5*$AC$2) -> 485 | P5: 120 | Q5: 185 | R5: 485 | S5: =P5*$AG$5 -> 84 | T5: =Q5*$AG$5 -> 129.5 | U5: =R5*$AG$5 -> 339.5 | V5: =P5*$AJ$5 -> 138 | W5: =Q5*$AJ$5 -> 212.75 | X5: =R5*$AJ$5 -> 557.75 | Y5: 0 | Z5: 0 | AA5: 0 | AB5: 0 | AC5: 0 | AD5: 0 | AG5: 0.7 | AJ5: 1.15
B6: Bovenbouw | C6: €/m² BVO | I6: 145 | J6: 260 | K6: 345 | M6: =AVERAGE(P6*$Q$2+S6*$T$2+V6*$W$2+Y6*$Z$2+AB6*$AC$2) -> 145 | N6: =AVERAGE(Q6*$Q$2+T6*$T$2+W6*$W$2+Z6*$Z$2+AC6*$AC$2) -> 230 | O6: =AVERAGE(R6*$Q$2+U6*$T$2+X6*$W$2+AA6*$Z$2+AD6*$AC$2) -> 345 | P6: 145 | Q6: 230 | R6: 345 | S6: =P6*$AG$5 -> 101.5 | T6: =Q6*$AG$5 -> 161 | U6: =R6*$AG$5 -> 241.5 | V6: =P6*$AJ$5 -> 166.75 | W6: =Q6*$AJ$5 -> 264.5 | X6: =R6*$AJ$5 -> 396.75 | Y6: 0 | Z6: 0 | AA6: 0 | AB6: 0 | AC6: 0 | AD6: 0
B7: Gevel | C7: €/m² BGO | M7: =AVERAGE(P7*$Q$2+S7*$T$2+V7*$W$2+Y7*$Z$2+AB7*$AC$2) -> 240 | N7: =AVERAGE(Q7*$Q$2+T7*$T$2+W7*$W$2+Z7*$Z$2+AC7*$AC$2) -> 260 | O7: =AVERAGE(R7*$Q$2+U7*$T$2+X7*$W$2+AA7*$Z$2+AD7*$AC$2) -> 450 | P7: 240 | Q7: 260 | R7: 450 | S7: =P7*$AG$5 -> 168 | T7: =Q7*$AG$5 -> 182 | U7: =R7*$AG$5 -> 315 | V7: =P7*$AJ$5 -> 276 | W7: =Q7*$AJ$5 -> 299 | X7: =R7*$AJ$5 -> 517.5 | Y7: 0 | Z7: 0 | AA7: 0 | AB7: 0 | AC7: 0 | AD7: 0
B8: Gevel open (toeslag) | C8: €/m² OG | M8: =AVERAGE(P8*$Q$2+S8*$T$2+V8*$W$2+Y8*$Z$2+AB8*$AC$2) -> 150 | N8: =AVERAGE(Q8*$Q$2+T8*$T$2+W8*$W$2+Z8*$Z$2+AC8*$AC$2) -> 260 | O8: =AVERAGE(R8*$Q$2+U8*$T$2+X8*$W$2+AA8*$Z$2+AD8*$AC$2) -> 280 | P8: 150 | Q8: 260 | R8: 280 | S8: =P8*$AG$5 -> 105 | T8: =Q8*$AG$5 -> 182 | U8: =R8*$AG$5 -> 196 | V8: =P8*$AJ$5 -> 172.5 | W8: =Q8*$AJ$5 -> 299 | X8: =R8*$AJ$5 -> 322 | Y8: 0 | Z8: 0 | AA8: 0 | AB8: 0 | AC8: 0 | AD8: 0
B9: Dak | C9: €/m² BDO | M9: =AVERAGE(P9*$Q$2+S9*$T$2+V9*$W$2+Y9*$Z$2+AB9*$AC$2) -> 110.25 | N9: =AVERAGE(Q9*$Q$2+T9*$T$2+W9*$W$2+Z9*$Z$2+AC9*$AC$2) -> 145 | O9: =AVERAGE(R9*$Q$2+U9*$T$2+X9*$W$2+AA9*$Z$2+AD9*$AC$2) -> 241.5 | P9: =105*1.05 -> 110.25 | Q9: 145 | R9: =230*1.05 -> 241.5 | S9: =P9*$AG$5 -> 77.175 | T9: =Q9*$AG$5 -> 101.5 | U9: =R9*$AG$5 -> 169.05 | V9: =P9*$AJ$5 -> 126.7875 | W9: =Q9*$AJ$5 -> 166.75 | X9: =R9*$AJ$5 -> 277.725 | Y9: 0 | Z9: 0 | AA9: 0 | AB9: 0 | AC9: 0 | AD9: 0
B10: Inbouw | C10: €/m² BVO | M10: =AVERAGE(P10*$Q$2+S10*$T$2+V10*$W$2+Y10*$Z$2+AB10*$AC$2) -> 241.5 | N10: =AVERAGE(Q10*$Q$2+T10*$T$2+W10*$W$2+Z10*$Z$2+AC10*$AC$2) -> 315 | O10: =AVERAGE(R10*$Q$2+U10*$T$2+X10*$W$2+AA10*$Z$2+AD10*$AC$2) -> 456.75 | P10: =230*1.05 -> 241.5 | Q10: 315 | R10: =435*1.05 -> 456.75 | S10: =P10*$AG$5 -> 169.05 | T10: =Q10*$AG$5 -> 220.5 | U10: =R10*$AG$5 -> 319.725 | V10: =P10*$AJ$5 -> 277.725 | W10: =Q10*$AJ$5 -> 362.25 | X10: =R10*$AJ$5 -> 525.2625 | Y10: 0 | Z10: 0 | AA10: 0 | AB10: 0 | AC10: 0 | AD10: 0
B11: W-installaties | C11: €/m² BVO | M11: =AVERAGE(P11*$Q$2+S11*$T$2+V11*$W$2+Y11*$Z$2+AB11*$AC$2) -> 305 | N11: =AVERAGE(Q11*$Q$2+T11*$T$2+W11*$W$2+Z11*$Z$2+AC11*$AC$2) -> 325 | O11: =AVERAGE(R11*$Q$2+U11*$T$2+X11*$W$2+AA11*$Z$2+AD11*$AC$2) -> 420 | P11: 305 | Q11: 325 | R11: 420 | S11: =P11*$AG$5 -> 213.5 | T11: =Q11*$AG$5 -> 227.5 | U11: =R11*$AG$5 -> 294 | V11: =P11*$AJ$5 -> 350.75 | W11: =Q11*$AJ$5 -> 373.75 | X11: =R11*$AJ$5 -> 483 | Y11: 0 | Z11: 0 | AA11: 0 | AB11: 0 | AC11: 0 | AD11: 0
B12: E-installaties | C12: €/m² BVO | M12: =AVERAGE(P12*$Q$2+S12*$T$2+V12*$W$2+Y12*$Z$2+AB12*$AC$2) -> 150 | N12: =AVERAGE(Q12*$Q$2+T12*$T$2+W12*$W$2+Z12*$Z$2+AC12*$AC$2) -> 210 | O12: =AVERAGE(R12*$Q$2+U12*$T$2+X12*$W$2+AA12*$Z$2+AD12*$AC$2) -> 260 | P12: 150 | Q12: 210 | R12: 260 | S12: =P12*$AG$5 -> 105 | T12: =Q12*$AG$5 -> 147 | U12: =R12*$AG$5 -> 182 | V12: =P12*$AJ$5 -> 172.5 | W12: =Q12*$AJ$5 -> 241.5 | X12: =R12*$AJ$5 -> 299 | Y12: 0 | Z12: 0 | AA12: 0 | AB12: 0 | AC12: 0 | AD12: 0
B13: T-installaties | C13: €/m² BVO | M13: =AVERAGE(P13*$Q$2+S13*$T$2+V13*$W$2+Y13*$Z$2+AB13*$AC$2) -> 5.25 | N13: =AVERAGE(Q13*$Q$2+T13*$T$2+W13*$W$2+Z13*$Z$2+AC13*$AC$2) -> 21 | O13: =AVERAGE(R13*$Q$2+U13*$T$2+X13*$W$2+AA13*$Z$2+AD13*$AC$2) -> 63 | P13: =5*1.05 -> 5.25 | Q13: =20*1.05 -> 21 | R13: =60*1.05 -> 63 | S13: =P13*$AG$5 -> 3.675 | T13: =Q13*$AG$5 -> 14.7 | U13: =R13*$AG$5 -> 44.1 | V13: =P13*$AJ$5 -> 6.0375 | W13: =Q13*$AJ$5 -> 24.15 | X13: =R13*$AJ$5 -> 72.45 | Y13: 0 | Z13: 0 | AA13: 0 | AB13: 0 | AC13: 0 | AD13: 0
B14: Vaste inrichting | C14: €/m² BVO | M14: =AVERAGE(P14*$Q$2+S14*$T$2+V14*$W$2+Y14*$Z$2+AB14*$AC$2) -> 15.75 | N14: =AVERAGE(Q14*$Q$2+T14*$T$2+W14*$W$2+Z14*$Z$2+AC14*$AC$2) -> 21 | O14: =AVERAGE(R14*$Q$2+U14*$T$2+X14*$W$2+AA14*$Z$2+AD14*$AC$2) -> 57.75 | P14: =15*1.05 -> 15.75 | Q14: =20*1.05 -> 21 | R14: =55*1.05 -> 57.75 | S14: =P14*$AG$5 -> 11.025 | T14: =Q14*$AG$5 -> 14.7 | U14: =R14*$AG$5 -> 40.425 | V14: =P14*$AJ$5 -> 18.1125 | W14: =Q14*$AJ$5 -> 24.15 | X14: =R14*$AJ$5 -> 66.4125 | Y14: 0 | Z14: 0 | AA14: 0 | AB14: 0 | AC14: 0 | AD14: 0
B15: Terrein | C15: €/m² kavel | M15: =AVERAGE(P15*$Q$2+S15*$T$2+V15*$W$2+Y15*$Z$2+AB15*$AC$2) -> 36.75 | N15: =AVERAGE(Q15*$Q$2+T15*$T$2+W15*$W$2+Z15*$Z$2+AC15*$AC$2) -> 89.25 | O15: =AVERAGE(R15*$Q$2+U15*$T$2+X15*$W$2+AA15*$Z$2+AD15*$AC$2) -> 215.25 | P15: =35*1.05 -> 36.75 | Q15: =85*1.05 -> 89.25 | R15: =205*1.05 -> 215.25 | S15: =P15*$AG$5 -> 25.725 | T15: =Q15*$AG$5 -> 62.475 | U15: =R15*$AG$5 -> 150.675 | V15: =P15*$AJ$5 -> 42.2625 | W15: =Q15*$AJ$5 -> 102.6375 | X15: =R15*$AJ$5 -> 247.5375 | Y15: 0 | Z15: 0 | AA15: 0 | AB15: 0 | AC15: 0 | AD15: 0
B16: Subtotaal (directe bouwkosten) | M16: =AVERAGE(P16*$Q$2+S16*$T$2+V16*$W$2+Y16*$Z$2+AB16*$AC$2) -> 1491 | N16: =AVERAGE(Q16*$Q$2+T16*$T$2+W16*$W$2+Z16*$Z$2+AC16*$AC$2) -> 1653.75 | O16: =AVERAGE(R16*$Q$2+U16*$T$2+X16*$W$2+AA16*$Z$2+AD16*$AC$2) -> 2063.25 | P16: =1420*1.05 -> 1491 | Q16: =1575*1.05 -> 1653.75 | R16: =1965*1.05 -> 2063.25 | S16: =P16*$AG$5 -> 1043.7 | T16: =Q16*$AG$5 -> 1157.625 | U16: =R16*$AG$5 -> 1444.275 | V16: =P16*$AJ$5 -> 1714.65 | W16: =Q16*$AJ$5 -> 1901.8125 | X16: =R16*$AJ$5 -> 2372.7375 | Y16: 1 | Z16: 1 | AA16: 1 | AB16: 1 | AC16: 1 | AD16: 1
B17: AUK | M17: =AVERAGE(P17*$Q$2+S17*$T$2+V17*$W$2+Y17*$Z$2+AB17*$AC$2) -> 1.1 | N17: =AVERAGE(Q17*$Q$2+T17*$T$2+W17*$W$2+Z17*$Z$2+AC17*$AC$2) -> 1.1 | O17: =AVERAGE(R17*$Q$2+U17*$T$2+X17*$W$2+AA17*$Z$2+AD17*$AC$2) -> 1.1 | P17: 1.1 | Q17: 1.1 | R17: 1.1 | S17: =P17 -> 1.1 | T17: =S17 -> 1.1 | U17: =T17 -> 1.1 | V17: =S17 -> 1.1 | W17: =V17 -> 1.1 | X17: =W17 -> 1.1 | Y17: 0 | Z17: 0 | AA17: 0 | AB17: 0 | AC17: 0 | AD17: 0
B18: AK | M18: =AVERAGE(P18*$Q$2+S18*$T$2+V18*$W$2+Y18*$Z$2+AB18*$AC$2) -> 1.07 | N18: =AVERAGE(Q18*$Q$2+T18*$T$2+W18*$W$2+Z18*$Z$2+AC18*$AC$2) -> 1.07 | O18: =AVERAGE(R18*$Q$2+U18*$T$2+X18*$W$2+AA18*$Z$2+AD18*$AC$2) -> 1.07 | P18: 1.07 | Q18: 1.07 | R18: 1.07 | S18: 1.07 | T18: 1.07 | U18: 1.07 | V18: 1.07 | W18: 1.07 | X18: 1.07 | Y18: 0 | Z18: 0 | AA18: 0 | AB18: 0 | AC18: 0 | AD18: 0
B19: W&R | M19: =AVERAGE(P19*$Q$2+S19*$T$2+V19*$W$2+Y19*$Z$2+AB19*$AC$2) -> 1.03 | N19: =AVERAGE(Q19*$Q$2+T19*$T$2+W19*$W$2+Z19*$Z$2+AC19*$AC$2) -> 1.03 | O19: =AVERAGE(R19*$Q$2+U19*$T$2+X19*$W$2+AA19*$Z$2+AD19*$AC$2) -> 1.03 | P19: 1.03 | Q19: 1.03 | R19: 1.03 | S19: 1.04 | T19: 1.04 | U19: 1.04 | V19: 1.04 | W19: 1.04 | X19: 1.04 | Y19: 0 | Z19: 0 | AA19: 0 | AB19: 0 | AC19: 0 | AD19: 0
B20: Totale bouwkosten | M20: =AVERAGE(P20*$Q$2+S20*$T$2+V20*$W$2+Y20*$Z$2+AB20*$AC$2) -> 1737.75 | N20: =AVERAGE(Q20*$Q$2+T20*$T$2+W20*$W$2+Z20*$Z$2+AC20*$AC$2) -> 1937.25 | O20: =AVERAGE(R20*$Q$2+U20*$T$2+X20*$W$2+AA20*$Z$2+AD20*$AC$2) -> 2420.25 | P20: =1655*1.05 -> 1737.75 | Q20: =1845*1.05 -> 1937.25 | R20: =2305*1.05 -> 2420.25 | S20: =P20*$AG$5 -> 1216.425 | T20: =Q20*$AG$5 -> 1356.075 | U20: =R20*$AG$5 -> 1694.175 | V20: =P20*$AJ$5 -> 1998.4125 | W20: =Q20*$AJ$5 -> 2227.8375 | X20: =R20*$AJ$5 -> 2783.2875 | Y20: 0 | Z20: 0 | AA20: 0 | AB20: 0 | AC20: 0 | AD20: 0
B21: Totale bouwkosten incl. BTW | M21: =AVERAGE(P21*$Q$2+S21*$T$2+V21*$W$2+Y21*$Z$2+AB21*$AC$2) -> 2102.6775 | N21: =AVERAGE(Q21*$Q$2+T21*$T$2+W21*$W$2+Z21*$Z$2+AC21*$AC$2) -> 2344.0725 | O21: =AVERAGE(R21*$Q$2+U21*$T$2+X21*$W$2+AA21*$Z$2+AD21*$AC$2) -> 2928.5025 | P21: =P20*1.21 -> 2102.6775 | Q21: =Q20*1.21 -> 2344.0725 | R21: =R20*1.21 -> 2928.5025 | S21: =P21*$AG$5 -> 1471.8742 | T21: =Q21*$AG$5 -> 1640.8507 | U21: =R21*$AG$5 -> 2049.9517 | V21: =P21*$AJ$5 -> 2418.0791 | W21: =Q21*$AJ$5 -> 2695.6834 | X21: =R21*$AJ$5 -> 3367.7779 | Y21: 0 | Z21: 0 | AA21: 0 | AB21: 0 | AC21: 0 | AD21: 0
M22: Totaal | P22: PO-School | S22: Gymzaal | V22: Kinderopvang | Y22: Functie 4 | AB22: Functie 5
B23: LOSSE TOESLAGEN (DIRECTE KOSTEN + AUK + AK + W&R excl. BTW) | C23: Keuzes gebruiker: | D23: Optie: | E23: Impact op cluster: | F23: optie A | G23: optie B | H23: optie C | I23: optie D | J23: optie E | K23: optie F | L23: Factor Toeslag: | Q23: =Q2 -> 1 | T23: =T2 -> 0 | W23: =W2 -> 0 | Z23: =Z2 -> 0 | AC23: =AC2 -> 0
B24: Voldoen aan NEN9120 | C24: =INPUT!E19 -> nee | D24: =IF(ISTEXT(C24), IF(ISNUMBER(SEARCH("nee",UPPER($C24))),"Optie A", IF(ISNUMBER(SEARCH("ja",UPPER($C24))),"Optie B",""))) -> Optie A | E24: Inbouw, Terrein, Gevel | F24: 0 | G24: 1.025 | L24: =IF(D24="","",INDEX($F24:$K24,MATCH(D24,{"Optie A";"Optie B";"Optie C";"Optie D";"Optie E";"Optie F"},0))) -> 0 | M24: =MAX(0,((SUM(M10,M15,M7)*$L$24-SUM(M10,M15,M7))*((((($M$16*($M$17-1))+$M$16)*($M$18-1)+$M$16+($M$16*($M$17-1)))*($M$19-1)+$M$16+($M$16*($M$17-1))+(($M$16*($M$17-1))+$M$16)*($M$18-1))/$M$16))) -> 0 | N24: =MAX(0,((SUM(N10,N15,N7)*$L$24-SUM(N10,N15,N7))*((((($M$16*($M$17-1))+$M$16)*($M$18-1)+$M$16+($M$16*($M$17-1)))*($M$19-1)+$M$16+($M$16*($M$17-1))+(($M$16*($M$17-1))+$M$16)*($M$18-1))/$M$16))) -> 0 | O24: =MAX(0,((SUM(O10,O15,O7)*$L$24-SUM(O10,O15,O7))*((((($M$16*($M$17-1))+$M$16)*($M$18-1)+$M$16+($M$16*($M$17-1)))*($M$19-1)+$M$16+($M$16*($M$17-1))+(($M$16*($M$17-1))+$M$16)*($M$18-1))/$M$16))) -> 0 | P24: =MAX(0,((SUM(P10,P15,P7)*$L$24-SUM(P10,P15,P7))*((((($M$16*($M$17-1))+$M$16)*($M$18-1)+$M$16+($M$16*($M$17-1)))*($M$19-1)+$M$16+($M$16*($M$17-1))+(($M$16*($M$17-1))+$M$16)*($M$18-1))/$M$16))) -> 0 | Q24: =MAX(0,((SUM(Q10,Q15,Q7)*$L$24-SUM(Q10,Q15,Q7))*((((($M$16*($M$17-1))+$M$16)*($M$18-1)+$M$16+($M$16*($M$17-1)))*($M$19-1)+$M$16+($M$16*($M$17-1))+(($M$16*($M$17-1))+$M$16)*($M$18-1))/$M$16))) -> 0 | R24: =MAX(0,((SUM(R10,R15,R7)*$L$24-SUM(R10,R15,R7))*((((($M$16*($M$17-1))+$M$16)*($M$18-1)+$M$16+($M$16*($M$17-1)))*($M$19-1)+$M$16+($M$16*($M$17-1))+(($M$16*($M$17-1))+$M$16)*($M$18-1))/$M$16))) -> 0 | S24: =MAX(0,((SUM(S10,S15,S7)*$L$24-SUM(S10,S15,S7))*((((($M$16*($M$17-1))+$M$16)*($M$18-1)+$M$16+($M$16*($M$17-1)))*($M$19-1)+$M$16+($M$16*($M$17-1))+(($M$16*($M$17-1))+$M$16)*($M$18-1))/$M$16))) -> 0 | T24: =MAX(0,((SUM(T10,T15,T7)*$L$24-SUM(T10,T15,T7))*((((($M$16*($M$17-1))+$M$16)*($M$18-1)+$M$16+($M$16*($M$17-1)))*($M$19-1)+$M$16+($M$16*($M$17-1))+(($M$16*($M$17-1))+$M$16)*($M$18-1))/$M$16))) -> 0 | ... AD24: =MAX(0,((SUM(AD10,AD15,AD7)*$L$24-SUM(AD10,AD15,AD7))*((((($M$16*($M$17-1))+$M$16)*($M$18-1)+$M$16+($M$16*($M$17-1)))*($M$19-1)+$M$16+($M$16*($M$17-1))+(($M$16*($M$17-1))+$M$16)*($M$18-1))/$M$16))) -> 0
B25: BBL, A, B of C | C25: =INPUT!E20 -> BBL | D25: =IF(ISTEXT(C25), IF(ISNUMBER(SEARCH("BBL", UPPER($C25))), "Optie A", IF(ISNUMBER(SEARCH("A", UPPER($C25))), "Optie B", IF(ISNUMBER(SEARCH("B", UPPER($C25))), "Optie C", IF(ISNUMBER(SEARCH("C", UPPER($C25))), "Optie D", IF(ISNUMBER(SEARCH("OPTIE E", UPPER($C25))), "Optie E", IF(ISNUMBER(SEARCH("OPTIE F", UPPER($C25))), "Optie F", "")))))), "") -> Optie A | E25: Inbouw, Gevel, Dak, E-installatie, W-installaties | F25: 0 | G25: 1.045 | H25: 1.03 | I25: 1.015 | L25: =IF(D25="","",INDEX($F25:$K25,MATCH(D25,{"Optie A";"Optie B";"Optie C";"Optie D";"Optie E";"Optie F"},0))) -> 0 | M25: =MAX(0,((SUM(M10,M7,M9,M12,M11)*$L$25-SUM(M10,M7,M9,M12,M11))*(((((M16*(M17-1))+M16)*(M18-1)+M16+(M16*(M17-1)))*(M19-1)+M16+(M16*(M17-1))+((M16*(M17-1))+M16)*(M18-1))/M16))) -> 0 | N25: =MAX(0,((SUM(N10,N7,N9,N12,N11)*$L$25-SUM(N10,N7,N9,N12,N11))*(((((N16*(N17-1))+N16)*(N18-1)+N16+(N16*(N17-1)))*(N19-1)+N16+(N16*(N17-1))+((N16*(N17-1))+N16)*(N18-1))/N16))) -> 0 | O25: =MAX(0,((SUM(O10,O7,O9,O12,O11)*$L$25-SUM(O10,O7,O9,O12,O11))*(((((O16*(O17-1))+O16)*(O18-1)+O16+(O16*(O17-1)))*(O19-1)+O16+(O16*(O17-1))+((O16*(O17-1))+O16)*(O18-1))/O16))) -> 0 | P25: =MAX(0,((SUM(P10,P7,P9,P12,P11)*$L$25-SUM(P10,P7,P9,P12,P11))*(((((P16*(P17-1))+P16)*(P18-1)+P16+(P16*(P17-1)))*(P19-1)+P16+(P16*(P17-1))+((P16*(P17-1))+P16)*(P18-1))/P16))) -> 0 | Q25: =MAX(0,((SUM(Q10,Q7,Q9,Q12,Q11)*$L$25-SUM(Q10,Q7,Q9,Q12,Q11))*(((((Q16*(Q17-1))+Q16)*(Q18-1)+Q16+(Q16*(Q17-1)))*(Q19-1)+Q16+(Q16*(Q17-1))+((Q16*(Q17-1))+Q16)*(Q18-1))/Q16))) -> 0 | R25: =MAX(0,((SUM(R10,R7,R9,R12,R11)*$L$25-SUM(R10,R7,R9,R12,R11))*(((((R16*(R17-1))+R16)*(R18-1)+R16+(R16*(R17-1)))*(R19-1)+R16+(R16*(R17-1))+((R16*(R17-1))+R16)*(R18-1))/R16))) -> 0 | S25: =MAX(0,((SUM(S10,S7,S9,S12,S11)*$L$25-SUM(S10,S7,S9,S12,S11))*(((((S16*(S17-1))+S16)*(S18-1)+S16+(S16*(S17-1)))*(S19-1)+S16+(S16*(S17-1))+((S16*(S17-1))+S16)*(S18-1))/S16))) -> 0 | T25: =MAX(0,((SUM(T10,T7,T9,T12,T11)*$L$25-SUM(T10,T7,T9,T12,T11))*(((((T16*(T17-1))+T16)*(T18-1)+T16+(T16*(T17-1)))*(T19-1)+T16+(T16*(T17-1))+((T16*(T17-1))+T16)*(T18-1))/T16))) -> 0 | ... AD25: =MAX(0,((SUM(AD10,AD7,AD9,AD12,AD11)*$L$25-SUM(AD10,AD7,AD9,AD12,AD11))*(((((AD16*(AD17-1))+AD16)*(AD18-1)+AD16+(AD16*(AD17-1)))*(AD19-1)+AD16+(AD16*(AD17-1))+((AD16*(AD17-1))+AD16)*(AD18-1))/AD16))) -> 0
A26: x | B26: BENG, Frisse scholen Engergie klasse A,B of C, ENG of 0 op de meter | C26: =INPUT!E21 -> BENG | D26: =IF(ISTEXT(C26), IF(ISNUMBER(SEARCH("BENG", UPPER($C26))), "Optie A", IF(ISNUMBER(SEARCH("Frisse scholen Engergie klasse A", UPPER($C26))), "Optie B", IF(ISNUMBER(SEARCH("Frisse scholen Engergie klasse B", UPPER($C26))), "Optie C", IF(ISNUMBER(SEARCH("Frisse scholen Engergie klasse C", UPPER($C26))), "Optie D", IF(ISNUMBER(SEARCH("ENG", UPPER($C26))), "Optie E", IF(ISNUMBER(SEARCH("0 op de meter", UPPER($C26))), "Optie F", "")))))), "") -> Optie A | E26: Inbouw, Gevel, Dak, E-installatie, W-installaties | F26: 0 | G26: 1.12 | H26: 1.1 | I26: 1.05 | J26: 1.14 | K26: 1.15 | L26: =IF(D26="","",INDEX($F26:$K26,MATCH(D26,{"Optie A";"Optie B";"Optie C";"Optie D";"Optie E";"Optie F"},0))) -> 0 | M26: =MAX(0,((SUM(M10,M7,M9,M12,M11)*$L$26-SUM(M10,M7,M9,M12,M11))*(((((M16*(M17-1))+M16)*(M18-1)+M16+(M16*(M17-1)))*(M19-1)+M16+(M16*(M17-1))+((M16*(M17-1))+M16)*(M18-1))/M16))) -> 0 | N26: =MAX(0,((SUM(N10,N7,N9,N12,N11)*$L$26-SUM(N10,N7,N9,N12,N11))*(((((N16*(N17-1))+N16)*(N18-1)+N16+(N16*(N17-1)))*(N19-1)+N16+(N16*(N17-1))+((N16*(N17-1))+N16)*(N18-1))/N16))) -> 0 | O26: =MAX(0,((SUM(O10,O7,O9,O12,O11)*$L$26-SUM(O10,O7,O9,O12,O11))*(((((O16*(O17-1))+O16)*(O18-1)+O16+(O16*(O17-1)))*(O19-1)+O16+(O16*(O17-1))+((O16*(O17-1))+O16)*(O18-1))/O16))) -> 0 | P26: =MAX(0,((SUM(P10,P7,P9,P12,P11)*$L$26-SUM(P10,P7,P9,P12,P11))*(((((P16*(P17-1))+P16)*(P18-1)+P16+(P16*(P17-1)))*(P19-1)+P16+(P16*(P17-1))+((P16*(P17-1))+P16)*(P18-1))/P16))) -> 0 | Q26: =MAX(0,((SUM(Q10,Q7,Q9,Q12,Q11)*$L$26-SUM(Q10,Q7,Q9,Q12,Q11))*(((((Q16*(Q17-1))+Q16)*(Q18-1)+Q16+(Q16*(Q17-1)))*(Q19-1)+Q16+(Q16*(Q17-1))+((Q16*(Q17-1))+Q16)*(Q18-1))/Q16))) -> 0 | R26: =MAX(0,((SUM(R10,R7,R9,R12,R11)*$L$26-SUM(R10,R7,R9,R12,R11))*(((((R16*(R17-1))+R16)*(R18-1)+R16+(R16*(R17-1)))*(R19-1)+R16+(R16*(R17-1))+((R16*(R17-1))+R16)*(R18-1))/R16))) -> 0 | S26: =MAX(0,((SUM(S10,S7,S9,S12,S11)*$L$26-SUM(S10,S7,S9,S12,S11))*(((((S16*(S17-1))+S16)*(S18-1)+S16+(S16*(S17-1)))*(S19-1)+S16+(S16*(S17-1))+((S16*(S17-1))+S16)*(S18-1))/S16))) -> 0 | T26: =MAX(0,((SUM(T10,T7,T9,T12,T11)*$L$26-SUM(T10,T7,T9,T12,T11))*(((((T16*(T17-1))+T16)*(T18-1)+T16+(T16*(T17-1)))*(T19-1)+T16+(T16*(T17-1))+((T16*(T17-1))+T16)*(T18-1))/T16))) -> 0 | ... AD26: =MAX(0,((SUM(AD10,AD7,AD9,AD12,AD11)*$L$26-SUM(AD10,AD7,AD9,AD12,AD11))*(((((AD16*(AD17-1))+AD16)*(AD18-1)+AD16+(AD16*(AD17-1)))*(AD19-1)+AD16+(AD16*(AD17-1))+((AD16*(AD17-1))+AD16)*(AD18-1))/AD16))) -> 0
A27: x | B27: Aandeel biobased hergebruikt of gerecycled | C27: =INPUT!E22 -> 15% | D27: =IF(ISTEXT(C27), IF(ISNUMBER(SEARCH("15%", UPPER($C27))), "Optie A", IF(ISNUMBER(SEARCH("25%", UPPER($C27))), "Optie B", IF(ISNUMBER(SEARCH("35%", UPPER($C27))), "Optie C", IF(ISNUMBER(SEARCH("C", UPPER($C27))), "Optie D", IF(ISNUMBER(SEARCH("OPTIE E", UPPER($C27))), "Optie E", IF(ISNUMBER(SEARCH("OPTIE F", UPPER($C27))), "Optie F", "")))))), "") -> Optie A | E27: Bovenbouw, Gevel, Dak, Inbouw | F27: 1.01 | G27: 1.02 | H27: 1.03 | L27: =IF(D27="","",INDEX($F27:$K27,MATCH(D27,{"Optie A";"Optie B";"Optie C";"Optie D";"Optie E";"Optie F"},0))) -> 1.01 | M27: =MAX(0,((SUM(M6+M7+M9+M10)*$L$27-SUM(M6+M7+M9+M10))*(((((M16*(M17-1))+M16)*(M18-1)+M16+(M16*(M17-1)))*(M19-1)+M16+(M16*(M17-1))+((M16*(M17-1))+M16)*(M18-1))/M16))) -> 8.9316939 | N27: =MAX(0,((SUM(N6+N7+N9+N10)*$L$27-SUM(N6+N7+N9+N10))*(((((N16*(N17-1))+N16)*(N18-1)+N16+(N16*(N17-1)))*(N19-1)+N16+(N16*(N17-1))+((N16*(N17-1))+N16)*(N18-1))/N16))) -> 11.516945 | O27: =MAX(0,((SUM(O6+O7+O9+O10)*$L$27-SUM(O6+O7+O9+O10))*(((((O16*(O17-1))+O16)*(O18-1)+O16+(O16*(O17-1)))*(O19-1)+O16+(O16*(O17-1))+((O16*(O17-1))+O16)*(O18-1))/O16))) -> 18.102819 | P27: =MAX(0,((SUM(P6+P7+P9+P10)*$L$27-SUM(P6+P7+P9+P10))*(((((P16*(P17-1))+P16)*(P18-1)+P16+(P16*(P17-1)))*(P19-1)+P16+(P16*(P17-1))+((P16*(P17-1))+P16)*(P18-1))/P16))) -> 8.9316939 | Q27: =MAX(0,((SUM(Q6+Q7+Q9+Q10)*$L$27-SUM(Q6+Q7+Q9+Q10))*(((((Q16*(Q17-1))+Q16)*(Q18-1)+Q16+(Q16*(Q17-1)))*(Q19-1)+Q16+(Q16*(Q17-1))+((Q16*(Q17-1))+Q16)*(Q18-1))/Q16))) -> 11.516945 | R27: =MAX(0,((SUM(R6+R7+R9+R10)*$L$27-SUM(R6+R7+R9+R10))*(((((R16*(R17-1))+R16)*(R18-1)+R16+(R16*(R17-1)))*(R19-1)+R16+(R16*(R17-1))+((R16*(R17-1))+R16)*(R18-1))/R16))) -> 18.102819 | S27: =MAX(0,((SUM(S6+S7+S9+S10)*$L$27-SUM(S6+S7+S9+S10))*(((((S16*(S17-1))+S16)*(S18-1)+S16+(S16*(S17-1)))*(S19-1)+S16+(S16*(S17-1))+((S16*(S17-1))+S16)*(S18-1))/S16))) -> 6.3128866 | T27: =MAX(0,((SUM(T6+T7+T9+T10)*$L$27-SUM(T6+T7+T9+T10))*(((((T16*(T17-1))+T16)*(T18-1)+T16+(T16*(T17-1)))*(T19-1)+T16+(T16*(T17-1))+((T16*(T17-1))+T16)*(T18-1))/T16))) -> 8.140132 | ... AD27: =MAX(0,((SUM(AD6+AD7+AD9+AD10)*$L$27-SUM(AD6+AD7+AD9+AD10))*(((((AD16*(AD17-1))+AD16)*(AD18-1)+AD16+(AD16*(AD17-1)))*(AD19-1)+AD16+(AD16*(AD17-1))+((AD16*(AD17-1))+AD16)*(AD18-1))/AD16))) -> 0
A28: x | B28: Losmaakbaarheidsindex | C28: =INPUT!E23 -> 30% | D28: =IF(ISTEXT(C28), IF(ISNUMBER(SEARCH("30%", UPPER($C28))), "Optie A", IF(ISNUMBER(SEARCH("40%", UPPER($C28))), "Optie B", IF(ISNUMBER(SEARCH("50%", UPPER($C28))), "Optie C", IF(ISNUMBER(SEARCH("C", UPPER($C28))), "Optie D", IF(ISNUMBER(SEARCH("OPTIE E", UPPER($C28))), "Optie E", IF(ISNUMBER(SEARCH("OPTIE F", UPPER($C28))), "Optie F", "")))))), "") -> Optie A | E28: Bovenbouw, Gevel, Dak, Inbouw | F28: 1.015 | G28: 1.03 | H28: 1.045 | L28: =IF(D28="","",INDEX($F28:$K28,MATCH(D28,{"Optie A";"Optie B";"Optie C";"Optie D";"Optie E";"Optie F"},0))) -> 1.015 | M28: =MAX(0,((SUM(M6+M7+M10+M9)*$L$28-SUM(M6+M7+M10+M9))*(((((M16*(M17-1))+M16)*(M18-1)+M16+(M16*(M17-1)))*(M19-1)+M16+(M16*(M17-1))+((M16*(M17-1))+M16)*(M18-1))/M16))) -> 13.397541 | N28: =MAX(0,((SUM(N6+N7+N10+N9)*$L$28-SUM(N6+N7+N10+N9))*(((((N16*(N17-1))+N16)*(N18-1)+N16+(N16*(N17-1)))*(N19-1)+N16+(N16*(N17-1))+((N16*(N17-1))+N16)*(N18-1))/N16))) -> 17.275417 | O28: =MAX(0,((SUM(O6+O7+O10+O9)*$L$28-SUM(O6+O7+O10+O9))*(((((O16*(O17-1))+O16)*(O18-1)+O16+(O16*(O17-1)))*(O19-1)+O16+(O16*(O17-1))+((O16*(O17-1))+O16)*(O18-1))/O16))) -> 27.154229 | P28: =MAX(0,((SUM(P6+P7+P10+P9)*$L$28-SUM(P6+P7+P10+P9))*(((((P16*(P17-1))+P16)*(P18-1)+P16+(P16*(P17-1)))*(P19-1)+P16+(P16*(P17-1))+((P16*(P17-1))+P16)*(P18-1))/P16))) -> 13.397541 | Q28: =MAX(0,((SUM(Q6+Q7+Q10+Q9)*$L$28-SUM(Q6+Q7+Q10+Q9))*(((((Q16*(Q17-1))+Q16)*(Q18-1)+Q16+(Q16*(Q17-1)))*(Q19-1)+Q16+(Q16*(Q17-1))+((Q16*(Q17-1))+Q16)*(Q18-1))/Q16))) -> 17.275417 | R28: =MAX(0,((SUM(R6+R7+R10+R9)*$L$28-SUM(R6+R7+R10+R9))*(((((R16*(R17-1))+R16)*(R18-1)+R16+(R16*(R17-1)))*(R19-1)+R16+(R16*(R17-1))+((R16*(R17-1))+R16)*(R18-1))/R16))) -> 27.154229 | S28: =MAX(0,((SUM(S6+S7+S10+S9)*$L$28-SUM(S6+S7+S10+S9))*(((((S16*(S17-1))+S16)*(S18-1)+S16+(S16*(S17-1)))*(S19-1)+S16+(S16*(S17-1))+((S16*(S17-1))+S16)*(S18-1))/S16))) -> 9.4693299 | T28: =MAX(0,((SUM(T6+T7+T10+T9)*$L$28-SUM(T6+T7+T10+T9))*(((((T16*(T17-1))+T16)*(T18-1)+T16+(T16*(T17-1)))*(T19-1)+T16+(T16*(T17-1))+((T16*(T17-1))+T16)*(T18-1))/T16))) -> 12.210198 | ... AD28: =MAX(0,((SUM(AD6+AD7+AD10+AD9)*$L$28-SUM(AD6+AD7+AD10+AD9))*(((((AD16*(AD17-1))+AD16)*(AD18-1)+AD16+(AD16*(AD17-1)))*(AD19-1)+AD16+(AD16*(AD17-1))+((AD16*(AD17-1))+AD16)*(AD18-1))/AD16))) -> 0
B29: Subbemetering | C29: =INPUT!E24 -> nee | D29: =IF(ISTEXT(C29), IF(ISNUMBER(SEARCH("nee",UPPER($C29))),"Optie A", IF(ISNUMBER(SEARCH("ja",UPPER($C29))),"Optie B",""))) -> Optie A | E29: W-installaties | F29: 0 | G29: 1.05 | L29: =IF(D29="","",INDEX($F29:$K29,MATCH(D29,{"Optie A";"Optie B";"Optie C";"Optie D";"Optie E";"Optie F"},0))) -> 0 | M29: =MAX(0,((M11*$L$29-M11)*(((((M16*(M17-1))+M16)*(M18-1)+M16+(M16*(M17-1)))*(M19-1)+M16+(M16*(M17-1))+((M16*(M17-1))+M16)*(M18-1))/M16))) -> 0 | N29: =MAX(0,((N11*$L$29-N11)*(((((N16*(N17-1))+N16)*(N18-1)+N16+(N16*(N17-1)))*(N19-1)+N16+(N16*(N17-1))+((N16*(N17-1))+N16)*(N18-1))/N16))) -> 0 | O29: =MAX(0,((O11*$L$29-O11)*(((((O16*(O17-1))+O16)*(O18-1)+O16+(O16*(O17-1)))*(O19-1)+O16+(O16*(O17-1))+((O16*(O17-1))+O16)*(O18-1))/O16))) -> 0 | P29: =MAX(0,((P11*$L$29-P11)*(((((P16*(P17-1))+P16)*(P18-1)+P16+(P16*(P17-1)))*(P19-1)+P16+(P16*(P17-1))+((P16*(P17-1))+P16)*(P18-1))/P16))) -> 0 | Q29: =MAX(0,((Q11*$L$29-Q11)*(((((Q16*(Q17-1))+Q16)*(Q18-1)+Q16+(Q16*(Q17-1)))*(Q19-1)+Q16+(Q16*(Q17-1))+((Q16*(Q17-1))+Q16)*(Q18-1))/Q16))) -> 0 | R29: =MAX(0,((R11*$L$29-R11)*(((((R16*(R17-1))+R16)*(R18-1)+R16+(R16*(R17-1)))*(R19-1)+R16+(R16*(R17-1))+((R16*(R17-1))+R16)*(R18-1))/R16))) -> 0 | S29: =MAX(0,((S11*$L$29-S11)*(((((S16*(S17-1))+S16)*(S18-1)+S16+(S16*(S17-1)))*(S19-1)+S16+(S16*(S17-1))+((S16*(S17-1))+S16)*(S18-1))/S16))) -> 0 | T29: =MAX(0,((T11*$L$29-T11)*(((((T16*(T17-1))+T16)*(T18-1)+T16+(T16*(T17-1)))*(T19-1)+T16+(T16*(T17-1))+((T16*(T17-1))+T16)*(T18-1))/T16))) -> 0 | ... AD29: =MAX(0,((AD11*$L$29-AD11)*(((((AD16*(AD17-1))+AD16)*(AD18-1)+AD16+(AD16*(AD17-1)))*(AD19-1)+AD16+(AD16*(AD17-1))+((AD16*(AD17-1))+AD16)*(AD18-1))/AD16))) -> 0
B30: Afvalwater hergebruiksysteem | C30: =INPUT!E25 -> nee | D30: =IF(ISTEXT(C30), IF(ISNUMBER(SEARCH("nee",UPPER($C30))),"Optie A", IF(ISNUMBER(SEARCH("ja",UPPER($C30))),"Optie B",""))) -> Optie A | E30: W-installaties | F30: 0 | G30: 1.05 | L30: =IF(D30="","",INDEX($F30:$K30,MATCH(D30,{"Optie A";"Optie B";"Optie C";"Optie D";"Optie E";"Optie F"},0))) -> 0 | M30: =MAX(0,((M11*$L$30-M11)*(((((M16*(M17-1))+M16)*(M18-1)+M16+(M16*(M17-1)))*(M19-1)+M16+(M16*(M17-1))+((M16*(M17-1))+M16)*(M18-1))/M16))) -> 0 | N30: =MAX(0,((N11*$L$30-N11)*(((((N16*(N17-1))+N16)*(N18-1)+N16+(N16*(N17-1)))*(N19-1)+N16+(N16*(N17-1))+((N16*(N17-1))+N16)*(N18-1))/N16))) -> 0 | O30: =MAX(0,((O11*$L$30-O11)*(((((O16*(O17-1))+O16)*(O18-1)+O16+(O16*(O17-1)))*(O19-1)+O16+(O16*(O17-1))+((O16*(O17-1))+O16)*(O18-1))/O16))) -> 0 | P30: =MAX(0,((P11*$L$30-P11)*(((((P16*(P17-1))+P16)*(P18-1)+P16+(P16*(P17-1)))*(P19-1)+P16+(P16*(P17-1))+((P16*(P17-1))+P16)*(P18-1))/P16))) -> 0 | Q30: =MAX(0,((Q11*$L$30-Q11)*(((((Q16*(Q17-1))+Q16)*(Q18-1)+Q16+(Q16*(Q17-1)))*(Q19-1)+Q16+(Q16*(Q17-1))+((Q16*(Q17-1))+Q16)*(Q18-1))/Q16))) -> 0 | R30: =MAX(0,((R11*$L$30-R11)*(((((R16*(R17-1))+R16)*(R18-1)+R16+(R16*(R17-1)))*(R19-1)+R16+(R16*(R17-1))+((R16*(R17-1))+R16)*(R18-1))/R16))) -> 0 | S30: =MAX(0,((S11*$L$30-S11)*(((((S16*(S17-1))+S16)*(S18-1)+S16+(S16*(S17-1)))*(S19-1)+S16+(S16*(S17-1))+((S16*(S17-1))+S16)*(S18-1))/S16))) -> 0 | T30: =MAX(0,((T11*$L$30-T11)*(((((T16*(T17-1))+T16)*(T18-1)+T16+(T16*(T17-1)))*(T19-1)+T16+(T16*(T17-1))+((T16*(T17-1))+T16)*(T18-1))/T16))) -> 0 | ... AD30: =MAX(0,((AD11*$L$30-AD11)*(((((AD16*(AD17-1))+AD16)*(AD18-1)+AD16+(AD16*(AD17-1)))*(AD19-1)+AD16+(AD16*(AD17-1))+((AD16*(AD17-1))+AD16)*(AD18-1))/AD16))) -> 0
B31: Grijswatersysteem | C31: =INPUT!E26 -> nee | D31: =IF(ISTEXT(C31), IF(ISNUMBER(SEARCH("nee",UPPER($C31))),"Optie A", IF(ISNUMBER(SEARCH("ja",UPPER($C31))),"Optie B",""))) -> Optie A | E31: W-installaties | F31: 0 | G31: 1.05 | L31: =IF(D31="","",INDEX($F31:$K31,MATCH(D31,{"Optie A";"Optie B";"Optie C";"Optie D";"Optie E";"Optie F"},0))) -> 0 | M31: =MAX(0,((M11*$L$31-M11)*(((((M16*(M17-1))+M16)*(M18-1)+M16+(M16*(M17-1)))*(M19-1)+M16+(M16*(M17-1))+((M16*(M17-1))+M16)*(M18-1))/M16))) -> 0 | N31: =MAX(0,((N11*$L$31-N11)*(((((N16*(N17-1))+N16)*(N18-1)+N16+(N16*(N17-1)))*(N19-1)+N16+(N16*(N17-1))+((N16*(N17-1))+N16)*(N18-1))/N16))) -> 0 | O31: =MAX(0,((O11*$L$31-O11)*(((((O16*(O17-1))+O16)*(O18-1)+O16+(O16*(O17-1)))*(O19-1)+O16+(O16*(O17-1))+((O16*(O17-1))+O16)*(O18-1))/O16))) -> 0 | P31: =MAX(0,((P11*$L$31-P11)*(((((P16*(P17-1))+P16)*(P18-1)+P16+(P16*(P17-1)))*(P19-1)+P16+(P16*(P17-1))+((P16*(P17-1))+P16)*(P18-1))/P16))) -> 0 | Q31: =MAX(0,((Q11*$L$31-Q11)*(((((Q16*(Q17-1))+Q16)*(Q18-1)+Q16+(Q16*(Q17-1)))*(Q19-1)+Q16+(Q16*(Q17-1))+((Q16*(Q17-1))+Q16)*(Q18-1))/Q16))) -> 0 | R31: =MAX(0,((R11*$L$31-R11)*(((((R16*(R17-1))+R16)*(R18-1)+R16+(R16*(R17-1)))*(R19-1)+R16+(R16*(R17-1))+((R16*(R17-1))+R16)*(R18-1))/R16))) -> 0 | S31: =MAX(0,((S11*$L$31-S11)*(((((S16*(S17-1))+S16)*(S18-1)+S16+(S16*(S17-1)))*(S19-1)+S16+(S16*(S17-1))+((S16*(S17-1))+S16)*(S18-1))/S16))) -> 0 | T31: =MAX(0,((T11*$L$31-T11)*(((((T16*(T17-1))+T16)*(T18-1)+T16+(T16*(T17-1)))*(T19-1)+T16+(T16*(T17-1))+((T16*(T17-1))+T16)*(T18-1))/T16))) -> 0 | ... AD31: =MAX(0,((AD11*$L$31-AD11)*(((((AD16*(AD17-1))+AD16)*(AD18-1)+AD16+(AD16*(AD17-1)))*(AD19-1)+AD16+(AD16*(AD17-1))+((AD16*(AD17-1))+AD16)*(AD18-1))/AD16))) -> 0
B32: Groendak | C32: =INPUT!E27 -> nee | D32: =IF(ISTEXT(C32), IF(ISNUMBER(SEARCH("nee",UPPER($C32))),"Optie A", IF(ISNUMBER(SEARCH("ja",UPPER($C32))),"Optie B",""))) -> Optie A | E32: Dak, W-installaties | F32: 0 | G32: 1.075 | L32: =IF(D32="","",INDEX($F32:$K32,MATCH(D32,{"Optie A";"Optie B";"Optie C";"Optie D";"Optie E";"Optie F"},0))) -> 0 | M32: =MAX(0,((SUM(M11,M9)*$L$32-SUM(M11,M9))*(((((M16*(M17-1))+M16)*(M18-1)+M16+(M16*(M17-1)))*(M19-1)+M16+(M16*(M17-1))+((M16*(M17-1))+M16)*(M18-1))/M16))) -> 0 | N32: =MAX(0,((SUM(N11,N9)*$L$32-SUM(N11,N9))*(((((N16*(N17-1))+N16)*(N18-1)+N16+(N16*(N17-1)))*(N19-1)+N16+(N16*(N17-1))+((N16*(N17-1))+N16)*(N18-1))/N16))) -> 0 | O32: =MAX(0,((SUM(O11,O9)*$L$32-SUM(O11,O9))*(((((O16*(O17-1))+O16)*(O18-1)+O16+(O16*(O17-1)))*(O19-1)+O16+(O16*(O17-1))+((O16*(O17-1))+O16)*(O18-1))/O16))) -> 0 | P32: =MAX(0,((SUM(P11,P9)*$L$32-SUM(P11,P9))*(((((P16*(P17-1))+P16)*(P18-1)+P16+(P16*(P17-1)))*(P19-1)+P16+(P16*(P17-1))+((P16*(P17-1))+P16)*(P18-1))/P16))) -> 0 | Q32: =MAX(0,((SUM(Q11,Q9)*$L$32-SUM(Q11,Q9))*(((((Q16*(Q17-1))+Q16)*(Q18-1)+Q16+(Q16*(Q17-1)))*(Q19-1)+Q16+(Q16*(Q17-1))+((Q16*(Q17-1))+Q16)*(Q18-1))/Q16))) -> 0 | R32: =MAX(0,((SUM(R11,R9)*$L$32-SUM(R11,R9))*(((((R16*(R17-1))+R16)*(R18-1)+R16+(R16*(R17-1)))*(R19-1)+R16+(R16*(R17-1))+((R16*(R17-1))+R16)*(R18-1))/R16))) -> 0 | S32: =MAX(0,((SUM(S11,S9)*$L$32-SUM(S11,S9))*(((((S16*(S17-1))+S16)*(S18-1)+S16+(S16*(S17-1)))*(S19-1)+S16+(S16*(S17-1))+((S16*(S17-1))+S16)*(S18-1))/S16))) -> 0 | T32: =MAX(0,((SUM(T11,T9)*$L$32-SUM(T11,T9))*(((((T16*(T17-1))+T16)*(T18-1)+T16+(T16*(T17-1)))*(T19-1)+T16+(T16*(T17-1))+((T16*(T17-1))+T16)*(T18-1))/T16))) -> 0 | ... AD32: =MAX(0,((SUM(AD11,AD9)*$L$32-SUM(AD11,AD9))*(((((AD16*(AD17-1))+AD16)*(AD18-1)+AD16+(AD16*(AD17-1)))*(AD19-1)+AD16+(AD16*(AD17-1))+((AD16*(AD17-1))+AD16)*(AD18-1))/AD16))) -> 0
B33: Waterretentie systeem | C33: =INPUT!E28 -> nee | D33: =IF(ISTEXT(C33), IF(ISNUMBER(SEARCH("nee",UPPER($C33))),"Optie A", IF(ISNUMBER(SEARCH("ja",UPPER($C33))),"Optie B",""))) -> Optie A | E33: Dak, W-installaties, Terrein | F33: 0 | G33: 1.02 | L33: =IF(D33="","",INDEX($F33:$K33,MATCH(D33,{"Optie A";"Optie B";"Optie C";"Optie D";"Optie E";"Optie F"},0))) -> 0 | M33: =MAX(0,((SUM(M9,M11,M15)*$L$33-SUM(M9,M11,M15))*(((((M16*(M17-1))+M16)*(M18-1)+M16+(M16*(M17-1)))*(M19-1)+M16+(M16*(M17-1))+((M16*(M17-1))+M16)*(M18-1))/M16))) -> 0 | N33: =MAX(0,((SUM(N9,N11,N15)*$L$33-SUM(N9,N11,N15))*(((((N16*(N17-1))+N16)*(N18-1)+N16+(N16*(N17-1)))*(N19-1)+N16+(N16*(N17-1))+((N16*(N17-1))+N16)*(N18-1))/N16))) -> 0 | O33: =MAX(0,((SUM(O9,O11,O15)*$L$33-SUM(O9,O11,O15))*(((((O16*(O17-1))+O16)*(O18-1)+O16+(O16*(O17-1)))*(O19-1)+O16+(O16*(O17-1))+((O16*(O17-1))+O16)*(O18-1))/O16))) -> 0 | P33: =MAX(0,((SUM(P9,P11,P15)*$L$33-SUM(P9,P11,P15))*(((((P16*(P17-1))+P16)*(P18-1)+P16+(P16*(P17-1)))*(P19-1)+P16+(P16*(P17-1))+((P16*(P17-1))+P16)*(P18-1))/P16))) -> 0 | Q33: =MAX(0,((SUM(Q9,Q11,Q15)*$L$33-SUM(Q9,Q11,Q15))*(((((Q16*(Q17-1))+Q16)*(Q18-1)+Q16+(Q16*(Q17-1)))*(Q19-1)+Q16+(Q16*(Q17-1))+((Q16*(Q17-1))+Q16)*(Q18-1))/Q16))) -> 0 | R33: =MAX(0,((SUM(R9,R11,R15)*$L$33-SUM(R9,R11,R15))*(((((R16*(R17-1))+R16)*(R18-1)+R16+(R16*(R17-1)))*(R19-1)+R16+(R16*(R17-1))+((R16*(R17-1))+R16)*(R18-1))/R16))) -> 0 | S33: =MAX(0,((SUM(S9,S11,S15)*$L$33-SUM(S9,S11,S15))*(((((S16*(S17-1))+S16)*(S18-1)+S16+(S16*(S17-1)))*(S19-1)+S16+(S16*(S17-1))+((S16*(S17-1))+S16)*(S18-1))/S16))) -> 0 | T33: =MAX(0,((SUM(T9,T11,T15)*$L$33-SUM(T9,T11,T15))*(((((T16*(T17-1))+T16)*(T18-1)+T16+(T16*(T17-1)))*(T19-1)+T16+(T16*(T17-1))+((T16*(T17-1))+T16)*(T18-1))/T16))) -> 0 | ... AD33: =MAX(0,((SUM(AD9,AD11,AD15)*$L$33-SUM(AD9,AD11,AD15))*(((((AD16*(AD17-1))+AD16)*(AD18-1)+AD16+(AD16*(AD17-1)))*(AD19-1)+AD16+(AD16*(AD17-1))+((AD16*(AD17-1))+AD16)*(AD18-1))/AD16))) -> 0
B34: Extra beveiligingsmaatregelen | C34: =INPUT!E29 -> nee | D34: =IF(ISTEXT(C34), IF(ISNUMBER(SEARCH("nee",UPPER($C34))),"Optie A", IF(ISNUMBER(SEARCH("ja",UPPER($C34))),"Optie B",""))) -> Optie A | E34: E-installaties | F34: 0 | G34: 1.02 | L34: =IF(D34="","",INDEX($F34:$K34,MATCH(D34,{"Optie A";"Optie B";"Optie C";"Optie D";"Optie E";"Optie F"},0))) -> 0 | M34: =MAX(0,((M12*$L$34-M12)*(((((M16*(M17-1))+M16)*(M18-1)+M16+(M16*(M17-1)))*(M19-1)+M16+(M16*(M17-1))+((M16*(M17-1))+M16)*(M18-1))/M16))) -> 0 | N34: =MAX(0,((N12*$L$34-N12)*(((((N16*(N17-1))+N16)*(N18-1)+N16+(N16*(N17-1)))*(N19-1)+N16+(N16*(N17-1))+((N16*(N17-1))+N16)*(N18-1))/N16))) -> 0 | O34: =MAX(0,((O12*$L$34-O12)*(((((O16*(O17-1))+O16)*(O18-1)+O16+(O16*(O17-1)))*(O19-1)+O16+(O16*(O17-1))+((O16*(O17-1))+O16)*(O18-1))/O16))) -> 0 | P34: =MAX(0,((P12*$L$34-P12)*(((((P16*(P17-1))+P16)*(P18-1)+P16+(P16*(P17-1)))*(P19-1)+P16+(P16*(P17-1))+((P16*(P17-1))+P16)*(P18-1))/P16))) -> 0 | Q34: =MAX(0,((Q12*$L$34-Q12)*(((((Q16*(Q17-1))+Q16)*(Q18-1)+Q16+(Q16*(Q17-1)))*(Q19-1)+Q16+(Q16*(Q17-1))+((Q16*(Q17-1))+Q16)*(Q18-1))/Q16))) -> 0 | R34: =MAX(0,((R12*$L$34-R12)*(((((R16*(R17-1))+R16)*(R18-1)+R16+(R16*(R17-1)))*(R19-1)+R16+(R16*(R17-1))+((R16*(R17-1))+R16)*(R18-1))/R16))) -> 0 | S34: =MAX(0,((S12*$L$34-S12)*(((((S16*(S17-1))+S16)*(S18-1)+S16+(S16*(S17-1)))*(S19-1)+S16+(S16*(S17-1))+((S16*(S17-1))+S16)*(S18-1))/S16))) -> 0 | T34: =MAX(0,((T12*$L$34-T12)*(((((T16*(T17-1))+T16)*(T18-1)+T16+(T16*(T17-1)))*(T19-1)+T16+(T16*(T17-1))+((T16*(T17-1))+T16)*(T18-1))/T16))) -> 0 | ... AD34: =MAX(0,((AD12*$L$34-AD12)*(((((AD16*(AD17-1))+AD16)*(AD18-1)+AD16+(AD16*(AD17-1)))*(AD19-1)+AD16+(AD16*(AD17-1))+((AD16*(AD17-1))+AD16)*(AD18-1))/AD16))) -> 0
B35: Toegangscontrolesysteem | C35: =INPUT!E30 -> nee | D35: =IF(ISTEXT(C35), IF(ISNUMBER(SEARCH("nee",UPPER($C35))),"Optie A", IF(ISNUMBER(SEARCH("ja",UPPER($C35))),"Optie B",""))) -> Optie A | E35: E-installaties, vaste inrichting | F35: 0 | G35: 1.1 | L35: =IF(D35="","",INDEX($F35:$K35,MATCH(D35,{"Optie A";"Optie B";"Optie C";"Optie D";"Optie E";"Optie F"},0))) -> 0 | M35: =MAX(0,((SUM(M12,M14)*$L$35-SUM(M12,M14))*(((((M16*(M17-1))+M16)*(M18-1)+M16+(M16*(M17-1)))*(M19-1)+M16+(M16*(M17-1))+((M16*(M17-1))+M16)*(M18-1))/M16))) -> 0 | N35: =MAX(0,((SUM(N12,N14)*$L$35-SUM(N12,N14))*(((((N16*(N17-1))+N16)*(N18-1)+N16+(N16*(N17-1)))*(N19-1)+N16+(N16*(N17-1))+((N16*(N17-1))+N16)*(N18-1))/N16))) -> 0 | O35: =MAX(0,((SUM(O12,O14)*$L$35-SUM(O12,O14))*(((((O16*(O17-1))+O16)*(O18-1)+O16+(O16*(O17-1)))*(O19-1)+O16+(O16*(O17-1))+((O16*(O17-1))+O16)*(O18-1))/O16))) -> 0 | P35: =MAX(0,((SUM(P12,P14)*$L$35-SUM(P12,P14))*(((((P16*(P17-1))+P16)*(P18-1)+P16+(P16*(P17-1)))*(P19-1)+P16+(P16*(P17-1))+((P16*(P17-1))+P16)*(P18-1))/P16))) -> 0 | Q35: =MAX(0,((SUM(Q12,Q14)*$L$35-SUM(Q12,Q14))*(((((Q16*(Q17-1))+Q16)*(Q18-1)+Q16+(Q16*(Q17-1)))*(Q19-1)+Q16+(Q16*(Q17-1))+((Q16*(Q17-1))+Q16)*(Q18-1))/Q16))) -> 0 | R35: =MAX(0,((SUM(R12,R14)*$L$35-SUM(R12,R14))*(((((R16*(R17-1))+R16)*(R18-1)+R16+(R16*(R17-1)))*(R19-1)+R16+(R16*(R17-1))+((R16*(R17-1))+R16)*(R18-1))/R16))) -> 0 | S35: =MAX(0,((SUM(S12,S14)*$L$35-SUM(S12,S14))*(((((S16*(S17-1))+S16)*(S18-1)+S16+(S16*(S17-1)))*(S19-1)+S16+(S16*(S17-1))+((S16*(S17-1))+S16)*(S18-1))/S16))) -> 0 | T35: =MAX(0,((SUM(T12,T14)*$L$35-SUM(T12,T14))*(((((T16*(T17-1))+T16)*(T18-1)+T16+(T16*(T17-1)))*(T19-1)+T16+(T16*(T17-1))+((T16*(T17-1))+T16)*(T18-1))/T16))) -> 0 | ... AD35: =MAX(0,((SUM(AD12,AD14)*$L$35-SUM(AD12,AD14))*(((((AD16*(AD17-1))+AD16)*(AD18-1)+AD16+(AD16*(AD17-1)))*(AD19-1)+AD16+(AD16*(AD17-1))+((AD16*(AD17-1))+AD16)*(AD18-1))/AD16))) -> 0
B36: Camerasysteem | C36: =INPUT!E31 -> nee | D36: =IF(ISTEXT(C36), IF(ISNUMBER(SEARCH("nee",UPPER($C36))),"Optie A", IF(ISNUMBER(SEARCH("ja",UPPER($C36))),"Optie B",""))) -> Optie A | E36: E-installaties, vaste inrichting | F36: 0 | G36: 1.12 | L36: =IF(D36="","",INDEX($F36:$K36,MATCH(D36,{"Optie A";"Optie B";"Optie C";"Optie D";"Optie E";"Optie F"},0))) -> 0 | M36: =MAX(0,((SUM(M12,M14)*$L$36-SUM(M12,M14))*(((((M16*(M17-1))+M16)*(M18-1)+M16+(M16*(M17-1)))*(M19-1)+M16+(M16*(M17-1))+((M16*(M17-1))+M16)*(M18-1))/M16))) -> 0 | N36: =MAX(0,((SUM(N12,N14)*$L$36-SUM(N12,N14))*(((((N16*(N17-1))+N16)*(N18-1)+N16+(N16*(N17-1)))*(N19-1)+N16+(N16*(N17-1))+((N16*(N17-1))+N16)*(N18-1))/N16))) -> 0 | O36: =MAX(0,((SUM(O12,O14)*$L$36-SUM(O12,O14))*(((((O16*(O17-1))+O16)*(O18-1)+O16+(O16*(O17-1)))*(O19-1)+O16+(O16*(O17-1))+((O16*(O17-1))+O16)*(O18-1))/O16))) -> 0 | P36: =MAX(0,((SUM(P12,P14)*$L$36-SUM(P12,P14))*(((((P16*(P17-1))+P16)*(P18-1)+P16+(P16*(P17-1)))*(P19-1)+P16+(P16*(P17-1))+((P16*(P17-1))+P16)*(P18-1))/P16))) -> 0 | Q36: =MAX(0,((SUM(Q12,Q14)*$L$36-SUM(Q12,Q14))*(((((Q16*(Q17-1))+Q16)*(Q18-1)+Q16+(Q16*(Q17-1)))*(Q19-1)+Q16+(Q16*(Q17-1))+((Q16*(Q17-1))+Q16)*(Q18-1))/Q16))) -> 0 | R36: =MAX(0,((SUM(R12,R14)*$L$36-SUM(R12,R14))*(((((R16*(R17-1))+R16)*(R18-1)+R16+(R16*(R17-1)))*(R19-1)+R16+(R16*(R17-1))+((R16*(R17-1))+R16)*(R18-1))/R16))) -> 0 | S36: =MAX(0,((SUM(S12,S14)*$L$36-SUM(S12,S14))*(((((S16*(S17-1))+S16)*(S18-1)+S16+(S16*(S17-1)))*(S19-1)+S16+(S16*(S17-1))+((S16*(S17-1))+S16)*(S18-1))/S16))) -> 0 | T36: =MAX(0,((SUM(T12,T14)*$L$36-SUM(T12,T14))*(((((T16*(T17-1))+T16)*(T18-1)+T16+(T16*(T17-1)))*(T19-1)+T16+(T16*(T17-1))+((T16*(T17-1))+T16)*(T18-1))/T16))) -> 0 | ... AD36: =MAX(0,((SUM(AD12,AD14)*$L$36-SUM(AD12,AD14))*(((((AD16*(AD17-1))+AD16)*(AD18-1)+AD16+(AD16*(AD17-1)))*(AD19-1)+AD16+(AD16*(AD17-1))+((AD16*(AD17-1))+AD16)*(AD18-1))/AD16))) -> 0
B37: Vandaalbestendigheidsmaatregelen | C37: =INPUT!E32 -> nee | D37: =IF(ISTEXT(C37), IF(ISNUMBER(SEARCH("nee",UPPER($C37))),"Optie A", IF(ISNUMBER(SEARCH("ja",UPPER($C37))),"Optie B",""))) -> Optie A | E37: Terrein, Gevel, Dak | F37: 0 | G37: 1.025 | L37: =IF(D37="","",INDEX($F37:$K37,MATCH(D37,{"Optie A";"Optie B";"Optie C";"Optie D";"Optie E";"Optie F"},0))) -> 0 | M37: =MAX(0,((SUM(M15,M7,M9)*$L$37-SUM(M15,M7,M9))*(((((M16*(M17-1))+M16)*(M18-1)+M16+(M16*(M17-1)))*(M19-1)+M16+(M16*(M17-1))+((M16*(M17-1))+M16)*(M18-1))/M16))) -> 0 | N37: =MAX(0,((SUM(N15,N7,N9)*$L$37-SUM(N15,N7,N9))*(((((N16*(N17-1))+N16)*(N18-1)+N16+(N16*(N17-1)))*(N19-1)+N16+(N16*(N17-1))+((N16*(N17-1))+N16)*(N18-1))/N16))) -> 0 | O37: =MAX(0,((SUM(O15,O7,O9)*$L$37-SUM(O15,O7,O9))*(((((O16*(O17-1))+O16)*(O18-1)+O16+(O16*(O17-1)))*(O19-1)+O16+(O16*(O17-1))+((O16*(O17-1))+O16)*(O18-1))/O16))) -> 0 | P37: =MAX(0,((SUM(P15,P7,P9)*$L$37-SUM(P15,P7,P9))*(((((P16*(P17-1))+P16)*(P18-1)+P16+(P16*(P17-1)))*(P19-1)+P16+(P16*(P17-1))+((P16*(P17-1))+P16)*(P18-1))/P16))) -> 0 | Q37: =MAX(0,((SUM(Q15,Q7,Q9)*$L$37-SUM(Q15,Q7,Q9))*(((((Q16*(Q17-1))+Q16)*(Q18-1)+Q16+(Q16*(Q17-1)))*(Q19-1)+Q16+(Q16*(Q17-1))+((Q16*(Q17-1))+Q16)*(Q18-1))/Q16))) -> 0 | R37: =MAX(0,((SUM(R15,R7,R9)*$L$37-SUM(R15,R7,R9))*(((((R16*(R17-1))+R16)*(R18-1)+R16+(R16*(R17-1)))*(R19-1)+R16+(R16*(R17-1))+((R16*(R17-1))+R16)*(R18-1))/R16))) -> 0 | S37: =MAX(0,((SUM(S15,S7,S9)*$L$37-SUM(S15,S7,S9))*(((((S16*(S17-1))+S16)*(S18-1)+S16+(S16*(S17-1)))*(S19-1)+S16+(S16*(S17-1))+((S16*(S17-1))+S16)*(S18-1))/S16))) -> 0 | T37: =MAX(0,((SUM(T15,T7,T9)*$L$37-SUM(T15,T7,T9))*(((((T16*(T17-1))+T16)*(T18-1)+T16+(T16*(T17-1)))*(T19-1)+T16+(T16*(T17-1))+((T16*(T17-1))+T16)*(T18-1))/T16))) -> 0 | ... AD37: =MAX(0,((SUM(AD15,AD7,AD9)*$L$37-SUM(AD15,AD7,AD9))*(((((AD16*(AD17-1))+AD16)*(AD18-1)+AD16+(AD16*(AD17-1)))*(AD19-1)+AD16+(AD16*(AD17-1))+((AD16*(AD17-1))+AD16)*(AD18-1))/AD16))) -> 0
B38: Slim gebouw | C38: =INPUT!E33 -> nee | D38: =IF(ISTEXT(C38), IF(ISNUMBER(SEARCH("nee",UPPER($C38))),"Optie A", IF(ISNUMBER(SEARCH("ja",UPPER($C38))),"Optie B",""))) -> Optie A | E38: E-installaties, vaste inrichting | F38: 0 | G38: 1.1 | L38: =IF(D38="","",INDEX($F38:$K38,MATCH(D38,{"Optie A";"Optie B";"Optie C";"Optie D";"Optie E";"Optie F"},0))) -> 0 | M38: =MAX(0,((SUM(M12,M14)*$L$38-SUM(M12,M14))*(((((M16*(M17-1))+M16)*(M18-1)+M16+(M16*(M17-1)))*(M19-1)+M16+(M16*(M17-1))+((M16*(M17-1))+M16)*(M18-1))/M16))) -> 0 | N38: =MAX(0,((SUM(N12,N14)*$L$38-SUM(N12,N14))*(((((N16*(N17-1))+N16)*(N18-1)+N16+(N16*(N17-1)))*(N19-1)+N16+(N16*(N17-1))+((N16*(N17-1))+N16)*(N18-1))/N16))) -> 0 | O38: =MAX(0,((SUM(O12,O14)*$L$38-SUM(O12,O14))*(((((O16*(O17-1))+O16)*(O18-1)+O16+(O16*(O17-1)))*(O19-1)+O16+(O16*(O17-1))+((O16*(O17-1))+O16)*(O18-1))/O16))) -> 0 | P38: =MAX(0,((SUM(P12,P14)*$L$38-SUM(P12,P14))*(((((P16*(P17-1))+P16)*(P18-1)+P16+(P16*(P17-1)))*(P19-1)+P16+(P16*(P17-1))+((P16*(P17-1))+P16)*(P18-1))/P16))) -> 0 | Q38: =MAX(0,((SUM(Q12,Q14)*$L$38-SUM(Q12,Q14))*(((((Q16*(Q17-1))+Q16)*(Q18-1)+Q16+(Q16*(Q17-1)))*(Q19-1)+Q16+(Q16*(Q17-1))+((Q16*(Q17-1))+Q16)*(Q18-1))/Q16))) -> 0 | R38: =MAX(0,((SUM(R12,R14)*$L$38-SUM(R12,R14))*(((((R16*(R17-1))+R16)*(R18-1)+R16+(R16*(R17-1)))*(R19-1)+R16+(R16*(R17-1))+((R16*(R17-1))+R16)*(R18-1))/R16))) -> 0 | S38: =MAX(0,((SUM(S12,S14)*$L$38-SUM(S12,S14))*(((((S16*(S17-1))+S16)*(S18-1)+S16+(S16*(S17-1)))*(S19-1)+S16+(S16*(S17-1))+((S16*(S17-1))+S16)*(S18-1))/S16))) -> 0 | T38: =MAX(0,((SUM(T12,T14)*$L$38-SUM(T12,T14))*(((((T16*(T17-1))+T16)*(T18-1)+T16+(T16*(T17-1)))*(T19-1)+T16+(T16*(T17-1))+((T16*(T17-1))+T16)*(T18-1))/T16))) -> 0 | ... AD38: =MAX(0,((SUM(AD12,AD14)*$L$38-SUM(AD12,AD14))*(((((AD16*(AD17-1))+AD16)*(AD18-1)+AD16+(AD16*(AD17-1)))*(AD19-1)+AD16+(AD16*(AD17-1))+((AD16*(AD17-1))+AD16)*(AD18-1))/AD16))) -> 0
M39: Totaal | P39: PO-School | S39: Gymzaal | V39: Kinderopvang | Y39: Functie 4 | AB39: Functie 5
B40: LOSSE TOESLAGEN (DIRECTE KOSTEN + AUK + AK + W&R incl. Bijkomende Kosten & BTW) | C40: Keuzes gebruiker: | D40: Optie: | E40: Impact op cluster: | F40: optie A | G40: optie B | H40: optie C | I40: optie D | J40: optie E | K40: optie F | L40: Factor Toeslag: | Q40: =Q23 -> 1 | T40: =T23 -> 0 | W40: =W23 -> 0 | Z40: =Z23 -> 0 | AC40: =AC23 -> 0
B41: Voldoen aan NEN9120 | C41: =C24 -> nee | D41: =D24 -> Optie A | E41: =E24 -> Inbouw, Terrein, Gevel | F41: =F24 -> 0 | G41: =G24 -> 1.025 | H41: =H24 -> 0 | I41: =I24 -> 0 | J41: =J24 -> 0 | ... L41: =L24 -> 0 | M41: =M24*1.18*1.21 -> 0 | N41: =N24*1.18*1.21 -> 0 | O41: =O24*1.18*1.21 -> 0 | P41: =P24*1.18*1.21 -> 0 | Q41: =Q24*1.18*1.21 -> 0 | R41: =R24*1.18*1.21 -> 0 | S41: =S24*1.18*1.21 -> 0 | T41: =T24*1.18*1.21 -> 0 | ... AD41: =AD24*1.18*1.21 -> 0
B42: BBL, A, B of C | C42: =C25 -> BBL | D42: =D25 -> Optie A | E42: =E25 -> Inbouw, Gevel, Dak, E-installatie, W-installaties | F42: =F25 -> 0 | G42: =G25 -> 1.045 | H42: =H25 -> 1.03 | I42: =I25 -> 1.015 | J42: =J25 -> 0 | ... L42: =L25 -> 0 | M42: =M25*1.18*1.21 -> 0 | N42: =N25*1.18*1.21 -> 0 | O42: =O25*1.18*1.21 -> 0 | P42: =P25*1.18*1.21 -> 0 | Q42: =Q25*1.18*1.21 -> 0 | R42: =R25*1.18*1.21 -> 0 | S42: =S25*1.18*1.21 -> 0 | T42: =T25*1.18*1.21 -> 0 | ... AD42: =AD25*1.18*1.21 -> 0
B43: BENG, Frisse scholen Engergie klasse A,B of C, ENG of 0 op de meter | C43: =C26 -> BENG | D43: =D26 -> Optie A | E43: =E26 -> Inbouw, Gevel, Dak, E-installatie, W-installaties | F43: =F26 -> 0 | G43: =G26 -> 1.12 | H43: =H26 -> 1.1 | I43: =I26 -> 1.05 | J43: =J26 -> 1.14 | ... L43: =L26 -> 0 | M43: =M26*1.18*1.21 -> 0 | N43: =N26*1.18*1.21 -> 0 | O43: =O26*1.18*1.21 -> 0 | P43: =P26*1.18*1.21 -> 0 | Q43: =Q26*1.18*1.21 -> 0 | R43: =R26*1.18*1.21 -> 0 | S43: =S26*1.18*1.21 -> 0 | T43: =T26*1.18*1.21 -> 0 | ... AD43: =AD26*1.18*1.21 -> 0
B44: Aandeel biobased hergebruikt of gerecycled | C44: =C27 -> 15% | D44: =D27 -> Optie A | E44: =E27 -> Bovenbouw, Gevel, Dak, Inbouw | F44: =F27 -> 1.01 | G44: =G27 -> 1.02 | H44: =H27 -> 1.03 | I44: =I27 -> 0 | J44: =J27 -> 0 | ... L44: =L27 -> 1.01 | M44: =M27*1.18*1.21 -> 12.752673 | N44: =N27*1.18*1.21 -> 16.443894 | O44: =O27*1.18*1.21 -> 25.847205 | P44: =P27*1.18*1.21 -> 12.752673 | Q44: =Q27*1.18*1.21 -> 16.443894 | R44: =R27*1.18*1.21 -> 25.847205 | S44: =S27*1.18*1.21 -> 9.0135395 | T44: =T27*1.18*1.21 -> 11.62248 | ... AD44: =AD27*1.18*1.21 -> 0
B45: Losmaakbaarheidsindex | C45: =C28 -> 30% | D45: =D28 -> Optie A | E45: =E28 -> Bovenbouw, Gevel, Dak, Inbouw | F45: =F28 -> 1.015 | G45: =G28 -> 1.03 | H45: =H28 -> 1.045 | I45: =I28 -> 0 | J45: =J28 -> 0 | ... L45: =L28 -> 1.015 | M45: =M28*1.18*1.21 -> 19.129009 | N45: =N28*1.18*1.21 -> 24.665841 | O45: =O28*1.18*1.21 -> 38.770808 | P45: =P28*1.18*1.21 -> 19.129009 | Q45: =Q28*1.18*1.21 -> 24.665841 | R45: =R28*1.18*1.21 -> 38.770808 | S45: =S28*1.18*1.21 -> 13.520309 | T45: =T28*1.18*1.21 -> 17.433721 | ... AD45: =AD28*1.18*1.21 -> 0
B46: Subbemetering | C46: =C29 -> nee | D46: =D29 -> Optie A | E46: =E29 -> W-installaties | F46: =F29 -> 0 | G46: =G29 -> 1.05 | H46: =H29 -> 0 | I46: =I29 -> 0 | J46: =J29 -> 0 | ... L46: =L29 -> 0 | M46: =M29*1.18*1.21 -> 0 | N46: =N29*1.18*1.21 -> 0 | O46: =O29*1.18*1.21 -> 0 | P46: =P29*1.18*1.21 -> 0 | Q46: =Q29*1.18*1.21 -> 0 | R46: =R29*1.18*1.21 -> 0 | S46: =S29*1.18*1.21 -> 0 | T46: =T29*1.18*1.21 -> 0 | ... AD46: =AD29*1.18*1.21 -> 0
B47: Afvalwater hergebruiksysteem | C47: =C30 -> nee | D47: =D30 -> Optie A | E47: =E30 -> W-installaties | F47: =F30 -> 0 | G47: =G30 -> 1.05 | H47: =H30 -> 0 | I47: =I30 -> 0 | J47: =J30 -> 0 | ... L47: =L30 -> 0 | M47: =M30*1.18*1.21 -> 0 | N47: =N30*1.18*1.21 -> 0 | O47: =O30*1.18*1.21 -> 0 | P47: =P30*1.18*1.21 -> 0 | Q47: =Q30*1.18*1.21 -> 0 | R47: =R30*1.18*1.21 -> 0 | S47: =S30*1.18*1.21 -> 0 | T47: =T30*1.18*1.21 -> 0 | ... AD47: =AD30*1.18*1.21 -> 0
B48: Grijswatersysteem | C48: =C31 -> nee | D48: =D31 -> Optie A | E48: =E31 -> W-installaties | F48: =F31 -> 0 | G48: =G31 -> 1.05 | H48: =H31 -> 0 | I48: =I31 -> 0 | J48: =J31 -> 0 | ... L48: =L31 -> 0 | M48: =M31*1.18*1.21 -> 0 | N48: =N31*1.18*1.21 -> 0 | O48: =O31*1.18*1.21 -> 0 | P48: =P31*1.18*1.21 -> 0 | Q48: =Q31*1.18*1.21 -> 0 | R48: =R31*1.18*1.21 -> 0 | S48: =S31*1.18*1.21 -> 0 | T48: =T31*1.18*1.21 -> 0 | ... AD48: =AD31*1.18*1.21 -> 0
B49: Groendak | C49: =C32 -> nee | D49: =D32 -> Optie A | E49: =E32 -> Dak, W-installaties | F49: =F32 -> 0 | G49: =G32 -> 1.075 | H49: =H32 -> 0 | I49: =I32 -> 0 | J49: =J32 -> 0 | ... L49: =L32 -> 0 | M49: =M32*1.18*1.21 -> 0 | N49: =N32*1.18*1.21 -> 0 | O49: =O32*1.18*1.21 -> 0 | P49: =P32*1.18*1.21 -> 0 | Q49: =Q32*1.18*1.21 -> 0 | R49: =R32*1.18*1.21 -> 0 | S49: =S32*1.18*1.21 -> 0 | T49: =T32*1.18*1.21 -> 0 | ... AD49: =AD32*1.18*1.21 -> 0
B50: Waterretentie systeem | C50: =C33 -> nee | D50: =D33 -> Optie A | E50: =E33 -> Dak, W-installaties, Terrein | F50: =F33 -> 0 | G50: =G33 -> 1.02 | H50: =H33 -> 0 | I50: =I33 -> 0 | J50: =J33 -> 0 | ... L50: =L33 -> 0 | M50: =M33*1.18*1.21 -> 0 | N50: =N33*1.18*1.21 -> 0 | O50: =O33*1.18*1.21 -> 0 | P50: =P33*1.18*1.21 -> 0 | Q50: =Q33*1.18*1.21 -> 0 | R50: =R33*1.18*1.21 -> 0 | S50: =S33*1.18*1.21 -> 0 | T50: =T33*1.18*1.21 -> 0 | ... AD50: =AD33*1.18*1.21 -> 0
B51: Extra beveiligingsmaatregelen | C51: =C34 -> nee | D51: =D34 -> Optie A | E51: =E34 -> E-installaties | F51: =F34 -> 0 | G51: =G34 -> 1.02 | H51: =H34 -> 0 | I51: =I34 -> 0 | J51: =J34 -> 0 | ... L51: =L34 -> 0 | M51: =M34*1.18*1.21 -> 0 | N51: =N34*1.18*1.21 -> 0 | O51: =O34*1.18*1.21 -> 0 | P51: =P34*1.18*1.21 -> 0 | Q51: =Q34*1.18*1.21 -> 0 | R51: =R34*1.18*1.21 -> 0 | S51: =S34*1.18*1.21 -> 0 | T51: =T34*1.18*1.21 -> 0 | ... AD51: =AD34*1.18*1.21 -> 0
B52: Toegangscontrolesysteem | C52: =C35 -> nee | D52: =D35 -> Optie A | E52: =E35 -> E-installaties, vaste inrichting | F52: =F35 -> 0 | G52: =G35 -> 1.1 | H52: =H35 -> 0 | I52: =I35 -> 0 | J52: =J35 -> 0 | ... L52: =L35 -> 0 | M52: =M35*1.18*1.21 -> 0 | N52: =N35*1.18*1.21 -> 0 | O52: =O35*1.18*1.21 -> 0 | P52: =P35*1.18*1.21 -> 0 | Q52: =Q35*1.18*1.21 -> 0 | R52: =R35*1.18*1.21 -> 0 | S52: =S35*1.18*1.21 -> 0 | T52: =T35*1.18*1.21 -> 0 | ... AD52: =AD35*1.18*1.21 -> 0
... B55: Slim gebouw | C55: =C38 -> nee | D55: =D38 -> Optie A | E55: =E38 -> E-installaties, vaste inrichting | F55: =F38 -> 0 | G55: =G38 -> 1.1 | H55: =H38 -> 0 | I55: =I38 -> 0 | J55: =J38 -> 0 | ... L55: =L38 -> 0 | M55: =M38*1.18*1.21 -> 0 | N55: =N38*1.18*1.21 -> 0 | O55: =O38*1.18*1.21 -> 0 | P55: =P38*1.18*1.21 -> 0 | Q55: =Q38*1.18*1.21 -> 0 | R55: =R38*1.18*1.21 -> 0 | S55: =S38*1.18*1.21 -> 0 | T55: =T38*1.18*1.21 -> 0 | ... AD55: =AD38*1.18*1.21 -> 0
M59: Totaal | P59: PO-School | S59: Gymzaal | V59: Kinderopvang | Y59: Functie 4 | AB59: Functie 5
B60: EXPLOITATIE > BASIS | Q60: 0.8 | T60: 0.2 | W60: 0
B61: Heffingen | M61: =AVERAGE(P61*$Q$2+S61*$T$2+V61*$W$2+Y61*$Z$2+AB61*$AC$2) -> 9.0695 | N61: =AVERAGE(Q61*$Q$2+T61*$T$2+W61*$W$2+Z61*$Z$2+AC61*$AC$2) -> 10.67 | O61: =AVERAGE(R61*$Q$2+U61*$T$2+X61*$W$2+AA61*$Z$2+AD61*$AC$2) -> 12.2705 | P61: 9.0695 | Q61: 10.67 | R61: 12.2705 | S61: =P61*$AG$5 -> 6.34865 | T61: =Q61*$AG$5 -> 7.469 | U61: =R61*$AG$5 -> 8.58935 | V61: =P61*$AJ$5 -> 10.429925 | W61: =Q61*$AJ$5 -> 12.2705 | X61: =R61*$AJ$5 -> 14.111075
B62: Verzekeringen | M62: =AVERAGE(P62*$Q$2+S62*$T$2+V62*$W$2+Y62*$Z$2+AB62*$AC$2) -> 4.1225 | N62: =AVERAGE(Q62*$Q$2+T62*$T$2+W62*$W$2+Z62*$Z$2+AC62*$AC$2) -> 4.85 | O62: =AVERAGE(R62*$Q$2+U62*$T$2+X62*$W$2+AA62*$Z$2+AD62*$AC$2) -> 5.5775 | P62: 4.1225 | Q62: 4.85 | R62: 5.5775 | S62: =P62*$AG$5 -> 2.88575 | T62: =Q62*$AG$5 -> 3.395 | U62: =R62*$AG$5 -> 3.90425 | V62: =P62*$AJ$5 -> 4.740875 | W62: =Q62*$AJ$5 -> 5.5775 | X62: =R62*$AJ$5 -> 6.414125
B63: Onderhoud | M63: =AVERAGE(P63*$Q$2+S63*$T$2+V63*$W$2+Y63*$Z$2+AB63*$AC$2) -> 38.7515 | N63: =AVERAGE(Q63*$Q$2+T63*$T$2+W63*$W$2+Z63*$Z$2+AC63*$AC$2) -> 45.59 | O63: =AVERAGE(R63*$Q$2+U63*$T$2+X63*$W$2+AA63*$Z$2+AD63*$AC$2) -> 52.4285 | P63: 38.7515 | Q63: 45.59 | R63: 52.4285 | S63: =P63*$AG$5 -> 27.12605 | T63: =Q63*$AG$5 -> 31.913 | U63: =R63*$AG$5 -> 36.69995 | V63: =P63*$AJ$5 -> 44.564225 | W63: =Q63*$AJ$5 -> 52.4285 | X63: =R63*$AJ$5 -> 60.292775
B64: Verbruik | M64: =AVERAGE(P64*$Q$2+S64*$T$2+V64*$W$2+Y64*$Z$2+AB64*$AC$2) -> 11.05 | N64: =AVERAGE(Q64*$Q$2+T64*$T$2+W64*$W$2+Z64*$Z$2+AC64*$AC$2) -> 13 | O64: =AVERAGE(R64*$Q$2+U64*$T$2+X64*$W$2+AA64*$Z$2+AD64*$AC$2) -> 14.95 | P64: 11.05 | Q64: 13 | R64: 14.95 | S64: =P64*$AG$5 -> 7.735 | T64: =Q64*$AG$5 -> 9.1 | U64: =R64*$AG$5 -> 10.465 | V64: =P64*$AJ$5 -> 12.7075 | W64: =Q64*$AJ$5 -> 14.95 | X64: =R64*$AJ$5 -> 17.1925
B65: Beheerskosten | M65: =AVERAGE(P65*$Q$2+S65*$T$2+V65*$W$2+Y65*$Z$2+AB65*$AC$2) -> 0 | N65: =AVERAGE(Q65*$Q$2+T65*$T$2+W65*$W$2+Z65*$Z$2+AC65*$AC$2) -> 0 | O65: =AVERAGE(R65*$Q$2+U65*$T$2+X65*$W$2+AA65*$Z$2+AD65*$AC$2) -> 0 | P65: 0 | Q65: 0 | R65: 0 | S65: =P65*$AG$5 -> 0 | T65: =Q65*$AG$5 -> 0 | U65: =R65*$AG$5 -> 0 | V65: =P65*$AJ$5 -> 0 | W65: =Q65*$AJ$5 -> 0 | X65: =R65*$AJ$5 -> 0
B66: Financieringskosten | M66: =AVERAGE(P66*$Q$2+S66*$T$2+V66*$W$2+Y66*$Z$2+AB66*$AC$2) -> 0 | N66: =AVERAGE(Q66*$Q$2+T66*$T$2+W66*$W$2+Z66*$Z$2+AC66*$AC$2) -> 0 | O66: =AVERAGE(R66*$Q$2+U66*$T$2+X66*$W$2+AA66*$Z$2+AD66*$AC$2) -> 0 | P66: 0 | Q66: 0 | R66: 0 | S66: =P66*$AG$5 -> 0 | T66: =Q66*$AG$5 -> 0 | U66: =R66*$AG$5 -> 0 | V66: =P66*$AJ$5 -> 0 | W66: =Q66*$AJ$5 -> 0 | X66: =R66*$AJ$5 -> 0
B67: Schoonmaakkosten | M67: =AVERAGE(P67*$Q$2+S67*$T$2+V67*$W$2+Y67*$Z$2+AB67*$AC$2) -> 11.543 | N67: =AVERAGE(Q67*$Q$2+T67*$T$2+W67*$W$2+Z67*$Z$2+AC67*$AC$2) -> 13.58 | O67: =AVERAGE(R67*$Q$2+U67*$T$2+X67*$W$2+AA67*$Z$2+AD67*$AC$2) -> 15.617 | P67: 11.543 | Q67: 13.58 | R67: 15.617 | S67: =P67*$AG$5 -> 8.0801 | T67: =Q67*$AG$5 -> 9.506 | U67: =R67*$AG$5 -> 10.9319 | V67: =P67*$AJ$5 -> 13.27445 | W67: =Q67*$AJ$5 -> 15.617 | X67: =R67*$AJ$5 -> 17.95955
B68: Totaal | M68: =SUM(M61:M67) -> 74.5365 | N68: =SUM(N61:N67) -> 87.69 | O68: =SUM(O61:O67) -> 100.8435
M71: Totaal | P71: PO-School | S71: Gymzaal | V71: Kinderopvang | Y71: Functie 4 | AB71: Functie 5
B72: EXPLOITATIE > GECORRIGEERD | C72: Deze hebben relatie met keuzes "toeslagen" | F72: optie A | G72: optie B | H72: optie C | I72: optie D | Q72: 0.8 | T72: 0.2 | W72: 0
B73: Heffingen | E73: Zeer beperkt/geen impact | L73: 1 | M73: =M$61*$L73 -> 9.0695 | N73: =N$61*$L73 -> 10.67 | O73: =O$61*$L73 -> 12.2705
B74: Verzekeringen | L74: 1 | M74: =M$62*$L74 -> 4.1225 | N74: =N$62*$L74 -> 4.85 | O74: =O$62*$L74 -> 5.5775
B75: Onderhoud | E75: wel impact | L75: =IF(SUM($L$41:$L$55)=1.05<1.1,1.01,IF(SUM($L$41:$L$55)=1.11<1.15,1.02,IF(SUM($L$41:$L$55)>=1.16,1.04))) -> 1.04 | M75: =M$63*$L75 -> 40.30156 | N75: =N$63*$L75 -> 47.4136 | O75: =O$63*$L75 -> 54.52564
B76: Verbruik | E76: wel impact | L76: =IF(SUM($L$41:$L$55)=1.05<1.1,0.97,IF(SUM($L$41:$L$55)=1.11<1.15,0.95,IF(SUM($L$41:$L$55)>=1.16,0.92))) -> 0.92 | M76: =M$64*$L76 -> 10.166 | N76: =N$64*$L76 -> 11.96 | O76: =O$64*$L76 -> 13.754
B77: Beheerskosten | L77: 1 | M77: =M$65*$L77 -> 0 | N77: =N$65*$L77 -> 0 | O77: =O$65*$L77 -> 0
B78: Financieringskosten | L78: 1 | M78: =M$66*$L78 -> 0 | N78: =N$66*$L78 -> 0 | O78: =O$66*$L78 -> 0
B79: Schoonmaakkosten | E79: nooit impact | L79: 1 | M79: =M$67*$L79 -> 11.543 | N79: =N$67*$L79 -> 13.58 | O79: =O$67*$L79 -> 15.617
M80: =SUM(M73:M79) -> 75.20256 | N80: =SUM(N73:N79) -> 88.4736 | O80: =SUM(O73:O79) -> 101.74464

Sheet Calculatie
A2: Onderdeel | B2: Hoeveelheid | C2: Eenheid | D2: Prijs/ eenheid | E2: Totaal
D3: vanuit tab elementclusters, obv TOP totaal tab elementclusters?
A4: BASIS (OBV ELEMENTCLUSTERS)
A5: Slopen | B5: =Vormfactoren!B2 -> 0 | C5: BVO | D5: =Elementclusters!N4 -> 0 | E5: =B5*D5 -> 0
A6: Onderbouw | B6: =Vormfactoren!H19 -> 0 | C6: BBO | D6: =Elementclusters!N5 -> 185 | E6: =B6*D6 -> 0
A7: Bovenbouw | B7: =Vormfactoren!B2 -> 0 | C7: BVO | D7: =Elementclusters!N6 -> 230 | E7: =B7*D7 -> 0
A8: Gevel | B8: =Vormfactoren!H20 -> 0 | C8: BGO | D8: =Elementclusters!N7 -> 260 | E8: =B8*D8 -> 0
A9: Gevel open (toeslag) | B9: =Vormfactoren!H21 -> 0 | C9: OG | D9: =Elementclusters!N8 -> 260 | E9: =B9*D9 -> 0
A10: Dak | B10: =Vormfactoren!H22 -> 0 | C10: BDO | D10: =Elementclusters!N9 -> 145 | E10: =B10*D10 -> 0
A11: Inbouw | B11: =Vormfactoren!B2 -> 0 | C11: BVO | D11: =Elementclusters!N10 -> 315 | E11: =B11*D11 -> 0
A12: W-installaties | B12: =Vormfactoren!$B$2 -> 0 | C12: BVO | D12: =Elementclusters!N11 -> 325 | E12: =B12*D12 -> 0
A13: E-installaties | B13: =Vormfactoren!$B$2 -> 0 | C13: BVO | D13: =Elementclusters!N12 -> 210 | E13: =B13*D13 -> 0
A14: T-installaties | B14: =Vormfactoren!$B$2 -> 0 | C14: BVO | D14: =Elementclusters!N13 -> 21 | E14: =B14*D14 -> 0
A15: Vaste inrichting | B15: =Vormfactoren!$B$2 -> 0 | C15: BVO | D15: =Elementclusters!N14 -> 21 | E15: =B15*D15 -> 0
A16: Terrein | B16: =Vormfactoren!H26 -> 0 | C16: kavel | D16: =Elementclusters!N15 -> 89.25 | E16: =B16*D16 -> 0
A17: Subtotaal (directe bouwkosten) | B17: =Vormfactoren!$B$2 -> 0 | C17: BVO | D17: =SUM(D5:D16) -> 2061.25 | E17: =SUM(E5:E16) -> 0
A18: AUK | B18: =Vormfactoren!$B$2 -> 0 | C18: BVO | D18: =D17*Elementclusters!N17-D17 -> 206.125 | E18: =B18*D18 -> 0
A19: AK | B19: =Vormfactoren!$B$2 -> 0 | C19: BVO | D19: =$D$17*Elementclusters!N18-$D$17 -> 144.2875 | E19: =B19*D19 -> 0
A20: W&R | B20: =Vormfactoren!$B$2 -> 0 | C20: BVO | D20: =$D$17*Elementclusters!N19-$D$17 -> 61.8375 | E20: =B20*D20 -> 0
A21: Totale bouwkosten | B21: =Vormfactoren!$B$2 -> 0 | C21: BVO | D21: =D17+D18+D19+D20 -> 2473.5 | E21: =SUM(E17:E20) -> 0
A22: BTW | B22: =Vormfactoren!$B$2 -> 0 | C22: BVO | D22: =D21*1.21-D21 -> 519.435 | E22: =B22*D22 -> 0
A23: Totale bouwkosten INCL BTW | B23: =Vormfactoren!$B$2 -> 0 | C23: BVO | D23: =D21+D22 -> 2992.935 | E23: =SUM(E21:E22) -> 0
A26: BASIS OBV NEN2699 | B26: Hoeveelheid | C26: Eenheid | D26: €/m² BVO | E26: TOTAAL
A27: Bouwkundige werken | B27: =INPUT!$E$3 -> 0 | C27: BVO | D27: =E27/B27 -> #DIV/0! | E27: =E6+E7+E8+E9+E10+E11 -> 0
A28: Installatietechnische werken | B28: =INPUT!$E$3 -> 0 | C28: BVO | D28: =E28/B28 -> #DIV/0! | E28: =E12+E13+E14 -> 0
A29: Vaste inrichting | B29: =INPUT!$E$3 -> 0 | C29: BVO | D29: =E29/B29 -> #DIV/0! | E29: =E15 -> 0
A30: Terrein | B30: =INPUT!$E$3 -> 0 | C30: BVO | D30: =E30/B30 -> #DIV/0! | E30: =E16 -> 0
A31: Indirecte bouwkosten | B31: =INPUT!$E$3 -> 0 | C31: BVO | D31: =E31/B31 -> #DIV/0! | E31: =E18+E19+E20 -> 0
A32: Bouwkosten | B32: =INPUT!$E$3 -> 0 | C32: BVO | D32: =E32/B32 -> #DIV/0! | E32: =SUM(E27:E31) -> 0
A33: Bijkomende kosten | B33: =INPUT!$E$3 -> 0 | C33: BVO | D33: =E33/B33 -> #DIV/0! | E33: =E32*0.18 -> 0
A34: Belasting | B34: =INPUT!$E$3 -> 0 | C34: BVO | D34: =E34/B34 -> #DIV/0! | E34: =SUM(E32:E33)*0.21 -> 0
A35: Investeringskosten | B35: =INPUT!$E$3 -> 0 | C35: BVO | D35: =E35/B35 -> #DIV/0! | E35: =SUM(E32:E34) -> 0
A39: TOESLAGEN (DIRECTE KOSTEN + AUK + AK + W&R incl. Bijkomende Kosten & BTW)
A40: Voldoen aan NEN9120 | B40: =Vormfactoren!$B$2 -> 0 | C40: €/m² BVO | D40: =Elementclusters!N41 -> 0 | E40: =B40*D40 -> 0
A41: BBL, A, B of C | B41: =Vormfactoren!$B$2 -> 0 | C41: €/m² BVO | D41: =Elementclusters!N42 -> 0 | E41: =B41*D41 -> 0
A42: BENG, Frisse scholen Engergie klasse A,B of C, ENG of 0 op de meter | B42: =Vormfactoren!$B$2 -> 0 | C42: €/m² BVO | D42: =Elementclusters!N43 -> 0 | E42: =B42*D42 -> 0
A43: Aandeel biobased hergebruikt of gerecycled | B43: =Vormfactoren!$B$2 -> 0 | C43: €/m² BVO | D43: =Elementclusters!N44 -> 16.443894 | E43: =B43*D43 -> 0
A44: Losmaakbaarheidsindex | B44: =Vormfactoren!$B$2 -> 0 | C44: €/m² BVO | D44: =Elementclusters!N45 -> 24.665841 | E44: =B44*D44 -> 0
A45: Subbemetering | B45: =Vormfactoren!$B$2 -> 0 | C45: €/m² BVO | D45: =Elementclusters!N46 -> 0 | E45: =B45*D45 -> 0
A46: Afvalwater hergebruiksysteem | B46: =Vormfactoren!$B$2 -> 0 | C46: €/m² BVO | D46: =Elementclusters!N47 -> 0 | E46: =B46*D46 -> 0
A47: Grijswatersysteem | B47: =Vormfactoren!$B$2 -> 0 | C47: €/m² BVO | D47: =Elementclusters!N48 -> 0 | E47: =B47*D47 -> 0
A48: Groendak | B48: =Vormfactoren!$B$2 -> 0 | C48: €/m² BVO | D48: =Elementclusters!N49 -> 0 | E48: =B48*D48 -> 0
A49: Waterretentie systeem | B49: =Vormfactoren!$B$2 -> 0 | C49: €/m² BVO | D49: =Elementclusters!N50 -> 0 | E49: =B49*D49 -> 0
A50: Extra beveiligingsmaatregelen | B50: =Vormfactoren!$B$2 -> 0 | C50: €/m² BVO | D50: =Elementclusters!N51 -> 0 | E50: =B50*D50 -> 0
A51: Toegangscontrolesysteem | B51: =Vormfactoren!$B$2 -> 0 | C51: €/m² BVO | D51: =Elementclusters!N52 -> 0 | E51: =B51*D51 -> 0
... A54: Slim gebouw | B54: =Vormfactoren!$B$2 -> 0 | C54: €/m² BVO | D54: =Elementclusters!N55 -> 0 | E54: =B54*D54 -> 0
A55: Totaal Toeslagen | B55: =B53 -> 0 | C55: €/m² BVO | D55: =SUM(D40:D54) -> 41.109735 | E55: =SUM(E40:E54) -> 0
A58: TOTAAL | B58: =Vormfactoren!$B$2 -> 0 | C58: €/m² BVO | D58: =D35+D55 -> #DIV/0! | E58: =E35+E55 -> 0

Sheet PO BASIS
C1: Scenarios obv Kwaliteitskader 2026 | I1: Berekend
C2: PO Klein 1312m2 | D2: PO Groot 2423m2 | I2: Power law (F3) with caps (+5% / -3%)
B3: BVO | C3: 1312 | D3: 2423 | F3: 4000 | G3: <<invullen BVO
B4: NEN2699 | C4: Basis | D4: Basis | H4: Laag | I4: Top | J4: Hoog | K4: Berekend
A5: 1 | B5: Bouwkundige werken | C5: 1211 | D5: 1071 | F5: =IF(OR($F$3="",$C$3="",$D$3="",$D$3=$C$3),"",MIN(MAX($C5+($D5-$C5)*(($F$3-$C$3)/($D$3-$C$3)),MAX($C5*0.97,$D5*0.97)),MAX($C5,$D5)*1.05)) -> 1174.67 | H5: =0.9*I5 -> 934.983 | I5: =IF(OR($F$3="", $C$3="", $D$3="", $D$3=$C$3, $C$3<=0, $D$3<=0), "", IF(OR($C5<=0, $D5<=0), MIN(MAX($C5 + ($D5-$C5)*(($F$3-$C$3)/($D$3-$C$3)), MIN($C5,$D5)*0.97), MAX($C5,$D5)*1.05), MIN(MAX($C5 * (($F$3/$C$3) ^ (LOG($D5/$C5) / LOG($D$3/$C$3))), MIN($C5,$D5)*0.97), MAX($C5,$D5)*1.05))) -> 1038.87 | J5: =1.1*I5 -> 1142.757 | K5: =Calculatie!D27 -> #DIV/0!
A6: 2 | B6: Installatietechnische werken | C6: 573 | D6: 527 | F6: =IF(OR($F$3="",$C$3="",$D$3="",$D$3=$C$3),"",MIN(MAX($C6+($D6-$C6)*(($F$3-$C$3)/($D$3-$C$3)),MAX($C6*0.97,$D6*0.97)),MAX($C6,$D6)*1.05)) -> 555.81 | H6: =0.9*I6 -> 460.071 | I6: =IF(OR($F$3="", $C$3="", $D$3="", $D$3=$C$3, $C$3<=0, $D$3<=0), "", IF(OR($C6<=0, $D6<=0), MIN(MAX($C6 + ($D6-$C6)*(($F$3-$C$3)/($D$3-$C$3)), MIN($C6,$D6)*0.97), MAX($C6,$D6)*1.05), MIN(MAX($C6 * (($F$3/$C$3) ^ (LOG($D6/$C6) / LOG($D$3/$C$3))), MIN($C6,$D6)*0.97), MAX($C6,$D6)*1.05))) -> 511.19 | J6: =1.1*I6 -> 562.309 | K6: =Calculatie!D28 -> #DIV/0!
A7: 3 | B7: Vaste inrichting | C7: 45 | D7: 36 | F7: =IF(OR($F$3="",$C$3="",$D$3="",$D$3=$C$3),"",MIN(MAX($C7+($D7-$C7)*(($F$3-$C$3)/($D$3-$C$3)),MAX($C7*0.97,$D7*0.97)),MAX($C7,$D7)*1.05)) -> 43.65 | H7: =0.9*I7 -> 31.428 | I7: =IF(OR($F$3="", $C$3="", $D$3="", $D$3=$C$3, $C$3<=0, $D$3<=0), "", IF(OR($C7<=0, $D7<=0), MIN(MAX($C7 + ($D7-$C7)*(($F$3-$C$3)/($D$3-$C$3)), MIN($C7,$D7)*0.97), MAX($C7,$D7)*1.05), MIN(MAX($C7 * (($F$3/$C$3) ^ (LOG($D7/$C7) / LOG($D$3/$C$3))), MIN($C7,$D7)*0.97), MAX($C7,$D7)*1.05))) -> 34.92 | J7: =1.1*I7 -> 38.412 | K7: =Calculatie!D29 -> #DIV/0!
A8: 4 | B8: Terrein | C8: 88 | D8: 95 | F8: =IF(OR($F$3="",$C$3="",$D$3="",$D$3=$C$3),"",MIN(MAX($C8+($D8-$C8)*(($F$3-$C$3)/($D$3-$C$3)),MAX($C8*0.97,$D8*0.97)),MAX($C8,$D8)*1.05)) -> 99.75 | H8: =0.9*I8 -> 89.775 | I8: =IF(OR($F$3="", $C$3="", $D$3="", $D$3=$C$3, $C$3<=0, $D$3<=0), "", IF(OR($C8<=0, $D8<=0), MIN(MAX($C8 + ($D8-$C8)*(($F$3-$C$3)/($D$3-$C$3)), MIN($C8,$D8)*0.97), MAX($C8,$D8)*1.05), MIN(MAX($C8 * (($F$3/$C$3) ^ (LOG($D8/$C8) / LOG($D$3/$C$3))), MIN($C8,$D8)*0.97), MAX($C8,$D8)*1.05))) -> 99.75 | J8: =1.1*I8 -> 109.725 | K8: =Calculatie!D30 -> #DIV/0!
A9: 5 | B9: Indirecte bouwkosten | C9: 385 | D9: 348 | F9: =IF(OR($F$3="",$C$3="",$D$3="",$D$3=$C$3),"",MIN(MAX($C9+($D9-$C9)*(($F$3-$C$3)/($D$3-$C$3)),MAX($C9*0.97,$D9*0.97)),MAX($C9,$D9)*1.05)) -> 373.45 | H9: =0.9*I9 -> 303.804 | I9: =IF(OR($F$3="", $C$3="", $D$3="", $D$3=$C$3, $C$3<=0, $D$3<=0), "", IF(OR($C9<=0, $D9<=0), MIN(MAX($C9 + ($D9-$C9)*(($F$3-$C$3)/($D$3-$C$3)), MIN($C9,$D9)*0.97), MAX($C9,$D9)*1.05), MIN(MAX($C9 * (($F$3/$C$3) ^ (LOG($D9/$C9) / LOG($D$3/$C$3))), MIN($C9,$D9)*0.97), MAX($C9,$D9)*1.05))) -> 337.56 | J9: =1.1*I9 -> 371.316 | K9: =Calculatie!D31 -> #DIV/0!
A10: 6 | B10: Bouwkosten | C10: 2302 | D10: 2077 | F10: =IF(OR($F$3="",$C$3="",$D$3="",$D$3=$C$3),"",MIN(MAX($C10+($D10-$C10)*(($F$3-$C$3)/($D$3-$C$3)),MAX($C10*0.97,$D10*0.97)),MAX($C10,$D10)*1.05)) -> 2232.94 | H10: =0.9*I10 -> 1813.221 | I10: =IF(OR($F$3="", $C$3="", $D$3="", $D$3=$C$3, $C$3<=0, $D$3<=0), "", IF(OR($C10<=0, $D10<=0), MIN(MAX($C10 + ($D10-$C10)*(($F$3-$C$3)/($D$3-$C$3)), MIN($C10,$D10)*0.97), MAX($C10,$D10)*1.05), MIN(MAX($C10 * (($F$3/$C$3) ^ (LOG($D10/$C10) / LOG($D$3/$C$3))), MIN($C10,$D10)*0.97), MAX($C10,$D10)*1.05))) -> 2014.69 | J10: =1.1*I10 -> 2216.159 | K10: =Calculatie!D32 -> #DIV/0!
A11: 7 | B11: Bijkomende kosten | C11: 413 | D11: 373 | F11: =IF(OR($F$3="",$C$3="",$D$3="",$D$3=$C$3),"",MIN(MAX($C11+($D11-$C11)*(($F$3-$C$3)/($D$3-$C$3)),MAX($C11*0.97,$D11*0.97)),MAX($C11,$D11)*1.05)) -> 400.61 | H11: =0.9*I11 -> 325.629 | I11: =IF(OR($F$3="", $C$3="", $D$3="", $D$3=$C$3, $C$3<=0, $D$3<=0), "", IF(OR($C11<=0, $D11<=0), MIN(MAX($C11 + ($D11-$C11)*(($F$3-$C$3)/($D$3-$C$3)), MIN($C11,$D11)*0.97), MAX($C11,$D11)*1.05), MIN(MAX($C11 * (($F$3/$C$3) ^ (LOG($D11/$C11) / LOG($D$3/$C$3))), MIN($C11,$D11)*0.97), MAX($C11,$D11)*1.05))) -> 361.81 | J11: =1.1*I11 -> 397.991 | K11: =Calculatie!D33 -> #DIV/0!
A12: 8 | B12: Belasting | C12: 567 | D12: 512 | F12: =IF(OR($F$3="",$C$3="",$D$3="",$D$3=$C$3),"",MIN(MAX($C12+($D12-$C12)*(($F$3-$C$3)/($D$3-$C$3)),MAX($C12*0.97,$D12*0.97)),MAX($C12,$D12)*1.05)) -> 549.99 | H12: =0.9*I12 -> 446.976 | I12: =IF(OR($F$3="", $C$3="", $D$3="", $D$3=$C$3, $C$3<=0, $D$3<=0), "", IF(OR($C12<=0, $D12<=0), MIN(MAX($C12 + ($D12-$C12)*(($F$3-$C$3)/($D$3-$C$3)), MIN($C12,$D12)*0.97), MAX($C12,$D12)*1.05), MIN(MAX($C12 * (($F$3/$C$3) ^ (LOG($D12/$C12) / LOG($D$3/$C$3))), MIN($C12,$D12)*0.97), MAX($C12,$D12)*1.05))) -> 496.64 | J12: =1.1*I12 -> 546.304 | K12: =Calculatie!D34 -> #DIV/0!
A13: 9 | B13: Investeringskosten (incl btw) | C13: 3283 | D13: 2962 | F13: =IF(OR($F$3="",$C$3="",$D$3="",$D$3=$C$3),"",MIN(MAX($C13+($D13-$C13)*(($F$3-$C$3)/($D$3-$C$3)),MAX($C13*0.97,$D13*0.97)),MAX($C13,$D13)*1.05)) -> 3184.51 | H13: =0.9*I13 -> 2585.826 | I13: =IF(OR($F$3="", $C$3="", $D$3="", $D$3=$C$3, $C$3<=0, $D$3<=0), "", IF(OR($C13<=0, $D13<=0), MIN(MAX($C13 + ($D13-$C13)*(($F$3-$C$3)/($D$3-$C$3)), MIN($C13,$D13)*0.97), MAX($C13,$D13)*1.05), MIN(MAX($C13 * (($F$3/$C$3) ^ (LOG($D13/$C13) / LOG($D$3/$C$3))), MIN($C13,$D13)*0.97), MAX($C13,$D13)*1.05))) -> 2873.14 | J13: =1.1*I13 -> 3160.454 | K13: =Calculatie!D35 -> #DIV/0!
B16: Toeslagen o.b.v. kwaliteitskader
B17: Energie neutraal | C17: 143 | D17: 138 | F17: =IF(OR($F$3="",$C$3="",$D$3="",$D$3=$C$3),"",MIN(MAX($C17+($D17-$C17)*(($F$3-$C$3)/($D$3-$C$3)),MAX($C17*0.97,$D17*0.97)),MAX($C17,$D17)*1.05)) -> 138.71 | H17: =0.85*I17 -> 113.93765 | I17: =IF(OR($F$3="", $C$3="", $D$3="", $D$3=$C$3, $C$3<=0, $D$3<=0), "", IF(OR($C17<=0, $D17<=0), MIN(MAX($C17 + ($D17-$C17)*(($F$3-$C$3)/($D$3-$C$3)), MIN($C17,$D17)*0.97), MAX($C17,$D17)*1.05), MIN(MAX($C17 * (($F$3/$C$3) ^ (LOG($D17/$C17) / LOG($D$3/$C$3))), MIN($C17,$D17)*0.97), MAX($C17,$D17)*1.05))) -> 134.04429 | J17: =1.15*I17 -> 154.15094
B18: Duurzaamheid | C18: 212 | D18: 212 | F18: =IF(OR($F$3="",$C$3="",$D$3="",$D$3=$C$3),"",MIN(MAX($C18+($D18-$C18)*(($F$3-$C$3)/($D$3-$C$3)),MAX($C18*0.97,$D18*0.97)),MAX($C18,$D18)*1.05)) -> 212 | H18: =0.85*I18 -> 180.2 | I18: =IF(OR($F$3="", $C$3="", $D$3="", $D$3=$C$3, $C$3<=0, $D$3<=0), "", IF(OR($C18<=0, $D18<=0), MIN(MAX($C18 + ($D18-$C18)*(($F$3-$C$3)/($D$3-$C$3)), MIN($C18,$D18)*0.97), MAX($C18,$D18)*1.05), MIN(MAX($C18 * (($F$3/$C$3) ^ (LOG($D18/$C18) / LOG($D$3/$C$3))), MIN($C18,$D18)*0.97), MAX($C18,$D18)*1.05))) -> 212 | J18: =1.15*I18 -> 243.8
B19: Frisse scholen | C19: 233 | D19: 203 | F19: =IF(OR($F$3="",$C$3="",$D$3="",$D$3=$C$3),"",MIN(MAX($C19+($D19-$C19)*(($F$3-$C$3)/($D$3-$C$3)),MAX($C19*0.97,$D19*0.97)),MAX($C19,$D19)*1.05)) -> 226.01 | H19: =0.85*I19 -> 167.3735 | I19: =IF(OR($F$3="", $C$3="", $D$3="", $D$3=$C$3, $C$3<=0, $D$3<=0), "", IF(OR($C19<=0, $D19<=0), MIN(MAX($C19 + ($D19-$C19)*(($F$3-$C$3)/($D$3-$C$3)), MIN($C19,$D19)*0.97), MAX($C19,$D19)*1.05), MIN(MAX($C19 * (($F$3/$C$3) ^ (LOG($D19/$C19) / LOG($D$3/$C$3))), MIN($C19,$D19)*0.97), MAX($C19,$D19)*1.05))) -> 196.91 | J19: =1.15*I19 -> 226.4465
B20: Exploitatie | C20: 24 | D20: 20 | F20: =IF(OR($F$3="",$C$3="",$D$3="",$D$3=$C$3),"",MIN(MAX($C20+($D20-$C20)*(($F$3-$C$3)/($D$3-$C$3)),MAX($C20*0.97,$D20*0.97)),MAX($C20,$D20)*1.05)) -> 23.28 | H20: =0.85*I20 -> 16.49 | I20: =IF(OR($F$3="", $C$3="", $D$3="", $D$3=$C$3, $C$3<=0, $D$3<=0), "", IF(OR($C20<=0, $D20<=0), MIN(MAX($C20 + ($D20-$C20)*(($F$3-$C$3)/($D$3-$C$3)), MIN($C20,$D20)*0.97), MAX($C20,$D20)*1.05), MIN(MAX($C20 * (($F$3/$C$3) ^ (LOG($D20/$C20) / LOG($D$3/$C$3))), MIN($C20,$D20)*0.97), MAX($C20,$D20)*1.05))) -> 19.4 | J20: =1.15*I20 -> 22.31
B21: ICT | C21: 5 | D21: 5 | F21: =IF(OR($F$3="",$C$3="",$D$3="",$D$3=$C$3),"",MIN(MAX($C21+($D21-$C21)*(($F$3-$C$3)/($D$3-$C$3)),MAX($C21*0.97,$D21*0.97)),MAX($C21,$D21)*1.05)) -> 5 | H21: =0.85*I21 -> 4.25 | I21: =IF(OR($F$3="", $C$3="", $D$3="", $D$3=$C$3, $C$3<=0, $D$3<=0), "", IF(OR($C21<=0, $D21<=0), MIN(MAX($C21 + ($D21-$C21)*(($F$3-$C$3)/($D$3-$C$3)), MIN($C21,$D21)*0.97), MAX($C21,$D21)*1.05), MIN(MAX($C21 * (($F$3/$C$3) ^ (LOG($D21/$C21) / LOG($D$3/$C$3))), MIN($C21,$D21)*0.97), MAX($C21,$D21)*1.05))) -> 5 | J21: =1.15*I21 -> 5.75
B22: Kwaliteit buitenruimte | C22: 96 | D22: 100 | F22: =IF(OR($F$3="",$C$3="",$D$3="",$D$3=$C$3),"",MIN(MAX($C22+($D22-$C22)*(($F$3-$C$3)/($D$3-$C$3)),MAX($C22*0.97,$D22*0.97)),MAX($C22,$D22)*1.05)) -> 105 | H22: =0.85*I22 -> 87.88325 | I22: =IF(OR($F$3="", $C$3="", $D$3="", $D$3=$C$3, $C$3<=0, $D$3<=0), "", IF(OR($C22<=0, $D22<=0), MIN(MAX($C22 + ($D22-$C22)*(($F$3-$C$3)/($D$3-$C$3)), MIN($C22,$D22)*0.97), MAX($C22,$D22)*1.05), MIN(MAX($C22 * (($F$3/$C$3) ^ (LOG($D22/$C22) / LOG($D$3/$C$3))), MIN($C22,$D22)*0.97), MAX($C22,$D22)*1.05))) -> 103.39206 | J22: =1.15*I22 -> 118.90087
B23: Overig | C23: 113 | D23: 83 | F23: =IF(OR($F$3="",$C$3="",$D$3="",$D$3=$C$3),"",MIN(MAX($C23+($D23-$C23)*(($F$3-$C$3)/($D$3-$C$3)),MAX($C23*0.97,$D23*0.97)),MAX($C23,$D23)*1.05)) -> 109.61 | H23: =0.85*I23 -> 68.4335 | I23: =IF(OR($F$3="", $C$3="", $D$3="", $D$3=$C$3, $C$3<=0, $D$3<=0), "", IF(OR($C23<=0, $D23<=0), MIN(MAX($C23 + ($D23-$C23)*(($F$3-$C$3)/($D$3-$C$3)), MIN($C23,$D23)*0.97), MAX($C23,$D23)*1.05), MIN(MAX($C23 * (($F$3/$C$3) ^ (LOG($D23/$C23) / LOG($D$3/$C$3))), MIN($C23,$D23)*0.97), MAX($C23,$D23)*1.05))) -> 80.51 | J23: =1.15*I23 -> 92.5865
B24: Totaal aanvullend (incl BTW) | C24: 826 | D24: 762 | F24: =IF(OR($F$3="",$C$3="",$D$3="",$D$3=$C$3),"",MIN(MAX($C24+($D24-$C24)*(($F$3-$C$3)/($D$3-$C$3)),MAX($C24*0.97,$D24*0.97)),MAX($C24,$D24)*1.05)) -> 801.22 | H24: =0.85*I24 -> 628.269 | I24: =IF(OR($F$3="", $C$3="", $D$3="", $D$3=$C$3, $C$3<=0, $D$3<=0), "", IF(OR($C24<=0, $D24<=0), MIN(MAX($C24 + ($D24-$C24)*(($F$3-$C$3)/($D$3-$C$3)), MIN($C24,$D24)*0.97), MAX($C24,$D24)*1.05), MIN(MAX($C24 * (($F$3/$C$3) ^ (LOG($D24/$C24) / LOG($D$3/$C$3))), MIN($C24,$D24)*0.97), MAX($C24,$D24)*1.05))) -> 739.14 | J24: =1.15*I24 -> 850.011
B28: Toeslagen o.b.v. eigen berekening POM
B29: Voldoen aan NEN9120 | K29: =Elementclusters!N41 -> 0
B30: BBL, A, B of C | K30: =Elementclusters!N42 -> 0
B31: BENG, Frisse scholen Engergie klasse A,B of C, ENG of 0 op de meter | K31: =Elementclusters!N43 -> 0
B32: Aandeel biobased hergebruikt of gerecycled | K32: =Elementclusters!N44 -> 16.443894
B33: Losmaakbaarheidsindex | K33: =Elementclusters!N45 -> 24.665841
B34: Subbemetering | K34: =Elementclusters!N46 -> 0
B35: Afvalwater hergebruiksysteem | K35: =Elementclusters!N47 -> 0
B36: Grijswatersysteem | K36: =Elementclusters!N48 -> 0
B37: Groendak | K37: =Elementclusters!N49 -> 0
B38: Waterretentie systeem | K38: =Elementclusters!N50 -> 0
B39: Extra beveiligingsmaatregelen | K39: =Elementclusters!N51 -> 0
B40: Toegangscontrolesysteem | K40: =Elementclusters!N52 -> 0
... B43: Slim gebouw | K43: =Elementclusters!N55 -> 0
B44: Totaal aanvullend (incl BTW) | K44: =SUM(K29:K43) -> 41.109735
B46: Exploitatie (40 jaar)
B47: Heffingen | C47: 13 | D47: 11 | F47: =IF(OR($F$3="",$C$3="",$D$3="",$D$3=$C$3),"",MIN(MAX($C47+($D47-$C47)*(($F$3-$C$3)/($D$3-$C$3)),MAX($C47*0.97,$D47*0.97)),MAX($C47,$D47)*1.05)) -> 12.61 | H47: =0.85*I47 -> 9.0695 | I47: =IF(OR($F$3="", $C$3="", $D$3="", $D$3=$C$3, $C$3<=0, $D$3<=0), "", IF(OR($C47<=0, $D47<=0), MIN(MAX($C47 + ($D47-$C47)*(($F$3-$C$3)/($D$3-$C$3)), MIN($C47,$D47)*0.97), MAX($C47,$D47)*1.05), MIN(MAX($C47 * (($F$3/$C$3) ^ (LOG($D47/$C47) / LOG($D$3/$C$3))), MIN($C47,$D47)*0.97), MAX($C47,$D47)*1.05))) -> 10.67 | J47: =1.15*I47 -> 12.2705 | K47: =Elementclusters!N73 -> 10.67
B48: Verzekeringen | C48: 6 | D48: 5 | F48: =IF(OR($F$3="",$C$3="",$D$3="",$D$3=$C$3),"",MIN(MAX($C48+($D48-$C48)*(($F$3-$C$3)/($D$3-$C$3)),MAX($C48*0.97,$D48*0.97)),MAX($C48,$D48)*1.05)) -> 5.82 | H48: =0.85*I48 -> 4.1225 | I48: =IF(OR($F$3="", $C$3="", $D$3="", $D$3=$C$3, $C$3<=0, $D$3<=0), "", IF(OR($C48<=0, $D48<=0), MIN(MAX($C48 + ($D48-$C48)*(($F$3-$C$3)/($D$3-$C$3)), MIN($C48,$D48)*0.97), MAX($C48,$D48)*1.05), MIN(MAX($C48 * (($F$3/$C$3) ^ (LOG($D48/$C48) / LOG($D$3/$C$3))), MIN($C48,$D48)*0.97), MAX($C48,$D48)*1.05))) -> 4.85 | J48: =1.15*I48 -> 5.5775 | K48: =Elementclusters!N74 -> 4.85
B49: Onderhoud | C49: 54 | D49: 47 | F49: =IF(OR($F$3="",$C$3="",$D$3="",$D$3=$C$3),"",MIN(MAX($C49+($D49-$C49)*(($F$3-$C$3)/($D$3-$C$3)),MAX($C49*0.97,$D49*0.97)),MAX($C49,$D49)*1.05)) -> 52.38 | H49: =0.85*I49 -> 38.7515 | I49: =IF(OR($F$3="", $C$3="", $D$3="", $D$3=$C$3, $C$3<=0, $D$3<=0), "", IF(OR($C49<=0, $D49<=0), MIN(MAX($C49 + ($D49-$C49)*(($F$3-$C$3)/($D$3-$C$3)), MIN($C49,$D49)*0.97), MAX($C49,$D49)*1.05), MIN(MAX($C49 * (($F$3/$C$3) ^ (LOG($D49/$C49) / LOG($D$3/$C$3))), MIN($C49,$D49)*0.97), MAX($C49,$D49)*1.05))) -> 45.59 | J49: =1.15*I49 -> 52.4285 | K49: =Elementclusters!N75 -> 47.4136
B50: Verbruik | C50: 13 | D50: 13 | F50: =IF(OR($F$3="",$C$3="",$D$3="",$D$3=$C$3),"",MIN(MAX($C50+($D50-$C50)*(($F$3-$C$3)/($D$3-$C$3)),MAX($C50*0.97,$D50*0.97)),MAX($C50,$D50)*1.05)) -> 13 | H50: =0.85*I50 -> 11.05 | I50: =IF(OR($F$3="", $C$3="", $D$3="", $D$3=$C$3, $C$3<=0, $D$3<=0), "", IF(OR($C50<=0, $D50<=0), MIN(MAX($C50 + ($D50-$C50)*(($F$3-$C$3)/($D$3-$C$3)), MIN($C50,$D50)*0.97), MAX($C50,$D50)*1.05), MIN(MAX($C50 * (($F$3/$C$3) ^ (LOG($D50/$C50) / LOG($D$3/$C$3))), MIN($C50,$D50)*0.97), MAX($C50,$D50)*1.05))) -> 13 | J50: =1.15*I50 -> 14.95 | K50: =Elementclusters!N76 -> 11.96
B51: Beheerskosten | C51: 0 | D51: 0 | F51: =IF(OR($F$3="",$C$3="",$D$3="",$D$3=$C$3),"",MIN(MAX($C51+($D51-$C51)*(($F$3-$C$3)/($D$3-$C$3)),MAX($C51*0.97,$D51*0.97)),MAX($C51,$D51)*1.05)) -> 0 | H51: =0.85*I51 -> 0 | I51: =IF(OR($F$3="", $C$3="", $D$3="", $D$3=$C$3, $C$3<=0, $D$3<=0), "", IF(OR($C51<=0, $D51<=0), MIN(MAX($C51 + ($D51-$C51)*(($F$3-$C$3)/($D$3-$C$3)), MIN($C51,$D51)*0.97), MAX($C51,$D51)*1.05), MIN(MAX($C51 * (($F$3/$C$3) ^ (LOG($D51/$C51) / LOG($D$3/$C$3))), MIN($C51,$D51)*0.97), MAX($C51,$D51)*1.05))) -> 0 | J51: =1.15*I51 -> 0 | K51: =Elementclusters!N77 -> 0
B52: Financieringskosten | C52: 0 | D52: 0 | F52: =IF(OR($F$3="",$C$3="",$D$3="",$D$3=$C$3),"",MIN(MAX($C52+($D52-$C52)*(($F$3-$C$3)/($D$3-$C$3)),MAX($C52*0.97,$D52*0.97)),MAX($C52,$D52)*1.05)) -> 0 | H52: =0.85*I52 -> 0 | I52: =IF(OR($F$3="", $C$3="", $D$3="", $D$3=$C$3, $C$3<=0, $D$3<=0), "", IF(OR($C52<=0, $D52<=0), MIN(MAX($C52 + ($D52-$C52)*(($F$3-$C$3)/($D$3-$C$3)), MIN($C52,$D52)*0.97), MAX($C52,$D52)*1.05), MIN(MAX($C52 * (($F$3/$C$3) ^ (LOG($D52/$C52) / LOG($D$3/$C$3))), MIN($C52,$D52)*0.97), MAX($C52,$D52)*1.05))) -> 0 | J52: =1.15*I52 -> 0 | K52: =Elementclusters!N78 -> 0
B53: Schoonmaakkosten | C53: 15 | D53: 14 | F53: =IF(OR($F$3="",$C$3="",$D$3="",$D$3=$C$3),"",MIN(MAX($C53+($D53-$C53)*(($F$3-$C$3)/($D$3-$C$3)),MAX($C53*0.97,$D53*0.97)),MAX($C53,$D53)*1.05)) -> 14.55 | H53: =0.85*I53 -> 11.543 | I53: =IF(OR($F$3="", $C$3="", $D$3="", $D$3=$C$3, $C$3<=0, $D$3<=0), "", IF(OR($C53<=0, $D53<=0), MIN(MAX($C53 + ($D53-$C53)*(($F$3-$C$3)/($D$3-$C$3)), MIN($C53,$D53)*0.97), MAX($C53,$D53)*1.05), MIN(MAX($C53 * (($F$3/$C$3) ^ (LOG($D53/$C53) / LOG($D$3/$C$3))), MIN($C53,$D53)*0.97), MAX($C53,$D53)*1.05))) -> 13.58 | J53: =1.15*I53 -> 15.617 | K53: =Elementclusters!N79 -> 13.58
B54: Totaal per m2 BVO/jaar (incl BTW) | C54: 100 | D54: 91 | F54: =IF(OR($F$3="",$C$3="",$D$3="",$D$3=$C$3),"",MIN(MAX($C54+($D54-$C54)*(($F$3-$C$3)/($D$3-$C$3)),MAX($C54*0.97,$D54*0.97)),MAX($C54,$D54)*1.05)) -> 97 | H54: =0.85*I54 -> 75.0295 | I54: =IF(OR($F$3="", $C$3="", $D$3="", $D$3=$C$3, $C$3<=0, $D$3<=0), "", IF(OR($C54<=0, $D54<=0), MIN(MAX($C54 + ($D54-$C54)*(($F$3-$C$3)/($D$3-$C$3)), MIN($C54,$D54)*0.97), MAX($C54,$D54)*1.05), MIN(MAX($C54 * (($F$3/$C$3) ^ (LOG($D54/$C54) / LOG($D$3/$C$3))), MIN($C54,$D54)*0.97), MAX($C54,$D54)*1.05))) -> 88.27 | J54: =1.15*I54 -> 101.5105 | K54: =Elementclusters!N80 -> 88.4736

Sheet TCO OUTPUT
A1: LCC — 40 years (rotated: items down, years across; CAPEX in Y1, OPEX in Y2..Y40)
A3: Analysis years | B3: 40
A4: Discount rate (per year) | B4: 0.04
A5: Escalation (per year) | B5: 0.03
A6: Area (m²) | B6: =INPUT!E3 -> 0
A7: Discount factors | E7: =1 -> 1 | F7: =1/(1+$B$4)^1 -> 0.96153846 | G7: =1/(1+$B$4)^2 -> 0.92455621 | H7: =1/(1+$B$4)^3 -> 0.88899636 | I7: =1/(1+$B$4)^4 -> 0.85480419 | J7: =1/(1+$B$4)^5 -> 0.82192711 | K7: =1/(1+$B$4)^6 -> 0.79031453 | L7: =1/(1+$B$4)^7 -> 0.75991781 | M7: =1/(1+$B$4)^8 -> 0.73069021 | N7: =1/(1+$B$4)^9 -> 0.70258674 | O7: =1/(1+$B$4)^10 -> 0.67556417 | P7: =1/(1+$B$4)^11 -> 0.64958093 | Q7: =1/(1+$B$4)^12 -> 0.62459705 | R7: =1/(1+$B$4)^13 -> 0.60057409 | S7: =1/(1+$B$4)^14 -> 0.57747508 | T7: =1/(1+$B$4)^15 -> 0.5552645 | U7: =1/(1+$B$4)^16 -> 0.53390818 | V7: =1/(1+$B$4)^17 -> 0.51337325 | W7: =1/(1+$B$4)^18 -> 0.49362812 | X7: =1/(1+$B$4)^19 -> 0.47464242 | Y7: =1/(1+$B$4)^20 -> 0.45638695 | Z7: =1/(1+$B$4)^21 -> 0.4388336 | AA7: =1/(1+$B$4)^22 -> 0.42195539 | AB7: =1/(1+$B$4)^23 -> 0.40572633 | AC7: =1/(1+$B$4)^24 -> 0.39012147 | AD7: =1/(1+$B$4)^25 -> 0.3751168 | AE7: =1/(1+$B$4)^26 -> 0.36068923 | AF7: =1/(1+$B$4)^27 -> 0.34681657 | AG7: =1/(1+$B$4)^28 -> 0.33347747 | AH7: =1/(1+$B$4)^29 -> 0.32065141 | AI7: =1/(1+$B$4)^30 -> 0.30831867 | AJ7: =1/(1+$B$4)^31 -> 0.29646026 | AK7: =1/(1+$B$4)^32 -> 0.28505794 | AL7: =1/(1+$B$4)^33 -> 0.27409417 | AM7: =1/(1+$B$4)^34 -> 0.26355209 | AN7: =1/(1+$B$4)^35 -> 0.25341547 | AO7: =1/(1+$B$4)^36 -> 0.24366872 | AP7: =1/(1+$B$4)^37 -> 0.23429685 | AQ7: =1/(1+$B$4)^38 -> 0.22528543 | AR7: =1/(1+$B$4)^39 -> 0.21662061
A8: Item | B8: PO BASIS B (baseline) | D8: Per m² (current) from PO BASIS G | E8: Year 0 | F8: Year 1 | G8: Year 2 | H8: Year 3 | I8: Year 4 | J8: Year 5 | K8: Year 6 | L8: Year 7 | M8: Year 8 | N8: Year 9 | O8: Year 10 | P8: Year 11 | Q8: Year 12 | R8: Year 13 | S8: Year 14 | T8: Year 15 | U8: Year 16 | V8: Year 17 | W8: Year 18 | X8: Year 19 | Y8: Year 20 | Z8: Year 21 | AA8: Year 22 | AB8: Year 23 | AC8: Year 24 | AD8: Year 25 | AE8: Year 26 | AF8: Year 27 | AG8: Year 28 | AH8: Year 29 | AI8: Year 30 | AJ8: Year 31 | AK8: Year 32 | AL8: Year 33 | AM8: Year 34 | AN8: Year 35 | AO8: Year 36 | AP8: Year 37 | AQ8: Year 38 | AR8: Year 39 | AS8: PV (sum of 0..40 years)
B9: CAPEX-BASIS (NEN2699)
A10: 1 | B10: ='PO BASIS'!$B$5 -> Bouwkundige werken | D10: ='PO BASIS'!$I$5 -> 1038.87 | E10: =IF($D10="", "", $D10*$B$6) -> 0 | F10: =0 -> 0 | G10: =0 -> 0 | H10: =0 -> 0 | I10: =0 -> 0 | J10: =0 -> 0 | K10: =0 -> 0 | L10: =0 -> 0 | M10: =0 -> 0 | ... AR10: =0 -> 0 | AS10: =IF($D10="", "", SUMPRODUCT(E10:AR10, E7:AR7)) -> 0
A11: 2 | B11: ='PO BASIS'!$B$6 -> Installatietechnische werken | D11: ='PO BASIS'!$I$6 -> 511.19 | E11: =IF($D11="", "", $D11*$B$6) -> 0 | F11: =0 -> 0 | G11: =0 -> 0 | H11: =0 -> 0 | I11: =0 -> 0 | J11: =0 -> 0 | K11: =0 -> 0 | L11: =0 -> 0 | M11: =0 -> 0 | ... AR11: =0 -> 0 | AS11: =IF($D11="", "", SUMPRODUCT(E11:AR11, E7:AR7)) -> 0
A12: 3 | B12: ='PO BASIS'!$B$7 -> Vaste inrichting | D12: ='PO BASIS'!$I$7 -> 34.92 | E12: =IF($D12="", "", $D12*$B$6) -> 0 | F12: =0 -> 0 | G12: =0 -> 0 | H12: =0 -> 0 | I12: =0 -> 0 | J12: =0 -> 0 | K12: =0 -> 0 | L12: =0 -> 0 | M12: =0 -> 0 | ... AR12: =0 -> 0 | AS12: =IF($D12="", "", SUMPRODUCT(E12:AR12, E7:AR7)) -> 0
A13: 4 | B13: ='PO BASIS'!$B$8 -> Terrein | D13: ='PO BASIS'!$I$8 -> 99.75 | E13: =IF($D13="", "", $D13*$B$6) -> 0 | F13: =0 -> 0 | G13: =0 -> 0 | H13: =0 -> 0 | I13: =0 -> 0 | J13: =0 -> 0 | K13: =0 -> 0 | L13: =0 -> 0 | M13: =0 -> 0 | ... AR13: =0 -> 0 | AS13: =IF($D13="", "", SUMPRODUCT(E13:AR13, E7:AR7)) -> 0
A14: 5 | B14: ='PO BASIS'!$B$9 -> Indirecte bouwkosten | D14: ='PO BASIS'!$I$9 -> 337.56 | E14: =IF($D14="", "", $D14*$B$6) -> 0 | F14: =0 -> 0 | G14: =0 -> 0 | H14: =0 -> 0 | I14: =0 -> 0 | J14: =0 -> 0 | K14: =0 -> 0 | L14: =0 -> 0 | M14: =0 -> 0 | ... AR14: =0 -> 0 | AS14: =IF($D14="", "", SUMPRODUCT(E14:AR14, E7:AR7)) -> 0
A15: 6 | B15: ='PO BASIS'!$B$11 -> Bijkomende kosten | D15: ='PO BASIS'!$I$11 -> 361.81 | E15: =IF($D15="", "", $D15*$B$6) -> 0 | F15: =0 -> 0 | G15: =0 -> 0 | H15: =0 -> 0 | I15: =0 -> 0 | J15: =0 -> 0 | K15: =0 -> 0 | L15: =0 -> 0 | M15: =0 -> 0 | ... AR15: =0 -> 0 | AS15: =IF($D15="", "", SUMPRODUCT(E15:AR15, E7:AR7)) -> 0
A16: 7 | B16: ='PO BASIS'!$B$12 -> Belasting | D16: ='PO BASIS'!$I$12 -> 496.64 | E16: =IF($D16="", "", $D16*$B$6) -> 0 | F16: =0 -> 0 | G16: =0 -> 0 | H16: =0 -> 0 | I16: =0 -> 0 | J16: =0 -> 0 | K16: =0 -> 0 | L16: =0 -> 0 | M16: =0 -> 0 | ... AR16: =0 -> 0 | AS16: =IF($D16="", "", SUMPRODUCT(E16:AR16, E7:AR7)) -> 0
B21: CAPEX-TOESLAGEN | C21: GEMAAKTE KEUZE:
A22: 8 | B22: ='PO BASIS'!B29 -> Voldoen aan NEN9120 | C22: =Elementclusters!C41 -> nee | D22: ='PO BASIS'!K29 -> 0 | E22: =IF($D22="", "", $D22*$B$6) -> 0 | F22: =0 -> 0 | G22: =0 -> 0 | H22: =0 -> 0 | I22: =0 -> 0 | J22: =0 -> 0 | K22: =0 -> 0 | L22: =0 -> 0 | M22: =0 -> 0 | ... AR22: =0 -> 0 | AS22: =IF($D22="", "", SUMPRODUCT(E22:AR22, E7:AR7)) -> 0
A23: 9 | B23: ='PO BASIS'!B30 -> BBL, A, B of C | C23: =Elementclusters!C42 -> BBL | D23: ='PO BASIS'!K30 -> 0 | E23: =IF($D23="", "", $D23*$B$6) -> 0 | F23: =0 -> 0 | G23: =0 -> 0 | H23: =0 -> 0 | I23: =0 -> 0 | J23: =0 -> 0 | K23: =0 -> 0 | L23: =0 -> 0 | M23: =0 -> 0 | ... AR23: =0 -> 0 | AS23: =IF($D23="", "", SUMPRODUCT(E23:AR23, E7:AR7)) -> 0
A24: 10 | B24: ='PO BASIS'!B31 -> BENG, Frisse scholen Engergie klasse A,B of C, ENG of 0 op de meter | C24: =Elementclusters!C43 -> BENG | D24: ='PO BASIS'!K31 -> 0 | E24: =IF($D24="", "", $D24*$B$6) -> 0 | F24: =0 -> 0 | G24: =0 -> 0 | H24: =0 -> 0 | I24: =0 -> 0 | J24: =0 -> 0 | K24: =0 -> 0 | L24: =0 -> 0 | M24: =0 -> 0 | ... AR24: =0 -> 0 | AS24: =IF($D24="", "", SUMPRODUCT(E24:AR24, E7:AR7)) -> 0
A25: 11 | B25: ='PO BASIS'!B32 -> Aandeel biobased hergebruikt of gerecycled | C25: =Elementclusters!C44 -> 15% | D25: ='PO BASIS'!K32 -> 16.443894 | E25: =IF($D25="", "", $D25*$B$6) -> 0 | F25: =0 -> 0 | G25: =0 -> 0 | H25: =0 -> 0 | I25: =0 -> 0 | J25: =0 -> 0 | K25: =0 -> 0 | L25: =0 -> 0 | M25: =0 -> 0 | ... AR25: =0 -> 0 | AS25: =IF($D25="", "", SUMPRODUCT(E25:AR25, E7:AR7)) -> 0
A26: 12 | B26: ='PO BASIS'!B33 -> Losmaakbaarheidsindex | C26: =Elementclusters!C45 -> 30% | D26: ='PO BASIS'!K33 -> 24.665841 | E26: =IF($D26="", "", $D26*$B$6) -> 0 | F26: =0 -> 0 | G26: =0 -> 0 | H26: =0 -> 0 | I26: =0 -> 0 | J26: =0 -> 0 | K26: =0 -> 0 | L26: =0 -> 0 | M26: =0 -> 0 | ... AR26: =0 -> 0 | AS26: =IF($D26="", "", SUMPRODUCT(E26:AR26, E7:AR7)) -> 0
A27: 13 | B27: ='PO BASIS'!B34 -> Subbemetering | C27: =Elementclusters!C46 -> nee | D27: ='PO BASIS'!K34 -> 0 | E27: =IF($D27="", "", $D27*$B$6) -> 0 | F27: =0 -> 0 | G27: =0 -> 0 | H27: =0 -> 0 | I27: =0 -> 0 | J27: =0 -> 0 | K27: =0 -> 0 | L27: =0 -> 0 | M27: =0 -> 0 | ... AR27: =0 -> 0 | AS27: =IF($D27="", "", SUMPRODUCT(E27:AR27, E7:AR7)) -> 0
A28: 14 | B28: ='PO BASIS'!B35 -> Afvalwater hergebruiksysteem | C28: =Elementclusters!C47 -> nee | D28: ='PO BASIS'!K35 -> 0 | E28: =IF($D28="", "", $D28*$B$6) -> 0 | F28: =0 -> 0 | G28: =0 -> 0 | H28: =0 -> 0 | I28: =0 -> 0 | J28: =0 -> 0 | K28: =0 -> 0 | L28: =0 -> 0 | M28: =0 -> 0 | ... AR28: =0 -> 0 | AS28: =IF($D28="", "", SUMPRODUCT(E28:AR28, E7:AR7)) -> 0
A29: 15 | B29: ='PO BASIS'!B36 -> Grijswatersysteem | C29: =Elementclusters!C48 -> nee | D29: ='PO BASIS'!K36 -> 0 | E29: =IF($D29="", "", $D29*$B$6) -> 0 | F29: =0 -> 0 | G29: =0 -> 0 | H29: =0 -> 0 | I29: =0 -> 0 | J29: =0 -> 0 | K29: =0 -> 0 | L29: =0 -> 0 | M29: =0 -> 0 | ... AR29: =0 -> 0 | AS29: =IF($D29="", "", SUMPRODUCT(E29:AR29, E8:AR8)) -> 0
A30: 16 | B30: ='PO BASIS'!B37 -> Groendak | C30: =Elementclusters!C49 -> nee | D30: ='PO BASIS'!K37 -> 0 | E30: =IF($D30="", "", $D30*$B$6) -> 0 | F30: =0 -> 0 | G30: =0 -> 0 | H30: =0 -> 0 | I30: =0 -> 0 | J30: =0 -> 0 | K30: =0 -> 0 | L30: =0 -> 0 | M30: =0 -> 0 | ... AR30: =0 -> 0 | AS30: =IF($D30="", "", SUMPRODUCT(E30:AR30, E9:AR9)) -> 0
A31: 17 | B31: ='PO BASIS'!B38 -> Waterretentie systeem | C31: =Elementclusters!C50 -> nee | D31: ='PO BASIS'!K38 -> 0 | E31: =IF($D31="", "", $D31*$B$6) -> 0 | F31: =0 -> 0 | G31: =0 -> 0 | H31: =0 -> 0 | I31: =0 -> 0 | J31: =0 -> 0 | K31: =0 -> 0 | L31: =0 -> 0 | M31: =0 -> 0 | ... AR31: =0 -> 0 | AS31: =IF($D31="", "", SUMPRODUCT(E31:AR31, E10:AR10)) -> 0
A32: 18 | B32: ='PO BASIS'!B39 -> Extra beveiligingsmaatregelen | C32: =Elementclusters!C51 -> nee | D32: ='PO BASIS'!K39 -> 0 | E32: =IF($D32="", "", $D32*$B$6) -> 0 | F32: =0 -> 0 | G32: =0 -> 0 | H32: =0 -> 0 | I32: =0 -> 0 | J32: =0 -> 0 | K32: =0 -> 0 | L32: =0 -> 0 | M32: =0 -> 0 | ... AR32: =0 -> 0 | AS32: =IF($D32="", "", SUMPRODUCT(E32:AR32, E11:AR11)) -> 0
A33: 19 | B33: ='PO BASIS'!B40 -> Toegangscontrolesysteem | C33: =Elementclusters!C52 -> nee | D33: ='PO BASIS'!K40 -> 0 | E33: =IF($D33="", "", $D33*$B$6) -> 0 | F33: =0 -> 0 | G33: =0 -> 0 | H33: =0 -> 0 | I33: =0 -> 0 | J33: =0 -> 0 | K33: =0 -> 0 | L33: =0 -> 0 | M33: =0 -> 0 | ... AR33: =0 -> 0 | AS33: =IF($D33="", "", SUMPRODUCT(E33:AR33, E12:AR12)) -> 0
A34: 20 | B34: ='PO BASIS'!B41 -> Camerasysteem | C34: =Elementclusters!C53 -> nee | D34: ='PO BASIS'!K41 -> 0 | E34: =IF($D34="", "", $D34*$B$6) -> 0 | F34: =0 -> 0 | G34: =0 -> 0 | H34: =0 -> 0 | I34: =0 -> 0 | J34: =0 -> 0 | K34: =0 -> 0 | L34: =0 -> 0 | M34: =0 -> 0 | ... AR34: =0 -> 0 | AS34: =IF($D34="", "", SUMPRODUCT(E34:AR34, E13:AR13)) -> 0
A35: 21 | B35: ='PO BASIS'!B42 -> Vandaalbestendigheidsmaatregelen | C35: =Elementclusters!C54 -> nee | D35: ='PO BASIS'!K42 -> 0 | E35: =IF($D35="", "", $D35*$B$6) -> 0 | F35: =0 -> 0 | G35: =0 -> 0 | H35: =0 -> 0 | I35: =0 -> 0 | J35: =0 -> 0 | K35: =0 -> 0 | L35: =0 -> 0 | M35: =0 -> 0 | ... AR35: =0 -> 0 | AS35: =IF($D35="", "", SUMPRODUCT(E35:AR35, E14:AR14)) -> 0
A36: 22 | B36: ='PO BASIS'!B43 -> Slim gebouw | C36: =Elementclusters!C55 -> nee | D36: ='PO BASIS'!K43 -> 0 | E36: =IF($D36="", "", $D36*$B$6) -> 0 | F36: =0 -> 0 | G36: =0 -> 0 | H36: =0 -> 0 | I36: =0 -> 0 | J36: =0 -> 0 | K36: =0 -> 0 | L36: =0 -> 0 | M36: =0 -> 0 | ... AR36: =0 -> 0 | AS36: =IF($D36="", "", SUMPRODUCT(E36:AR36, E15:AR15)) -> 0
B40: OPEX
A41: 23 | B41: ='PO BASIS'!$B$47 -> Heffingen | D41: ='PO BASIS'!$K$47 -> 10.67 | E41: =0 -> 0 | F41: =IF($D41="", "", $D41*(1+$B$5)^0*$B$6) -> 0 | G41: =IF($D41="", "", $D41*(1+$B$5)^1*$B$6) -> 0 | H41: =IF($D41="", "", $D41*(1+$B$5)^2*$B$6) -> 0 | I41: =IF($D41="", "", $D41*(1+$B$5)^3*$B$6) -> 0 | J41: =IF($D41="", "", $D41*(1+$B$5)^4*$B$6) -> 0 | K41: =IF($D41="", "", $D41*(1+$B$5)^5*$B$6) -> 0 | L41: =IF($D41="", "", $D41*(1+$B$5)^6*$B$6) -> 0 | M41: =IF($D41="", "", $D41*(1+$B$5)^7*$B$6) -> 0 | N41: =IF($D41="", "", $D41*(1+$B$5)^8*$B$6) -> 0 | O41: =IF($D41="", "", $D41*(1+$B$5)^9*$B$6) -> 0 | P41: =IF($D41="", "", $D41*(1+$B$5)^10*$B$6) -> 0 | Q41: =IF($D41="", "", $D41*(1+$B$5)^11*$B$6) -> 0 | R41: =IF($D41="", "", $D41*(1+$B$5)^12*$B$6) -> 0 | S41: =IF($D41="", "", $D41*(1+$B$5)^13*$B$6) -> 0 | T41: =IF($D41="", "", $D41*(1+$B$5)^14*$B$6) -> 0 | U41: =IF($D41="", "", $D41*(1+$B$5)^15*$B$6) -> 0 | V41: =IF($D41="", "", $D41*(1+$B$5)^16*$B$6) -> 0 | W41: =IF($D41="", "", $D41*(1+$B$5)^17*$B$6) -> 0 | X41: =IF($D41="", "", $D41*(1+$B$5)^18*$B$6) -> 0 | Y41: =IF($D41="", "", $D41*(1+$B$5)^19*$B$6) -> 0 | Z41: =IF($D41="", "", $D41*(1+$B$5)^20*$B$6) -> 0 | AA41: =IF($D41="", "", $D41*(1+$B$5)^21*$B$6) -> 0 | AB41: =IF($D41="", "", $D41*(1+$B$5)^22*$B$6) -> 0 | AC41: =IF($D41="", "", $D41*(1+$B$5)^23*$B$6) -> 0 | AD41: =IF($D41="", "", $D41*(1+$B$5)^24*$B$6) -> 0 | AE41: =IF($D41="", "", $D41*(1+$B$5)^25*$B$6) -> 0 | AF41: =IF($D41="", "", $D41*(1+$B$5)^26*$B$6) -> 0 | AG41: =IF($D41="", "", $D41*(1+$B$5)^27*$B$6) -> 0 | AH41: =IF($D41="", "", $D41*(1+$B$5)^28*$B$6) -> 0 | AI41: =IF($D41="", "", $D41*(1+$B$5)^29*$B$6) -> 0 | AJ41: =IF($D41="", "", $D41*(1+$B$5)^30*$B$6) -> 0 | AK41: =IF($D41="", "", $D41*(1+$B$5)^31*$B$6) -> 0 | AL41: =IF($D41="", "", $D41*(1+$B$5)^32*$B$6) -> 0 | AM41: =IF($D41="", "", $D41*(1+$B$5)^33*$B$6) -> 0 | AN41: =IF($D41="", "", $D41*(1+$B$5)^34*$B$6) -> 0 | AO41: =IF($D41="", "", $D41*(1+$B$5)^35*$B$6) -> 0 | AP41: =IF($D41="", "", $D41*(1+$B$5)^36*$B$6) -> 0 | AQ41: =IF($D41="", "", $D41*(1+$B$5)^37*$B$6) -> 0 | AR41: =IF($D41="", "", $D41*(1+$B$5)^38*$B$6) -> 0 | AS41: =IF($D41="", "", SUMPRODUCT(E41:AR41, E7:AR7)) -> 0
A42: 24 | B42: ='PO BASIS'!$B$48 -> Verzekeringen | D42: ='PO BASIS'!$K$48 -> 4.85 | E42: =0 -> 0 | F42: =IF($D42="", "", $D42*(1+$B$5)^0*$B$6) -> 0 | G42: =IF($D42="", "", $D42*(1+$B$5)^1*$B$6) -> 0 | H42: =IF($D42="", "", $D42*(1+$B$5)^2*$B$6) -> 0 | I42: =IF($D42="", "", $D42*(1+$B$5)^3*$B$6) -> 0 | J42: =IF($D42="", "", $D42*(1+$B$5)^4*$B$6) -> 0 | K42: =IF($D42="", "", $D42*(1+$B$5)^5*$B$6) -> 0 | L42: =IF($D42="", "", $D42*(1+$B$5)^6*$B$6) -> 0 | M42: =IF($D42="", "", $D42*(1+$B$5)^7*$B$6) -> 0 | N42: =IF($D42="", "", $D42*(1+$B$5)^8*$B$6) -> 0 | O42: =IF($D42="", "", $D42*(1+$B$5)^9*$B$6) -> 0 | P42: =IF($D42="", "", $D42*(1+$B$5)^10*$B$6) -> 0 | Q42: =IF($D42="", "", $D42*(1+$B$5)^11*$B$6) -> 0 | R42: =IF($D42="", "", $D42*(1+$B$5)^12*$B$6) -> 0 | S42: =IF($D42="", "", $D42*(1+$B$5)^13*$B$6) -> 0 | T42: =IF($D42="", "", $D42*(1+$B$5)^14*$B$6) -> 0 | U42: =IF($D42="", "", $D42*(1+$B$5)^15*$B$6) -> 0 | V42: =IF($D42="", "", $D42*(1+$B$5)^16*$B$6) -> 0 | W42: =IF($D42="", "", $D42*(1+$B$5)^17*$B$6) -> 0 | X42: =IF($D42="", "", $D42*(1+$B$5)^18*$B$6) -> 0 | Y42: =IF($D42="", "", $D42*(1+$B$5)^19*$B$6) -> 0 | Z42: =IF($D42="", "", $D42*(1+$B$5)^20*$B$6) -> 0 | AA42: =IF($D42="", "", $D42*(1+$B$5)^21*$B$6) -> 0 | AB42: =IF($D42="", "", $D42*(1+$B$5)^22*$B$6) -> 0 | AC42: =IF($D42="", "", $D42*(1+$B$5)^23*$B$6) -> 0 | AD42: =IF($D42="", "", $D42*(1+$B$5)^24*$B$6) -> 0 | AE42: =IF($D42="", "", $D42*(1+$B$5)^25*$B$6) -> 0 | AF42: =IF($D42="", "", $D42*(1+$B$5)^26*$B$6) -> 0 | AG42: =IF($D42="", "", $D42*(1+$B$5)^27*$B$6) -> 0 | AH42: =IF($D42="", "", $D42*(1+$B$5)^28*$B$6) -> 0 | AI42: =IF($D42="", "", $D42*(1+$B$5)^29*$B$6) -> 0 | AJ42: =IF($D42="", "", $D42*(1+$B$5)^30*$B$6) -> 0 | AK42: =IF($D42="", "", $D42*(1+$B$5)^31*$B$6) -> 0 | AL42: =IF($D42="", "", $D42*(1+$B$5)^32*$B$6) -> 0 | AM42: =IF($D42="", "", $D42*(1+$B$5)^33*$B$6) -> 0 | AN42: =IF($D42="", "", $D42*(1+$B$5)^34*$B$6) -> 0 | AO42: =IF($D42="", "", $D42*(1+$B$5)^35*$B$6) -> 0 | AP42: =IF($D42="", "", $D42*(1+$B$5)^36*$B$6) -> 0 | AQ42: =IF($D42="", "", $D42*(1+$B$5)^37*$B$6) -> 0 | AR42: =IF($D42="", "", $D42*(1+$B$5)^38*$B$6) -> 0 | AS42: =IF($D42="", "", SUMPRODUCT(E42:AR42, E7:AR7)) -> 0
A43: 25 | B43: ='PO BASIS'!$B$49 -> Onderhoud | D43: ='PO BASIS'!$K$49 -> 47.4136 | E43: =0 -> 0 | F43: =IF($D43="", "", $D43*(1+$B$5)^0*$B$6) -> 0 | G43: =IF($D43="", "", $D43*(1+$B$5)^1*$B$6) -> 0 | H43: =IF($D43="", "", $D43*(1+$B$5)^2*$B$6) -> 0 | I43: =IF($D43="", "", $D43*(1+$B$5)^3*$B$6) -> 0 | J43: =IF($D43="", "", $D43*(1+$B$5)^4*$B$6) -> 0 | K43: =IF($D43="", "", $D43*(1+$B$5)^5*$B$6) -> 0 | L43: =IF($D43="", "", $D43*(1+$B$5)^6*$B$6) -> 0 | M43: =IF($D43="", "", $D43*(1+$B$5)^7*$B$6) -> 0 | N43: =IF($D43="", "", $D43*(1+$B$5)^8*$B$6) -> 0 | O43: =IF($D43="", "", $D43*(1+$B$5)^9*$B$6) -> 0 | P43: =IF($D43="", "", $D43*(1+$B$5)^10*$B$6) -> 0 | Q43: =IF($D43="", "", $D43*(1+$B$5)^11*$B$6) -> 0 | R43: =IF($D43="", "", $D43*(1+$B$5)^12*$B$6) -> 0 | S43: =IF($D43="", "", $D43*(1+$B$5)^13*$B$6) -> 0 | T43: =IF($D43="", "", $D43*(1+$B$5)^14*$B$6) -> 0 | U43: =IF($D43="", "", $D43*(1+$B$5)^15*$B$6) -> 0 | V43: =IF($D43="", "", $D43*(1+$B$5)^16*$B$6) -> 0 | W43: =IF($D43="", "", $D43*(1+$B$5)^17*$B$6) -> 0 | X43: =IF($D43="", "", $D43*(1+$B$5)^18*$B$6) -> 0 | Y43: =IF($D43="", "", $D43*(1+$B$5)^19*$B$6) -> 0 | Z43: =IF($D43="", "", $D43*(1+$B$5)^20*$B$6) -> 0 | AA43: =IF($D43="", "", $D43*(1+$B$5)^21*$B$6) -> 0 | AB43: =IF($D43="", "", $D43*(1+$B$5)^22*$B$6) -> 0 | AC43: =IF($D43="", "", $D43*(1+$B$5)^23*$B$6) -> 0 | AD43: =IF($D43="", "", $D43*(1+$B$5)^24*$B$6) -> 0 | AE43: =IF($D43="", "", $D43*(1+$B$5)^25*$B$6) -> 0 | AF43: =IF($D43="", "", $D43*(1+$B$5)^26*$B$6) -> 0 | AG43: =IF($D43="", "", $D43*(1+$B$5)^27*$B$6) -> 0 | AH43: =IF($D43="", "", $D43*(1+$B$5)^28*$B$6) -> 0 | AI43: =IF($D43="", "", $D43*(1+$B$5)^29*$B$6) -> 0 | AJ43: =IF($D43="", "", $D43*(1+$B$5)^30*$B$6) -> 0 | AK43: =IF($D43="", "", $D43*(1+$B$5)^31*$B$6) -> 0 | AL43: =IF($D43="", "", $D43*(1+$B$5)^32*$B$6) -> 0 | AM43: =IF($D43="", "", $D43*(1+$B$5)^33*$B$6) -> 0 | AN43: =IF($D43="", "", $D43*(1+$B$5)^34*$B$6) -> 0 | AO43: =IF($D43="", "", $D43*(1+$B$5)^35*$B$6) -> 0 | AP43: =IF($D43="", "", $D43*(1+$B$5)^36*$B$6) -> 0 | AQ43: =IF($D43="", "", $D43*(1+$B$5)^37*$B$6) -> 0 | AR43: =IF($D43="", "", $D43*(1+$B$5)^38*$B$6) -> 0 | AS43: =IF($D43="", "", SUMPRODUCT(E43:AR43, E7:AR7)) -> 0
A44: 26 | B44: ='PO BASIS'!$B$50 -> Verbruik | D44: ='PO BASIS'!$K$50 -> 11.96 | E44: =0 -> 0 | F44: =IF($D44="", "", $D44*(1+$B$5)^0*$B$6) -> 0 | G44: =IF($D44="", "", $D44*(1+$B$5)^1*$B$6) -> 0 | H44: =IF($D44="", "", $D44*(1+$B$5)^2*$B$6) -> 0 | I44: =IF($D44="", "", $D44*(1+$B$5)^3*$B$6) -> 0 | J44: =IF($D44="", "", $D44*(1+$B$5)^4*$B$6) -> 0 | K44: =IF($D44="", "", $D44*(1+$B$5)^5*$B$6) -> 0 | L44: =IF($D44="", "", $D44*(1+$B$5)^6*$B$6) -> 0 | M44: =IF($D44="", "", $D44*(1+$B$5)^7*$B$6) -> 0 | N44: =IF($D44="", "", $D44*(1+$B$5)^8*$B$6) -> 0 | O44: =IF($D44="", "", $D44*(1+$B$5)^9*$B$6) -> 0 | P44: =IF($D44="", "", $D44*(1+$B$5)^10*$B$6) -> 0 | Q44: =IF($D44="", "", $D44*(1+$B$5)^11*$B$6) -> 0 | R44: =IF($D44="", "", $D44*(1+$B$5)^12*$B$6) -> 0 | S44: =IF($D44="", "", $D44*(1+$B$5)^13*$B$6) -> 0 | T44: =IF($D44="", "", $D44*(1+$B$5)^14*$B$6) -> 0 | U44: =IF($D44="", "", $D44*(1+$B$5)^15*$B$6) -> 0 | V44: =IF($D44="", "", $D44*(1+$B$5)^16*$B$6) -> 0 | W44: =IF($D44="", "", $D44*(1+$B$5)^17*$B$6) -> 0 | X44: =IF($D44="", "", $D44*(1+$B$5)^18*$B$6) -> 0 | Y44: =IF($D44="", "", $D44*(1+$B$5)^19*$B$6) -> 0 | Z44: =IF($D44="", "", $D44*(1+$B$5)^20*$B$6) -> 0 | AA44: =IF($D44="", "", $D44*(1+$B$5)^21*$B$6) -> 0 | AB44: =IF($D44="", "", $D44*(1+$B$5)^22*$B$6) -> 0 | AC44: =IF($D44="", "", $D44*(1+$B$5)^23*$B$6) -> 0 | AD44: =IF($D44="", "", $D44*(1+$B$5)^24*$B$6) -> 0 | AE44: =IF($D44="", "", $D44*(1+$B$5)^25*$B$6) -> 0 | AF44: =IF($D44="", "", $D44*(1+$B$5)^26*$B$6) -> 0 | AG44: =IF($D44="", "", $D44*(1+$B$5)^27*$B$6) -> 0 | AH44: =IF($D44="", "", $D44*(1+$B$5)^28*$B$6) -> 0 | AI44: =IF($D44="", "", $D44*(1+$B$5)^29*$B$6) -> 0 | AJ44: =IF($D44="", "", $D44*(1+$B$5)^30*$B$6) -> 0 | AK44: =IF($D44="", "", $D44*(1+$B$5)^31*$B$6) -> 0 | AL44: =IF($D44="", "", $D44*(1+$B$5)^32*$B$6) -> 0 | AM44: =IF($D44="", "", $D44*(1+$B$5)^33*$B$6) -> 0 | AN44: =IF($D44="", "", $D44*(1+$B$5)^34*$B$6) -> 0 | AO44: =IF($D44="", "", $D44*(1+$B$5)^35*$B$6) -> 0 | AP44: =IF($D44="", "", $D44*(1+$B$5)^36*$B$6) -> 0 | AQ44: =IF($D44="", "", $D44*(1+$B$5)^37*$B$6) -> 0 | AR44: =IF($D44="", "", $D44*(1+$B$5)^38*$B$6) -> 0 | AS44: =IF($D44="", "", SUMPRODUCT(E44:AR44, E7:AR7)) -> 0
A45: 27 | B45: ='PO BASIS'!$B$51 -> Beheerskosten | D45: ='PO BASIS'!$K$51 -> 0 | E45: =0 -> 0 | F45: =IF($D45="", "", $D45*(1+$B$5)^0*$B$6) -> 0 | G45: =IF($D45="", "", $D45*(1+$B$5)^1*$B$6) -> 0 | H45: =IF($D45="", "", $D45*(1+$B$5)^2*$B$6) -> 0 | I45: =IF($D45="", "", $D45*(1+$B$5)^3*$B$6) -> 0 | J45: =IF($D45="", "", $D45*(1+$B$5)^4*$B$6) -> 0 | K45: =IF($D45="", "", $D45*(1+$B$5)^5*$B$6) -> 0 | L45: =IF($D45="", "", $D45*(1+$B$5)^6*$B$6) -> 0 | M45: =IF($D45="", "", $D45*(1+$B$5)^7*$B$6) -> 0 | N45: =IF($D45="", "", $D45*(1+$B$5)^8*$B$6) -> 0 | O45: =IF($D45="", "", $D45*(1+$B$5)^9*$B$6) -> 0 | P45: =IF($D45="", "", $D45*(1+$B$5)^10*$B$6) -> 0 | Q45: =IF($D45="", "", $D45*(1+$B$5)^11*$B$6) -> 0 | R45: =IF($D45="", "", $D45*(1+$B$5)^12*$B$6) -> 0 | S45: =IF($D45="", "", $D45*(1+$B$5)^13*$B$6) -> 0 | T45: =IF($D45="", "", $D45*(1+$B$5)^14*$B$6) -> 0 | U45: =IF($D45="", "", $D45*(1+$B$5)^15*$B$6) -> 0 | V45: =IF($D45="", "", $D45*(1+$B$5)^16*$B$6) -> 0 | W45: =IF($D45="", "", $D45*(1+$B$5)^17*$B$6) -> 0 | X45: =IF($D45="", "", $D45*(1+$B$5)^18*$B$6) -> 0 | Y45: =IF($D45="", "", $D45*(1+$B$5)^19*$B$6) -> 0 | Z45: =IF($D45="", "", $D45*(1+$B$5)^20*$B$6) -> 0 | AA45: =IF($D45="", "", $D45*(1+$B$5)^21*$B$6) -> 0 | AB45: =IF($D45="", "", $D45*(1+$B$5)^22*$B$6) -> 0 | AC45: =IF($D45="", "", $D45*(1+$B$5)^23*$B$6) -> 0 | AD45: =IF($D45="", "", $D45*(1+$B$5)^24*$B$6) -> 0 | AE45: =IF($D45="", "", $D45*(1+$B$5)^25*$B$6) -> 0 | AF45: =IF($D45="", "", $D45*(1+$B$5)^26*$B$6) -> 0 | AG45: =IF($D45="", "", $D45*(1+$B$5)^27*$B$6) -> 0 | AH45: =IF($D45="", "", $D45*(1+$B$5)^28*$B$6) -> 0 | AI45: =IF($D45="", "", $D45*(1+$B$5)^29*$B$6) -> 0 | AJ45: =IF($D45="", "", $D45*(1+$B$5)^30*$B$6) -> 0 | AK45: =IF($D45="", "", $D45*(1+$B$5)^31*$B$6) -> 0 | AL45: =IF($D45="", "", $D45*(1+$B$5)^32*$B$6) -> 0 | AM45: =IF($D45="", "", $D45*(1+$B$5)^33*$B$6) -> 0 | AN45: =IF($D45="", "", $D45*(1+$B$5)^34*$B$6) -> 0 | AO45: =IF($D45="", "", $D45*(1+$B$5)^35*$B$6) -> 0 | AP45: =IF($D45="", "", $D45*(1+$B$5)^36*$B$6) -> 0 | AQ45: =IF($D45="", "", $D45*(1+$B$5)^37*$B$6) -> 0 | AR45: =IF($D45="", "", $D45*(1+$B$5)^38*$B$6) -> 0 | AS45: =IF($D45="", "", SUMPRODUCT(E45:AR45, E7:AR7)) -> 0
A46: 28 | B46: ='PO BASIS'!$B$52 -> Financieringskosten | D46: ='PO BASIS'!$K$52 -> 0 | E46: =0 -> 0 | F46: =IF($D46="", "", $D46*(1+$B$5)^0*$B$6) -> 0 | G46: =IF($D46="", "", $D46*(1+$B$5)^1*$B$6) -> 0 | H46: =IF($D46="", "", $D46*(1+$B$5)^2*$B$6) -> 0 | I46: =IF($D46="", "", $D46*(1+$B$5)^3*$B$6) -> 0 | J46: =IF($D46="", "", $D46*(1+$B$5)^4*$B$6) -> 0 | K46: =IF($D46="", "", $D46*(1+$B$5)^5*$B$6) -> 0 | L46: =IF($D46="", "", $D46*(1+$B$5)^6*$B$6) -> 0 | M46: =IF($D46="", "", $D46*(1+$B$5)^7*$B$6) -> 0 | N46: =IF($D46="", "", $D46*(1+$B$5)^8*$B$6) -> 0 | O46: =IF($D46="", "", $D46*(1+$B$5)^9*$B$6) -> 0 | P46: =IF($D46="", "", $D46*(1+$B$5)^10*$B$6) -> 0 | Q46: =IF($D46="", "", $D46*(1+$B$5)^11*$B$6) -> 0 | R46: =IF($D46="", "", $D46*(1+$B$5)^12*$B$6) -> 0 | S46: =IF($D46="", "", $D46*(1+$B$5)^13*$B$6) -> 0 | T46: =IF($D46="", "", $D46*(1+$B$5)^14*$B$6) -> 0 | U46: =IF($D46="", "", $D46*(1+$B$5)^15*$B$6) -> 0 | V46: =IF($D46="", "", $D46*(1+$B$5)^16*$B$6) -> 0 | W46: =IF($D46="", "", $D46*(1+$B$5)^17*$B$6) -> 0 | X46: =IF($D46="", "", $D46*(1+$B$5)^18*$B$6) -> 0 | Y46: =IF($D46="", "", $D46*(1+$B$5)^19*$B$6) -> 0 | Z46: =IF($D46="", "", $D46*(1+$B$5)^20*$B$6) -> 0 | AA46: =IF($D46="", "", $D46*(1+$B$5)^21*$B$6) -> 0 | AB46: =IF($D46="", "", $D46*(1+$B$5)^22*$B$6) -> 0 | AC46: =IF($D46="", "", $D46*(1+$B$5)^23*$B$6) -> 0 | AD46: =IF($D46="", "", $D46*(1+$B$5)^24*$B$6) -> 0 | AE46: =IF($D46="", "", $D46*(1+$B$5)^25*$B$6) -> 0 | AF46: =IF($D46="", "", $D46*(1+$B$5)^26*$B$6) -> 0 | AG46: =IF($D46="", "", $D46*(1+$B$5)^27*$B$6) -> 0 | AH46: =IF($D46="", "", $D46*(1+$B$5)^28*$B$6) -> 0 | AI46: =IF($D46="", "", $D46*(1+$B$5)^29*$B$6) -> 0 | AJ46: =IF($D46="", "", $D46*(1+$B$5)^30*$B$6) -> 0 | AK46: =IF($D46="", "", $D46*(1+$B$5)^31*$B$6) -> 0 | AL46: =IF($D46="", "", $D46*(1+$B$5)^32*$B$6) -> 0 | AM46: =IF($D46="", "", $D46*(1+$B$5)^33*$B$6) -> 0 | AN46: =IF($D46="", "", $D46*(1+$B$5)^34*$B$6) -> 0 | AO46: =IF($D46="", "", $D46*(1+$B$5)^35*$B$6) -> 0 | AP46: =IF($D46="", "", $D46*(1+$B$5)^36*$B$6) -> 0 | AQ46: =IF($D46="", "", $D46*(1+$B$5)^37*$B$6) -> 0 | AR46: =IF($D46="", "", $D46*(1+$B$5)^38*$B$6) -> 0 | AS46: =IF($D46="", "", SUMPRODUCT(E46:AR46, E7:AR7)) -> 0
A47: 29 | B47: ='PO BASIS'!$B$53 -> Schoonmaakkosten | D47: ='PO BASIS'!$K$53 -> 13.58 | E47: =0 -> 0 | F47: =IF($D47="", "", $D47*(1+$B$5)^0*$B$6) -> 0 | G47: =IF($D47="", "", $D47*(1+$B$5)^1*$B$6) -> 0 | H47: =IF($D47="", "", $D47*(1+$B$5)^2*$B$6) -> 0 | I47: =IF($D47="", "", $D47*(1+$B$5)^3*$B$6) -> 0 | J47: =IF($D47="", "", $D47*(1+$B$5)^4*$B$6) -> 0 | K47: =IF($D47="", "", $D47*(1+$B$5)^5*$B$6) -> 0 | L47: =IF($D47="", "", $D47*(1+$B$5)^6*$B$6) -> 0 | M47: =IF($D47="", "", $D47*(1+$B$5)^7*$B$6) -> 0 | N47: =IF($D47="", "", $D47*(1+$B$5)^8*$B$6) -> 0 | O47: =IF($D47="", "", $D47*(1+$B$5)^9*$B$6) -> 0 | P47: =IF($D47="", "", $D47*(1+$B$5)^10*$B$6) -> 0 | Q47: =IF($D47="", "", $D47*(1+$B$5)^11*$B$6) -> 0 | R47: =IF($D47="", "", $D47*(1+$B$5)^12*$B$6) -> 0 | S47: =IF($D47="", "", $D47*(1+$B$5)^13*$B$6) -> 0 | T47: =IF($D47="", "", $D47*(1+$B$5)^14*$B$6) -> 0 | U47: =IF($D47="", "", $D47*(1+$B$5)^15*$B$6) -> 0 | V47: =IF($D47="", "", $D47*(1+$B$5)^16*$B$6) -> 0 | W47: =IF($D47="", "", $D47*(1+$B$5)^17*$B$6) -> 0 | X47: =IF($D47="", "", $D47*(1+$B$5)^18*$B$6) -> 0 | Y47: =IF($D47="", "", $D47*(1+$B$5)^19*$B$6) -> 0 | Z47: =IF($D47="", "", $D47*(1+$B$5)^20*$B$6) -> 0 | AA47: =IF($D47="", "", $D47*(1+$B$5)^21*$B$6) -> 0 | AB47: =IF($D47="", "", $D47*(1+$B$5)^22*$B$6) -> 0 | AC47: =IF($D47="", "", $D47*(1+$B$5)^23*$B$6) -> 0 | AD47: =IF($D47="", "", $D47*(1+$B$5)^24*$B$6) -> 0 | AE47: =IF($D47="", "", $D47*(1+$B$5)^25*$B$6) -> 0 | AF47: =IF($D47="", "", $D47*(1+$B$5)^26*$B$6) -> 0 | AG47: =IF($D47="", "", $D47*(1+$B$5)^27*$B$6) -> 0 | AH47: =IF($D47="", "", $D47*(1+$B$5)^28*$B$6) -> 0 | AI47: =IF($D47="", "", $D47*(1+$B$5)^29*$B$6) -> 0 | AJ47: =IF($D47="", "", $D47*(1+$B$5)^30*$B$6) -> 0 | AK47: =IF($D47="", "", $D47*(1+$B$5)^31*$B$6) -> 0 | AL47: =IF($D47="", "", $D47*(1+$B$5)^32*$B$6) -> 0 | AM47: =IF($D47="", "", $D47*(1+$B$5)^33*$B$6) -> 0 | AN47: =IF($D47="", "", $D47*(1+$B$5)^34*$B$6) -> 0 | AO47: =IF($D47="", "", $D47*(1+$B$5)^35*$B$6) -> 0 | AP47: =IF($D47="", "", $D47*(1+$B$5)^36*$B$6) -> 0 | AQ47: =IF($D47="", "", $D47*(1+$B$5)^37*$B$6) -> 0 | AR47: =IF($D47="", "", $D47*(1+$B$5)^38*$B$6) -> 0 | AS47: =IF($D47="", "", SUMPRODUCT(E47:AR47, E7:AR7)) -> 0
F48: =IF($D48="", "", IF(1>=2, $D48*(1+$B$5)^0*$B$6, 0)) | G48: =IF($D48="", "", IF(2>=2, $D48*(1+$B$5)^1*$B$6, 0)) | H48: =IF($D48="", "", IF(3>=2, $D48*(1+$B$5)^2*$B$6, 0)) | I48: =IF($D48="", "", IF(4>=2, $D48*(1+$B$5)^3*$B$6, 0)) | J48: =IF($D48="", "", IF(5>=2, $D48*(1+$B$5)^4*$B$6, 0)) | K48: =IF($D48="", "", IF(6>=2, $D48*(1+$B$5)^5*$B$6, 0)) | L48: =IF($D48="", "", IF(7>=2, $D48*(1+$B$5)^6*$B$6, 0)) | M48: =IF($D48="", "", IF(8>=2, $D48*(1+$B$5)^7*$B$6, 0)) | N48: =IF($D48="", "", IF(9>=2, $D48*(1+$B$5)^8*$B$6, 0)) | O48: =IF($D48="", "", IF(10>=2, $D48*(1+$B$5)^9*$B$6, 0)) | P48: =IF($D48="", "", IF(11>=2, $D48*(1+$B$5)^10*$B$6, 0)) | Q48: =IF($D48="", "", IF(12>=2, $D48*(1+$B$5)^11*$B$6, 0)) | R48: =IF($D48="", "", IF(13>=2, $D48*(1+$B$5)^12*$B$6, 0)) | S48: =IF($D48="", "", IF(14>=2, $D48*(1+$B$5)^13*$B$6, 0)) | T48: =IF($D48="", "", IF(15>=2, $D48*(1+$B$5)^14*$B$6, 0)) | U48: =IF($D48="", "", IF(16>=2, $D48*(1+$B$5)^15*$B$6, 0)) | V48: =IF($D48="", "", IF(17>=2, $D48*(1+$B$5)^16*$B$6, 0)) | W48: =IF($D48="", "", IF(18>=2, $D48*(1+$B$5)^17*$B$6, 0)) | X48: =IF($D48="", "", IF(19>=2, $D48*(1+$B$5)^18*$B$6, 0)) | Y48: =IF($D48="", "", IF(20>=2, $D48*(1+$B$5)^19*$B$6, 0)) | Z48: =IF($D48="", "", IF(21>=2, $D48*(1+$B$5)^20*$B$6, 0)) | AA48: =IF($D48="", "", IF(22>=2, $D48*(1+$B$5)^21*$B$6, 0)) | AB48: =IF($D48="", "", IF(23>=2, $D48*(1+$B$5)^22*$B$6, 0)) | AC48: =IF($D48="", "", IF(24>=2, $D48*(1+$B$5)^23*$B$6, 0)) | AD48: =IF($D48="", "", IF(25>=2, $D48*(1+$B$5)^24*$B$6, 0)) | AE48: =IF($D48="", "", IF(26>=2, $D48*(1+$B$5)^25*$B$6, 0)) | AF48: =IF($D48="", "", IF(27>=2, $D48*(1+$B$5)^26*$B$6, 0)) | AG48: =IF($D48="", "", IF(28>=2, $D48*(1+$B$5)^27*$B$6, 0)) | AH48: =IF($D48="", "", IF(29>=2, $D48*(1+$B$5)^28*$B$6, 0)) | AI48: =IF($D48="", "", IF(30>=2, $D48*(1+$B$5)^29*$B$6, 0)) | AJ48: =IF($D48="", "", IF(31>=2, $D48*(1+$B$5)^30*$B$6, 0)) | AK48: =IF($D48="", "", IF(32>=2, $D48*(1+$B$5)^31*$B$6, 0)) | AL48: =IF($D48="", "", IF(33>=2, $D48*(1+$B$5)^32*$B$6, 0)) | AM48: =IF($D48="", "", IF(34>=2, $D48*(1+$B$5)^33*$B$6, 0)) | AN48: =IF($D48="", "", IF(35>=2, $D48*(1+$B$5)^34*$B$6, 0)) | AO48: =IF($D48="", "", IF(36>=2, $D48*(1+$B$5)^35*$B$6, 0)) | AP48: =IF($D48="", "", IF(37>=2, $D48*(1+$B$5)^36*$B$6, 0)) | AQ48: =IF($D48="", "", IF(38>=2, $D48*(1+$B$5)^37*$B$6, 0)) | AR48: =IF($D48="", "", IF(39>=2, $D48*(1+$B$5)^38*$B$6, 0)) | AS48: =IF($D48="", "", SUMPRODUCT(E48:AR48, E7:AR7))
AS49: =SUM(AS9:AS47) -> 0
A50: TOTALS | E50: =SUM(E9:E49) -> 0 | F50: =SUM(F9:F49) -> 0 | G50: =SUM(G9:G49) -> 0 | H50: =SUM(H9:H49) -> 0 | I50: =SUM(I9:I49) -> 0 | J50: =SUM(J9:J49) -> 0 | K50: =SUM(K9:K49) -> 0 | L50: =SUM(L9:L49) -> 0 | ... AR50: =SUM(AR9:AR49) -> 0 | AS50: =SUM(F50:AR50) -> 0
